Workbook
Name C_RATE: Summary!$F$3
Name P_RATE: Summary!$G$3

Sheet Summary
C2: 46142 | L2: 3.4239533e+09 | M2: 2286812.8 | P2: =8000000/12 -> 666666.67 | AA2: 622.94867
D3: =-D12/D8 -> 0.44573318 | F3: =INDEX('FX Rate'!$B$3:$ZZ$8,5,MATCH(Summary!F$6,'FX Rate'!$B$3:$ZZ$3)) -> 1374.55 | G3: =INDEX('FX Rate'!$B$3:$ZZ$8,5,MATCH(Summary!G$6,'FX Rate'!$B$3:$ZZ$3)) -> 1601.9 | L3: =-L12/L8 -> 0.55254625 | M3: =M2-N8 -> 562255.83 | N3: =C_RATE -> 1374.55 | O3: =G3 -> 1601.9 | AA3: =N8-AA2 -> 1723934
C4: NIGERIA INCOME STATEMENT | K4: GROUP INCOME STATEMENT | R4: Target | U4: SEGMENTED INCOME STATEMENT (USD) | AF4: Ratios | AG4: CONSULTING | AH4: PRODUCT-FIXIAM | AI4: GROUP TOTAL | AO4: Sep'25 YTD | AP4: Bridge | AQ4: FY 2025 Exit | AX4: Item | AY4: USD | BC4: SEGMENTED INCOME STATEMENT (NGN)
C5: Income Statement | D5: YTD | E5: YTD | F5: =D5 -> YTD | G5: =E5 -> YTD | H5: Variance (%) | K5: Income Statement | L5: YTD | M5: YTD | N5: =L5 -> YTD | O5: =M5 -> YTD | P5: Variance (%) | V5: PUBLIC SECTOR | W5: TELCO | X5: VERIFY | Y5: OTHERS | Z5: CONSULTING | AA5: PRODUCT-FIXIAM | AB5: GROUP TOTAL | AF5: Gross Profit Margin | AG5: =Z9 -> 0.44375507 | AH5: =AA9 -> -113.29788 | AI5: =AB9 -> 0.42815559 | AN5: Revenue | AO5: =AB6 -> 1076068.8 | AP5: =AQ5-AO5 -> 5062293.2 | AQ5: 6138362 | AR5: $5.1m incremental revenue to bridge revenue gap which si | AX5: Revenue | AY5: =Z6 -> 1075921.2 | BD5: PUBLIC SECTOR | BE5: TELCO | BF5: VERIFY | BG5: OTHERS | BH5: CONSULTING | BI5: PRODUCT-FIXIAM | BJ5: GROUP TOTAL
D6: =C2 -> 46142 | E6: =EOMONTH(D6,-12) -> 45777 | F6: =D6 -> 46142 | G6: =E6 -> 45777 | L6: =$C$2 -> 46142 | M6: =EOMONTH(L6,-12) -> 45777 | N6: =L6 -> 46142 | O6: =M6 -> 45777 | S6: =R8/12*4 -> 1666666.7 | T6: =R9/12*4 -> 2666666.7 | U6: Revenue | V6: =N25 -> 805513.66 | W6: =N24 -> 265137.43 | X6: =N23 -> 4661.0739 | Y6: =N26 -> 609.07883 | Z6: =SUM(V6:Y6) -> 1075921.2 | AA6: =L27/C_RATE -> 147.58112 | AB6: =Z6+AA6 -> 1076068.8 | AC6: =N8 -> 1724556.9 | AD6: =AB6-AC6 -> -648488.11 | AE6: =Z6*C_RATE -> 1.4789075e+09 | AF6: EBITDA Margin | AG6: =Z20 -> 0 | AH6: =AA20 -> 0 | AI6: =AB20 -> 0 | AN6: Cost | AO6: =AO7-AO5 -> -1076068.8 | AP6: =AQ6-AO6 -> -4141046.2 | AQ6: -5217115 | AR6: Budgeted opex and 30% cost of sales provision | AX6: Cost of Sales | AY6: =Z7 -> -598475.73 | BC6: Revenue | BD6: =V6*C_RATE -> 1.1072188e+09 | BE6: =W6*C_RATE -> 3.6444465e+08 | BF6: =X6*C_RATE -> 6406879.1 | BG6: =Y6*C_RATE -> 837209.3 | BH6: =SUM(BD6:BG6) -> 1.4789075e+09 | BI6: =AA6*C_RATE -> 202857.63 | BJ6: =BH6+BI6 -> 1.4791104e+09
D7: NGN | E7: NGN | F7: USD | G7: USD | L7: NGN | M7: NGN | N7: USD | O7: USD | S7: =N8/S6 -> 1.0347342 | T7: =N8/T6 -> 0.64670885 | U7: Direct Expenses | V7: ='Segment Report'!Z5 -> -157852.81 | W7: ='Segment Report'!AA5 -> -351581.99 | X7: ='Segment Report'!AB5 -> -54815.184 | Y7: ='Segment Report'!AC5 -> -34225.743 | Z7: =SUM(V7:Y7) -> -598475.73 | AA7: ='Segment Report'!X5 -> -16868.209 | AB7: =Z7+AA7 -> -615343.94 | AC7: =N9 -> -375233.15 | AD7: =AB7-AC7 -> -240110.79 | AE7: =Z7*C_RATE -> -8.2263481e+08 | AF7: Net Income Margin | AG7: =Z16 -> -1.3364953 | AH7: =AA16 -> -11219.184 | AI7: =AB16 -> -2.8750051 | AN7: EBITDA | AO7: =AB21 -> 0 | AP7: =AQ7-AO7 -> 921247 | AQ7: 921247 | AX7: Gross Profit | AY7: =AY5+AY6 -> 477445.51 | BC7: Direct Expenses | BD7: =V7*C_RATE -> -2.1697658e+08 | BE7: =W7*C_RATE -> -4.8326702e+08 | BF7: =X7*C_RATE -> -75346211 | BG7: =Y7*C_RATE -> -47044995 | BH7: =SUM(BD7:BG7) -> -8.2263481e+08 | BI7: =AA7*C_RATE -> -23186197 | BJ7: =BH7+BI7 -> -8.4582101e+08
B8: TOTAL REVENUE | C8: =PROPER(PL_NG!C19) -> Total Revenue | D8: =SUMIFS( INDEX(NG!C:AL, MATCH($B8, NG!$B:$B, 0), ), NG!$C$3:$AL$3, ">="&DATE(YEAR($C$2),1,1), NG!$C$3:$AL$3, "<="&$C$2 ) -> 2.36368e+09 | E8: =SUMIFS( INDEX(NG!C:AL, MATCH($B8, NG!$B:$B, 0), ), NG!$C$3:$AL$3, ">="&DATE(YEAR($C$2)-1,1,1), NG!$C$3:$AL$3, "<="&EDATE($C$2,-12) ) -> 8.7542054e+08 | F8: =D8/$F$3 -> 1719602.7 | G8: =E8/$G$3 -> 546488.88 | H8: =IFERROR(D8/E8-1,0) -> 1.7000508 | K8: Total Revenue | L8: =SUMIFS( INDEX(Group!C:AL, MATCH($B8, Group!$B:$B, 0), ), Group!$C$3:$AL$3, ">="&DATE(YEAR($C$2),1,1), Group!$C$3:$AL$3, "<="&$C$2 ) -> 2.3704897e+09 | M8: =SUMIFS( INDEX(Group!C:AL, MATCH($B8, Group!$B:$B, 0), ), Group!$C$3:$AL$3, ">="&DATE(YEAR($C$2)-1,1,1), Group!$C$3:$AL$3, "<="&EDATE($C$2,-12) ) -> 9.316079e+08 | N8: =L8/$F$3 -> 1724556.9 | O8: =M8/$G$3 -> 581564.33 | P8: =IFERROR(L8/M8-1,0) -> 1.5445144 | Q8: =L8-M8 -> 1.4388818e+09 | R8: =5000000 -> 5000000 | S8: =N8/R8 -> 0.34491139 | T8: =R8-N8 -> 3275443.1 | U8: Contribution per product | V8: =V6+V7 -> 647660.84 | W8: =W6+W7 -> -86444.561 | X8: =X6+X7 -> -50154.11 | Y8: =Y6+Y7 -> -33616.664 | Z8: =Z6+Z7 -> 477445.51 | AA8: =AA6+AA7 -> -16720.628 | AB8: =AB6+AB7 -> 460724.88 | AE8: =Z8*C_RATE -> 6.5627272e+08 | AF8: Payroll Expense | AG8: =-'Segment Report'!Y7 -> 254958.18 | AH8: =-'Segment Report'!X7 -> 397957.54 | AI8: =AG8+AH8 -> 652915.73 | AN8: EBITDA Margin | AO8: =AO7/AO5 -> 0 | AP8: =AP7/AP5 -> 0.18198215 | AQ8: =AQ7/AQ5 -> 0.15008027 | AX8: Gross Margin | AY8: =AY7/AY5 -> 0.44375507 | BC8: Contribution per product | BD8: =BD6+BD7 -> 8.9024221e+08 | BE8: =BE6+BE7 -> -1.1882237e+08 | BF8: =BF6+BF7 -> -68939332 | BG8: =BG6+BG7 -> -46207785 | BH8: =BH6+BH7 -> 6.5627272e+08 | BI8: =BI6+BI7 -> -22983339 | BJ8: =BJ6+BJ7 -> 6.3328938e+08 | BN8: 510 | BO8: 81600000 | BQ8: =T8/8 -> 409430.38
B9: TOTAL COST OF SALES | C9: Cost of Sales | D9: =SUMIFS( INDEX(NG!C:AL, MATCH($B9, NG!$B:$B, 0), ), NG!$C$3:$AL$3, ">="&DATE(YEAR($C$2),1,1), NG!$C$3:$AL$3, "<="&$C$2 ) -> -5.0525847e+08 | E9: =SUMIFS( INDEX(NG!C:AL, MATCH($B9, NG!$B:$B, 0), ), NG!$C$3:$AL$3, ">="&DATE(YEAR($C$2)-1,1,1), NG!$C$3:$AL$3, "<="&EDATE($C$2,-12) ) -> -2.3859699e+08 | F9: =D9/$F$3 -> -367581 | G9: =E9/$G$3 -> -148946.24 | H9: =IFERROR(D9/E9-1,0) -> 1.117623 | K9: Cost of Sales | L9: =SUMIFS( INDEX(Group!C:AL, MATCH($B9, Group!$B:$B, 0), ), Group!$C$3:$AL$3, ">="&DATE(YEAR($C$2),1,1), Group!$C$3:$AL$3, "<="&$C$2 ) -> -5.1577673e+08 | M9: =SUMIFS( INDEX(Group!C:AL, MATCH($B9, Group!$B:$B, 0), ), Group!$C$3:$AL$3, ">="&DATE(YEAR($C$2)-1,1,1), Group!$C$3:$AL$3, "<="&EDATE($C$2,-12) ) -> -2.5840061e+08 | N9: =L9/$F$3 -> -375233.15 | O9: =M9/$G$3 -> -161308.83 | P9: =IFERROR(L9/M9-1,0) -> 0.99603521 | Q9: =L9-M9 -> -2.5737611e+08 | R9: =8000000 -> 8000000 | S9: =N8/R9 -> 0.21556962 | T9: =R9-N8 -> 6275443.1 | U9: Contribution margin % | V9: =IFERROR(V8/V6,"") -> 0.80403459 | W9: =IFERROR(W8/W6,"") -> -0.32603681 | X9: =IFERROR(X8/X6,"") -> -10.760205 | Y9: =IFERROR(Y8/Y6,"") -> -55.192633 | Z9: =IFERROR(Z8/Z6,"") -> 0.44375507 | AA9: =IFERROR(AA8/AA6,"n/a") -> -113.29788 | AB9: =IFERROR(AB8/AB6,"") -> 0.42815559 | AE9: =Z9*C_RATE -> 609.96354 | AF9: Payroll % of Revenue | AG9: =AG8/Z6 -> 0.23696733 | AH9: =IFERROR(AH8/AA6,"n/a") -> 2696.5343 | AI9: =AI8/AB6 -> 0.60676019 | AX9: Other Revenue | AY9: =Z10 -> -134423.63 | BC9: Contribution margin % | BD9: =IFERROR(BD8/BD6,"") -> 0.80403459 | BE9: =IFERROR(BE8/BE6,"") -> -0.32603681 | BF9: =IFERROR(BF8/BF6,"") -> -10.760205 | BG9: =IFERROR(BG8/BG6,"") -> -55.192633 | BH9: =IFERROR(BH8/BH6,"") -> 0.44375507 | BI9: =IFERROR(BI8/BI6,"n/a") -> -113.29788 | BJ9: =IFERROR(BJ8/BJ6,"") -> 0.42815559 | BO9: =BO8/BN8 -> 160000 | BQ9: =T9/8 -> 784430.38
C10: Gross Profit | D10: =D8+D9 -> 1.8584215e+09 | E10: =E8+E9 -> 6.3682356e+08 | F10: =F8+F9 -> 1352021.7 | G10: =G8+G9 -> 397542.64 | H10: =IFERROR(D10/E10-1,0) -> 1.9182675 | K10: Gross Profit | L10: =L8+L9 -> 1.854713e+09 | M10: =M8+M9 -> 6.7320728e+08 | N10: =N8+N9 -> 1349323.8 | O10: =O8+O9 -> 420255.5 | P10: =IFERROR(L10/M10-1,0) -> 1.75504 | Q10: =L10-M10 -> 1.1815057e+09 | U10: Other income | V10: ='Segment Report'!Z6 -> -100639.41 | W10: ='Segment Report'!AA6 -> -33125.786 | X10: ='Segment Report'!AB6 -> -582.34606 | Y10: ='Segment Report'!AC6 -> -76.097196 | Z10: =SUM(V10:Y10) -> -134423.63 | AA10: ='Segment Report'!X6 -> 187121.98 | AB10: =Z10+AA10 -> 52698.344 | AC10: =N11 -> 52698.344 | AD10: =AB10-AC10 -> 0 | AE10: =Z10*C_RATE -> -1.8477201e+08 | AF10: Employee Count | AG10: =L71-AH10 -> -8 | AH10: 8 | AI10: =AG10+AH10 -> 0 | AP10: Target | AQ10: 0.15 | AX10: Operating Expenses | AY10: =SUM('Segment Report'!Y7:Y15,'Segment Report'!Y16) -> -448237.54 | BC10: Other income | BD10: =V10*C_RATE -> -1.3833389e+08 | BE10: =W10*C_RATE -> -45533049 | BF10: =X10*C_RATE -> -800463.77 | BG10: =Y10*C_RATE -> -104599.4 | BH10: =SUM(BD10:BG10) -> -1.8477201e+08 | BI10: =AA10*C_RATE -> 2.5720852e+08 | BJ10: =BH10+BI10 -> 72436509
B11: TOTAL OTHER REVENUE | C11: Other Income | D11: =SUMIFS( INDEX(NG!C:AL, MATCH($B11, NG!$B:$B, 0), ), NG!$C$3:$AL$3, ">="&DATE(YEAR($C$2),1,1), NG!$C$3:$AL$3, "<="&$C$2 ) -> 72436509 | E11: =SUMIFS( INDEX(NG!C:AL, MATCH($B11, NG!$B:$B, 0), ), NG!$C$3:$AL$3, ">="&DATE(YEAR($C$2)-1,1,1), NG!$C$3:$AL$3, "<="&EDATE($C$2,-12) ) -> 1.2825463e+08 | F11: =D11/$F$3 -> 52698.344 | G11: =E11/$G$3 -> 80064.068 | H11: =IFERROR(D11/E11-1,0) -> -0.4352133 | K11: Other Income | L11: =SUMIFS( INDEX(Group!C:AL, MATCH($B11, Group!$B:$B, 0), ), Group!$C$3:$AL$3, ">="&DATE(YEAR($C$2),1,1), Group!$C$3:$AL$3, "<="&$C$2 ) -> 72436509 | M11: =SUMIFS( INDEX(Group!C:AL, MATCH($B11, Group!$B:$B, 0), ), Group!$C$3:$AL$3, ">="&DATE(YEAR($C$2)-1,1,1), Group!$C$3:$AL$3, "<="&EDATE($C$2,-12) ) -> 1.2825828e+08 | N11: =L11/$F$3 -> 52698.344 | O11: =M11/$G$3 -> 80066.349 | P11: =IFERROR(L11/M11-1,0) -> -0.4352294 | Q11: =L11-M11 -> -55821776 | U11: Operating Expenses | V11: =-'Segment Report'!E16/C_RATE -> -768980.96 | W11: =-'Segment Report'!F16/C_RATE -> -893225.65 | X11: =-'Segment Report'!G16/C_RATE -> -41120.557 | Y11: =-'Segment Report'!H16/C_RATE -> -27127.99 | Z11: =SUM(V11:Y11) -> -1730455.2 | AA11: =-'Segment Report'!I16/C_RATE -> -1621394.8 | AB11: =Z11+AA11 -> -3351849.9 | AC11: =N12 -> -952897.47 | AD11: =AB11-AC11 -> -2398952.5 | AE11: =Z11*C_RATE -> -2.3785971e+09 | AF11: Average Revenue per Employee | AG11: =Z6/AG10/MONTH(C2) -> -33622.539 | AH11: n/a | AI11: =AB6/AI10/MONTH(C2) -> #DIV/0! | AN11: Total budget | AO11: 6560351823 | AX11: EBITDA | AY11: =AY7+AY9+AY10 -> -105215.67 | BC11: Operating Expenses | BD11: =V11*C_RATE -> -1057002780 | BE11: =W11*C_RATE -> -1227783317 | BF11: =X11*C_RATE -> -56522261 | BG11: =Y11*C_RATE -> -37288779 | BH11: =SUM(BD11:BG11) -> -2378597137 | BI11: =AA11*C_RATE -> -2228688178 | BJ11: =BH11+BI11 -> -4607285315
B12: TOTAL OPERATING EXPENSES | C12: Total Operating Expenses | D12: =SUMIFS( INDEX(NG!C:AL, MATCH($B12, NG!$B:$B, 0), ), NG!$C$3:$AL$3, ">="&DATE(YEAR($C$2),1,1), NG!$C$3:$AL$3, "<="&$C$2 ) -> -1.0535706e+09 | E12: =SUMIFS( INDEX(NG!C:AL, MATCH($B12, NG!$B:$B, 0), ), NG!$C$3:$AL$3, ">="&DATE(YEAR($C$2)-1,1,1), NG!$C$3:$AL$3, "<="&EDATE($C$2,-12) ) -> -6.9973042e+08 | F12: =D12/$F$3 -> -766484.01 | G12: =E12/$G$3 -> -436812.8 | H12: =IFERROR(D12/E12-1,0) -> 0.50568071 | K12: Total Operating Expenses | L12: =SUMIFS( INDEX(Group!C:AL, MATCH($B12, Group!$B:$B, 0), ), Group!$C$3:$AL$3, ">="&DATE(YEAR($C$2),1,1), Group!$C$3:$AL$3, "<="&$C$2 ) -> -1.3098052e+09 | M12: =SUMIFS( INDEX(Group!C:AL, MATCH($B12, Group!$B:$B, 0), ), Group!$C$3:$AL$3, ">="&DATE(YEAR($C$2)-1,1,1), Group!$C$3:$AL$3, "<="&EDATE($C$2,-12) ) -> -1.0454146e+09 | N12: =L12/$F$3 -> -952897.47 | O12: =M12/$G$3 -> -652609.13 | P12: =IFERROR(L12/M12-1,0) -> 0.25290507 | Q12: =L12-M12 -> -2.6439065e+08 | R12: =L12+PL_NG!AB38+PL_NG!AB39+PL_NG!AB28+PL_NG!AB34+PL_NG!AB30 -> -1.3771453e+09 | S12: =R12/N3 -> -1001888.1 | U12: EBITDA | V12: =V8+V10+V11 -> -221959.52 | W12: =W8+W10+W11 -> -1012796 | X12: =X8+X10+X11 -> -91857.013 | Y12: =Y8+Y10+Y11 -> -60820.751 | Z12: =Z8+Z10+Z11 -> -1387433.3 | AA12: =AA8+AA10+AA11 -> -1450993.4 | AB12: =AB8+AB10+AB11 -> -2838426.7 | AN12: Capex | AO12: 833331500 | AX12: EBITDA Margin | AY12: =AY11/AY5 -> -0.097791234 | BC12: EBITDA | BD12: =BD8+BD10+BD11 -> -3.0509446e+08 | BE12: =BE8+BE10+BE11 -> -1.3921387e+09 | BF12: =BF8+BF10+BF11 -> -1.2626206e+08 | BG12: =BG8+BG10+BG11 -> -83601164 | BH12: =BH8+BH10+BH11 -> -1.9070964e+09 | BI12: =BI8+BI10+BI11 -> -1.994463e+09 | BJ12: =BJ8+BJ10+BJ11 -> -3.9015594e+09
C13: EBITDA | D13: =D10+D11+D12 -> 8.7728741e+08 | E13: =E10+E11+E12 -> 65347768 | F13: =F10+F11+F12 -> 638236.08 | G13: =G10+G11+G12 -> 40793.912 | H13: =IFERROR(D13/E13-1,0) -> 12.424902 | K13: EBITDA | L13: =L10+L11+L12 -> 6.173443e+08 | M13: =M10+M11+M12 -> -2.43949e+08 | N13: =N10+N11+N12 -> 449124.66 | O13: =O10+O11+O12 -> -152287.28 | P13: =IFERROR(L13/M13-1,0) -> -3.5306285 | Q13: =L13-M13 -> 8.6129329e+08 | U13: EBITDA Margin | V13: =V12/V6 -> -0.27555029 | W13: =W12/W6 -> -3.8198907 | X13: =X12/X6 -> -19.707264 | Y13: =Y12/Y6 -> -99.856946 | Z13: =Z12/Z6 -> -1.2895305 | AA13: =AA12/AA6 -> -9831.8365 | AB13: =AB12/AB6 -> -2.6377743 | AF13: Common Size Analysis | AO13: 5727020323 | AX13: Dep, Int & Taxes | AY13: ='Segment Report'!Y17+'Segment Report'!Y18+'Segment Report'!Y19+'Segment Report'!Y20 -> -35392.781 | BC13: EBITDA Margin | BD13: =BD12/BD6 -> -0.27555029 | BE13: =BE12/BE6 -> -3.8198907 | BF13: =BF12/BF6 -> -19.707264 | BG13: =BG12/BG6 -> -99.856946 | BH13: =BH12/BH6 -> -1.2895305 | BI13: =BI12/BI6 -> -9831.8365 | BJ13: =BJ12/BJ6 -> -2.6377743
B14: TOTAL DEPRECIATION & AMORTISATION | C14: Depreciation & Amortisation | D14: =SUMIFS( INDEX(NG!C:AL, MATCH($B14, NG!$B:$B, 0), ), NG!$C$3:$AL$3, ">="&DATE(YEAR($C$2),1,1), NG!$C$3:$AL$3, "<="&$C$2 ) -> -48860521 | E14: =SUMIFS( INDEX(NG!C:AL, MATCH($B14, NG!$B:$B, 0), ), NG!$C$3:$AL$3, ">="&DATE(YEAR($C$2)-1,1,1), NG!$C$3:$AL$3, "<="&EDATE($C$2,-12) ) -> -19017580 | F14: =D14/$F$3 -> -35546.558 | G14: =E14/$G$3 -> -11871.89 | H14: =IFERROR(D14/E14-1,0) -> 1.5692292 | K14: Depreciation & Amortisation | L14: =SUMIFS( INDEX(Group!C:AL, MATCH($B14, Group!$B:$B, 0), ), Group!$C$3:$AL$3, ">="&DATE(YEAR($C$2),1,1), Group!$C$3:$AL$3, "<="&$C$2 ) -> -49839069 | M14: =SUMIFS( INDEX(Group!C:AL, MATCH($B14, Group!$B:$B, 0), ), Group!$C$3:$AL$3, ">="&DATE(YEAR($C$2)-1,1,1), Group!$C$3:$AL$3, "<="&EDATE($C$2,-12) ) -> -20067919 | N14: =L14/$F$3 -> -36258.462 | O14: =M14/$G$3 -> -12527.573 | P14: =IFERROR(L14/M14-1,0) -> 1.4835196 | Q14: =L14-M14 -> -29771150 | U14: Depreciation, Interest Expense & Tax | V14: =-'Segment Report'!E21/C_RATE -> -21474.355 | W14: =-'Segment Report'!F21/C_RATE -> -22845.713 | X14: =-'Segment Report'!G21/C_RATE -> -5541.4339 | Y14: =-'Segment Report'!H21/C_RATE -> -668.91492 | Z14: =SUM(V14:Y14) -> -50530.416 | AA14: =-'Segment Report'!I21/C_RATE -> -204746.25 | AB14: =Z14+AA14 -> -255276.66 | AC14: =N14+N16+N18 -> -36258.462 | AD14: =AB14-AC14 -> -219018.2 | AF14: as a % of Revenue | AO14: 3694851.8 | AX14: NI | AY14: =AY11+AY13 -> -140608.45 | BC14: Depreciation & Interest Expense | BD14: =V14*C_RATE -> -29517574 | BE14: =W14*C_RATE -> -31402575 | BF14: =X14*C_RATE -> -7616978 | BG14: =Y14*C_RATE -> -919457 | BH14: =SUM(BD14:BG14) -> -69456584 | BI14: =AA14*C_RATE -> -281433954 | BJ14: =BH14+BI14 -> -350890538 | BK14: =L14+L16+L18 -> -49839069
C15: EBIT | D15: =D13+D14 -> 8.2842688e+08 | E15: =E13+E14 -> 46330188 | F15: =F13+F14 -> 602689.52 | G15: =G13+G14 -> 28922.023 | H15: =IFERROR(D15/E15-1,0) -> 16.880931 | K15: EBIT | L15: =L13+L14 -> 5.6750523e+08 | M15: =M13+M14 -> -2.6401692e+08 | N15: =N13+N14 -> 412866.19 | O15: =O13+O14 -> -164814.85 | P15: =IFERROR(L15/M15-1,0) -> -3.1495033 | Q15: =L15-M15 -> 8.3152214e+08 | U15: Profit or Loss | V15: =V12+V14 -> -243433.88 | W15: =W12+W14 -> -1035641.7 | X15: =X12+X14 -> -97398.447 | Y15: =Y12+Y14 -> -61489.666 | Z15: =Z12+Z14 -> -1437963.7 | AA15: =AA12+AA14 -> -1655739.7 | AB15: =AB12+AB14 -> -3093703.4 | AE15: =Z15*C_RATE -> -1.976553e+09 | AF15: Cost of Sales | AG15: =-Z9 -> -0.44375507 | AH15: =AA9 -> -113.29788 | AI15: =AB9 -> 0.42815559 | AX15: Net Margin | AY15: =AY14/AY5 -> -0.13068656 | BC15: Profit or Loss | BD15: =BD12+BD14 -> -3.3461204e+08 | BE15: =BE12+BE14 -> -1.4235413e+09 | BF15: =BF12+BF14 -> -1.3387903e+08 | BG15: =BG12+BG14 -> -84520621 | BH15: =BH12+BH14 -> -1.976553e+09 | BI15: =BI12+BI14 -> -2.275897e+09 | BJ15: =BJ12+BJ14 -> -4.25245e+09
B16: TOTAL INTEREST EXPENSES | C16: Interest Expense | D16: =SUMIFS( INDEX(NG!C:AL, MATCH($B16, NG!$B:$B, 0), ), NG!$C$3:$AL$3, ">="&DATE(YEAR($C$2),1,1), NG!$C$3:$AL$3, "<="&$C$2 ) -> 0 | E16: =SUMIFS( INDEX(NG!C:AL, MATCH($B16, NG!$B:$B, 0), ), NG!$C$3:$AL$3, ">="&DATE(YEAR($C$2)-1,1,1), NG!$C$3:$AL$3, "<="&EDATE($C$2,-12) ) -> 0 | F16: =D16/$F$3 -> 0 | G16: =E16/$G$3 -> 0 | H16: =IFERROR(D16/E16-1,0) -> 0 | K16: Interest Expense | L16: =SUMIFS( INDEX(Group!C:AL, MATCH($B16, Group!$B:$B, 0), ), Group!$C$3:$AL$3, ">="&DATE(YEAR($C$2),1,1), Group!$C$3:$AL$3, "<="&$C$2 ) -> 0 | M16: =SUMIFS( INDEX(Group!C:AL, MATCH($B16, Group!$B:$B, 0), ), Group!$C$3:$AL$3, ">="&DATE(YEAR($C$2)-1,1,1), Group!$C$3:$AL$3, "<="&EDATE($C$2,-12) ) -> 0 | N16: =L16/$F$3 -> 0 | O16: =M16/$G$3 -> 0 | P16: =IFERROR(L16/M16-1,0) -> 0 | Q16: =L16-M16 -> 0 | U16: Profit Margin | V16: =IFERROR(V15/V6,"") -> -0.3022095 | W16: =IFERROR(W15/W6,"") -> -3.9060563 | X16: =IFERROR(X15/X6,"") -> -20.896139 | Y16: =IFERROR(Y15/Y6,"") -> -100.95519 | Z16: =IFERROR(Z15/Z6,"") -> -1.3364953 | AA16: =IFERROR(AA15/AA6,"n/a") -> -11219.184 | AB16: =IFERROR(AB15/AB6,"") -> -2.8750051 | AE16: =Z16*C_RATE -> -1837.0796 | AF16: Operating Expenses | AG16: ='Segment Report'!Y21/Summary!Z6 -> -0.44950346 | AH16: n/a | AI16: ='Segment Report'!W21/Summary!AB6 -> -0.9192311 | BC16: Profit Margin | BD16: =IFERROR(BD15/BD6,"") -> -0.3022095 | BE16: =IFERROR(BE15/BE6,"") -> -3.9060563 | BF16: =IFERROR(BF15/BF6,"") -> -20.896139 | BG16: =IFERROR(BG15/BG6,"") -> -100.95519 | BH16: =IFERROR(BH15/BH6,"") -> -1.3364953 | BI16: =IFERROR(BI15/BI6,"n/a") -> -11219.184 | BJ16: =IFERROR(BJ15/BJ6,"") -> -2.8750051
C17: Profit before Tax | D17: =D15+D16 -> 8.2842688e+08 | E17: =E15+E16 -> 46330188 | F17: =F15+F16 -> 602689.52 | G17: =G15+G16 -> 28922.023 | H17: =IFERROR(D17/E17-1,0) -> 16.880931 | K17: Profit before Tax | L17: =L15+L16 -> 5.6750523e+08 | M17: =M15+M16 -> -2.6401692e+08 | N17: =N15+N16 -> 412866.19 | O17: =O15+O16 -> -164814.85 | P17: =IFERROR(L17/M17-1,0) -> -3.1495033 | Q17: =L17-M17 -> 8.3152214e+08 | U17: Expense to Income Ratio | V17: =100%-V16 -> 1.3022095 | W17: =100%-W16 -> 4.9060563 | X17: =100%-X16 -> 21.896139 | Y17: =100%-Y16 -> 101.95519 | Z17: =100%-Z16 -> 2.3364953 | AA17: =100%-AA16 -> 11220.184 | AB17: =100%-AB16 -> 3.8750051 | AE17: =Z17*C_RATE -> 3211.6296 | AF17: Total Cost | AG17: =Z17 -> 2.3364953 | AH17: n/a | AI17: =AB17 -> 3.8750051 | BC17: Expense to Income Ratio | BD17: =100%-BD16 -> 1.3022095 | BE17: =100%-BE16 -> 4.9060563 | BF17: =100%-BF16 -> 21.896139 | BG17: =100%-BG16 -> 101.95519 | BH17: =100%-BH16 -> 2.3364953 | BI17: =100%-BI16 -> 11220.184 | BJ17: =100%-BJ16 -> 3.8750051
B18: TOTAL TAX EXPENSES | C18: Tax Expense | D18: =SUMIFS( INDEX(NG!C:AL, MATCH($B18, NG!$B:$B, 0), ), NG!$C$3:$AL$3, ">="&DATE(YEAR($C$2),1,1), NG!$C$3:$AL$3, "<="&$C$2 ) -> 0 | E18: =SUMIFS( INDEX(NG!C:AL, MATCH($B18, NG!$B:$B, 0), ), NG!$C$3:$AL$3, ">="&DATE(YEAR($C$2)-1,1,1), NG!$C$3:$AL$3, "<="&EDATE($C$2,-12) ) -> 0 | F18: =D18/$F$3 -> 0 | G18: =E18/$G$3 -> 0 | H18: =IFERROR(D18/E18-1,0) -> 0 | K18: Tax Expense | L18: =SUMIFS( INDEX(Group!C:AL, MATCH($B18, Group!$B:$B, 0), ), Group!$C$3:$AL$3, ">="&DATE(YEAR($C$2),1,1), Group!$C$3:$AL$3, "<="&$C$2 ) -> 0 | M18: =SUMIFS( INDEX(Group!C:AL, MATCH($B18, Group!$B:$B, 0), ), Group!$C$3:$AL$3, ">="&DATE(YEAR($C$2)-1,1,1), Group!$C$3:$AL$3, "<="&EDATE($C$2,-12) ) -> 0 | N18: =L18/$F$3 -> 0 | O18: =M18/$G$3 -> 0 | P18: =IFERROR(L18/M18-1,0) -> 0 | Q18: =L18-M18 -> 0 | U18: *Others- Next Gen, Rose of Sharon & Hardware | Z18: =(Z11+Z14)*C_RATE -> -2.4480537e+09 | AA18: =(AA11+AA14)*C_RATE -> -2510122132 | BC18: *Others- Next Gen, Rose of Sharon & Hardware | BH18: =(BH11+BH14) -> -2448053721 | BI18: =(BI11+BI14) -> -2510122132
C19: Profit After Tax | D19: =D17+D18 -> 8.2842688e+08 | E19: =E17+E18 -> 46330188 | F19: =F17+F18 -> 602689.52 | G19: =G17+G18 -> 28922.023 | H19: =IFERROR(D19/E19-1,0) -> 16.880931 | K19: Profit After Tax | L19: =L17+L18 -> 5.6750523e+08 | M19: =M17+M18 -> -2.6401692e+08 | N19: =N17+N18 -> 412866.19 | O19: =O17+O18 -> -164814.85 | P19: =IFERROR(L19/M19-1,0) -> -3.1495033 | Q19: =L19-M19 -> 8.3152214e+08
D20: =D12+D16+D14+D18 -> -1.1024311e+09 | L20: =L12+L16+L14+L18 -> -1.3596443e+09 | U20: =L12+L14+L16+L18 -> -1.3596443e+09
U21: =L13/L8 -> 0.26042901 | V21: =M16+M18 -> 0 | AD21: =AD11*C_RATE -> -3.2974801e+09 | AE21: =Z21*C_RATE -> 0 | AF21: Ratios | AG21: CONSULTING | AH21: PRODUCT-FIXIAM | AI21: GROUP TOTAL
C22: Revenue by Vertical | D22: =D7 -> NGN | E22: =E7 -> NGN | F22: =F7 -> USD | G22: =G7 -> USD | K22: Revenue by Vertical | L22: =D22 -> NGN | M22: =E22 -> NGN | N22: =F22 -> USD | O22: =G22 -> USD | AF22: Current Ratio | AG22: =(W30+W29)/W34 -> 0.97912996 | AH22: n/a | AI22: =(AA30+AA29)/AA34 -> 2.1085441
B23: Verify | C23: Identity Suite | D23: =SUMIFS( INDEX(NG!C:AL, MATCH($B23, NG!$B:$B, 0), ), NG!$C$3:$AL$3, ">="&DATE(YEAR($C$2),1,1), NG!$C$3:$AL$3, "<="&$C$2 ) -> 0 | E23: =SUMIFS( INDEX(NG!C:AL, MATCH($B23, NG!$B:$B, 0), ), NG!$C$3:$AL$3, ">="&DATE(YEAR($C$2)-1,1,1), NG!$C$3:$AL$3, "<="&EDATE($C$2,-12) ) -> 29039114 | F23: =D23/$F$3 -> 0 | G23: =E23/$G$3 -> 18127.919 | H23: =IFERROR(D23/E23-1,0) -> -1 | I23: =D23/$D$28 -> 0 | K23: Identity Suite | L23: =SUMIFS( INDEX(Group!C:AL, MATCH($B23, Group!$B:$B, 0), ), Group!$C$3:$AL$3, ">="&DATE(YEAR($C$2),1,1), Group!$C$3:$AL$3, "<="&$C$2 ) -> 6406879.1 | M23: =SUMIFS( INDEX(Group!C:AL, MATCH($B23, Group!$B:$B, 0), ), Group!$C$3:$AL$3, ">="&DATE(YEAR($C$2)-1,1,1), Group!$C$3:$AL$3, "<="&EDATE($C$2,-12) ) -> 34044054 | N23: =L23/$F$3 -> 4661.0739 | O23: =M23/$G$3 -> 21252.297 | P23: =IFERROR(L23/M23-1,0) -> -0.81180622 | S23: =N23/$N$28 -> 0.004331576 | T23: =O23/$O$28 -> 0.036543329 | AF23: Asset turnover ratio (Times) | AG23: =Z6/W31 -> 0.52779646 | AH23: n/a | AI23: =AB6/AA31 -> 0.23124478
B24: Telco | C24: Telco Suite | D24: =SUMIFS( INDEX(NG!C:AL, MATCH($B24, NG!$B:$B, 0), ), NG!$C$3:$AL$3, ">="&DATE(YEAR($C$2),1,1), NG!$C$3:$AL$3, "<="&$C$2 ) -> 3.6444465e+08 | E24: =SUMIFS( INDEX(NG!C:AL, MATCH($B24, NG!$B:$B, 0), ), NG!$C$3:$AL$3, ">="&DATE(YEAR($C$2)-1,1,1), NG!$C$3:$AL$3, "<="&EDATE($C$2,-12) ) -> 399567769 | F24: =D24/$F$3 -> 265137.43 | G24: =E24/$G$3 -> 249433.65 | H24: =IFERROR(D24/E24-1,0) -> -0.087902779 | I24: =D24/$D$28 -> 0.2475005 | K24: Telco Suite | L24: =SUMIFS( INDEX(Group!C:AL, MATCH($B24, Group!$B:$B, 0), ), Group!$C$3:$AL$3, ">="&DATE(YEAR($C$2),1,1), Group!$C$3:$AL$3, "<="&$C$2 ) -> 3.6444465e+08 | M24: =SUMIFS( INDEX(Group!C:AL, MATCH($B24, Group!$B:$B, 0), ), Group!$C$3:$AL$3, ">="&DATE(YEAR($C$2)-1,1,1), Group!$C$3:$AL$3, "<="&EDATE($C$2,-12) ) -> 399567769 | N24: =L24/$F$3 -> 265137.43 | O24: =M24/$G$3 -> 249433.65 | P24: =IFERROR(L24/M24-1,0) -> -0.087902779 | S24: =N24/$N$28 -> 0.24639449 | T24: =O24/$O$28 -> 0.42890122 | AF24: Receivables turnover ratio (Times) | AG24: =Z6/'Segment Report'!S57 -> 2.4888134 | AH24: n/a | AI24: =AG24 -> 2.4888134
B25: Public Sector | C25: Public Sector Suite | D25: =SUMIFS( INDEX(NG!C:AL, MATCH($B25, NG!$B:$B, 0), ), NG!$C$3:$AL$3, ">="&DATE(YEAR($C$2),1,1), NG!$C$3:$AL$3, "<="&$C$2 ) -> 1.1072188e+09 | E25: =SUMIFS( INDEX(NG!C:AL, MATCH($B25, NG!$B:$B, 0), ), NG!$C$3:$AL$3, ">="&DATE(YEAR($C$2)-1,1,1), NG!$C$3:$AL$3, "<="&EDATE($C$2,-12) ) -> 428038702 | F25: =D25/$F$3 -> 805513.66 | G25: =E25/$G$3 -> 267206.88 | H25: =IFERROR(D25/E25-1,0) -> 1.5867259 | I25: =D25/$D$28 -> 0.75193094 | K25: Public Sector Suite | L25: =SUMIFS( INDEX(Group!C:AL, MATCH($B25, Group!$B:$B, 0), ), Group!$C$3:$AL$3, ">="&DATE(YEAR($C$2),1,1), Group!$C$3:$AL$3, "<="&$C$2 ) -> 1.1072188e+09 | M25: =SUMIFS( INDEX(Group!C:AL, MATCH($B25, Group!$B:$B, 0), ), Group!$C$3:$AL$3, ">="&DATE(YEAR($C$2)-1,1,1), Group!$C$3:$AL$3, "<="&EDATE($C$2,-12) ) -> 4.7922112e+08 | N25: =L25/$F$3 -> 805513.66 | O25: =M25/$G$3 -> 299157.95 | P25: =IFERROR(L25/M25-1,0) -> 1.3104549 | S25: =N25/$N$28 -> 0.74857076 | T25: =O25/$O$28 -> 0.51440216 | U25: SEGMENTED BALANCE SHEET | AF25: Average Receivable Days Outstanding (Days) | AG25: =(D$6-DATE(2025,1,1))/AG24 -> 194.47018 | AH25: n/a | AI25: =(F$6-DATE(2025,1,1))/AI24 -> 194.47018
B26: Others | C26: Others | D26: =SUMIFS( INDEX(NG!C:AL, MATCH($B26, NG!$B:$B, 0), ), NG!$C$3:$AL$3, ">="&DATE(YEAR($C$2),1,1), NG!$C$3:$AL$3, "<="&$C$2 ) -> 837209.3 | E26: =SUMIFS( INDEX(NG!C:AL, MATCH($B26, NG!$B:$B, 0), ), NG!$C$3:$AL$3, ">="&DATE(YEAR($C$2)-1,1,1), NG!$C$3:$AL$3, "<="&EDATE($C$2,-12) ) -> 18774958 | F26: =D26/$F$3 -> 609.07883 | G26: =E26/$G$3 -> 11720.431 | H26: =IFERROR(D26/E26-1,0) -> -0.95540819 | I26: =D26/$D$28 -> 0.00056856294 | K26: Others | L26: =SUMIFS( INDEX(Group!C:AL, MATCH($B26, Group!$B:$B, 0), ), Group!$C$3:$AL$3, ">="&DATE(YEAR($C$2),1,1), Group!$C$3:$AL$3, "<="&$C$2 ) -> 837209.3 | M26: =SUMIFS( INDEX(Group!C:AL, MATCH($B26, Group!$B:$B, 0), ), Group!$C$3:$AL$3, ">="&DATE(YEAR($C$2)-1,1,1), Group!$C$3:$AL$3, "<="&EDATE($C$2,-12) ) -> 18774958 | N26: =L26/$F$3 -> 609.07883 | O26: =M26/$G$3 -> 11720.431 | P26: =IFERROR(L26/M26-1,0) -> -0.95540819 | S26: =N26/$N$28 -> 0.00056602219 | T26: =O26/$O$28 -> 0.020153283 | V26: CONSULTING BUSINESS | X26: PRODUCT BUSINESS | Z26: TOTAL | AF26: Working capital turnover | AG26: =Z6/(W29+W30-W34) -> -36.483476 | AH26: n/a | AI26: =AB6/(AA29+AA30-AA34) -> 0.68676204
B27: Fixiam | C27: Fixiam | D27: =SUMIFS( INDEX(NG!C:AL, MATCH($B27, NG!$B:$B, 0), ), NG!$C$3:$AL$3, ">="&DATE(YEAR($C$2),1,1), NG!$C$3:$AL$3, "<="&$C$2 ) -> 0 | E27: =SUMIFS( INDEX(NG!C:AL, MATCH($B27, NG!$B:$B, 0), ), NG!$C$3:$AL$3, ">="&DATE(YEAR($C$2)-1,1,1), NG!$C$3:$AL$3, "<="&EDATE($C$2,-12) ) -> 0 | F27: =D27/$F$3 -> 0 | G27: =E27/$G$3 -> 0 | H27: =IFERROR(D27/E27-1,0) -> 0 | K27: Fixiam | L27: =SUMIFS( INDEX(Group!C:AL, MATCH($B27, Group!$B:$B, 0), ), Group!$C$3:$AL$3, ">="&DATE(YEAR($C$2),1,1), Group!$C$3:$AL$3, "<="&$C$2 ) -> 202857.63 | M27: =SUMIFS( INDEX(Group!C:AL, MATCH($B27, Group!$B:$B, 0), ), Group!$C$3:$AL$3, ">="&DATE(YEAR($C$2)-1,1,1), Group!$C$3:$AL$3, "<="&EDATE($C$2,-12) ) -> 0 | N27: =L27/$F$3 -> 147.58112 | O27: =M27/$G$3 -> 0 | P27: =IFERROR(L27/M27-1,0) -> 0 | S27: =N27/$N$28 -> 0.0001371484 | T27: =O27/$O$28 -> 0 | U27: Financial Position Summary | V27: NGN | W27: USD | X27: NGN | Y27: USD | Z27: NGN | AA27: USD | AF27: Payables turnover ratio (Times) | AG27: =-Z7/'Segment Report'!S67 -> 2.3589477 | AH27: n/a | AI27: =-AB7/'Segment Report'!T67 -> 2.4254353
B28: Total | C28: Total | D28: =SUM(D23:D27) -> 1.4725007e+09 | E28: =SUM(E23:E27) -> 875420543 | F28: =SUM(F23:F27) -> 1071260.2 | G28: =SUM(G23:G27) -> 546488.88 | H28: =IFERROR(D28/E28-1,0) -> 0.68204947 | K28: Total | L28: =SUM(L23:L27) -> 1.4791104e+09 | M28: =SUM(M23:M27) -> 9.316079e+08 | N28: =L28/$F$3 -> 1076068.8 | O28: =M28/$G$3 -> 581564.33 | P28: =IFERROR(L28/M28-1,0) -> 0.58769627 | U28: Non Current Assets | V28: =SUM('Segment Report'!Q63:Q65) -> 9.0025456e+08 | W28: =V28/C_RATE -> 654944.94 | X28: =SUM('Segment Report'!P63:P65) -> 1.3994385e+09 | Y28: =X28/C_RATE -> 1018106.7 | Z28: =V28+X28 -> 2.2996931e+09 | AA28: =W28+Y28 -> 1673051.6 | AF28: Average Payables Days Outstanding (Days) | AG28: =(D$6-DATE(2025,1,1))/AG27 -> 205.17623 | AH28: n/a | AI28: =(F$6-DATE(2025,1,1))/AI27 -> 199.55181
D29: =D8-D28 -> 8.911793e+08 | E29: =E8-E28 -> -1.1700001 | L29: =L8-L28 -> 8.9137933e+08 | M29: =M8-M28 -> -1.17 | U29: Cash & Cash Equivalent | V29: ='Segment Report'!Q56 -> 4.4852083e+08 | W29: =V29/C_RATE -> 326303.76 | X29: ='Segment Report'!P56 -> 2.1948175e+09 | Y29: =X29/C_RATE -> 1596753.5 | Z29: =V29+X29 -> 2.6433384e+09 | AA29: =W29+Y29 -> 1923057.3 | AF29: ROA | AG29: =Z15/W31 -> -0.7053975 | AH29: =AA15/Y31 -> -0.63320389 | AI29: =AB15/AA31 -> -0.66482992
U30: Current Assets | V30: =SUM('Segment Report'!Q57:Q62) -> 1.453266e+09 | W30: =V30/C_RATE -> 1057266.8 | X30: =SUM('Segment Report'!P57:P62) -> 0 | Y30: =X30/C_RATE -> 0 | Z30: =V30+X30 -> 1.453266e+09 | AA30: =W30+Y30 -> 1057266.8 | AF30: ROE | AG30: =Z15/W39 -> -3.0353926 | AH30: =AA15/Y39 -> -0.62040548 | AI30: =AB15/AA39 -> -0.98446113
C31: Revenue by Customer | D31: NGN | E31: NGN | F31: USD | G31: USD | K31: Revenue by Customer | L31: NGN | M31: NGN | N31: USD | O31: USD | U31: Total Assets | V31: =SUM(V28:V30) -> 2.8020414e+09 | W31: =SUM(W28:W30) -> 2038515.4 | X31: =SUM(X28:X30) -> 3.5942561e+09 | Y31: =SUM(Y28:Y30) -> 2614860.2 | Z31: =SUM(Z28:Z30) -> 6.3962975e+09 | AA31: =SUM(AA28:AA30) -> 4653375.7
B32: MTN Nigeria | C32: MTN Nigeria | D32: =SUMIFS( INDEX(NG!C:AL, MATCH($B32, NG!$B:$B, 0), ), NG!$C$3:$AL$3, ">="&DATE(YEAR($C$2),1,1), NG!$C$3:$AL$3, "<="&$C$2 ) -> 74230520 | E32: =SUMIFS( INDEX(NG!C:AL, MATCH($B32, NG!$B:$B, 0), ), NG!$C$3:$AL$3, ">="&DATE(YEAR($C$2)-1,1,1), NG!$C$3:$AL$3, "<="&EDATE($C$2,-12) ) -> 3.893693e+08 | F32: =D32/$F$3 -> 54003.507 | G32: =E32/$G$3 -> 243067.17 | H32: =IFERROR(D32/E32-1,0) -> -0.80935703 | K32: MTN Nigeria | L32: =SUMIFS( INDEX(Group!C:AL, MATCH($B32, Group!$B:$B, 0), ), Group!$C$3:$AL$3, ">="&DATE(YEAR($C$2),1,1), Group!$C$3:$AL$3, "<="&$C$2 ) -> 74230520 | M32: =SUMIFS( INDEX(Group!C:AL, MATCH($B32, Group!$B:$B, 0), ), Group!$C$3:$AL$3, ">="&DATE(YEAR($C$2)-1,1,1), Group!$C$3:$AL$3, "<="&EDATE($C$2,-12) ) -> 3.893693e+08 | N32: =L32/$F$3 -> 54003.507 | O32: =M32/$G$3 -> 243067.17 | P32: =IFERROR(L32/M32-1,0) -> -0.80935703
B33: Globacom | C33: Globacom | D33: =SUMIFS( INDEX(NG!C:AL, MATCH($B33, NG!$B:$B, 0), ), NG!$C$3:$AL$3, ">="&DATE(YEAR($C$2),1,1), NG!$C$3:$AL$3, "<="&$C$2 ) -> 2.1006136e+08 | E33: =SUMIFS( INDEX(NG!C:AL, MATCH($B33, NG!$B:$B, 0), ), NG!$C$3:$AL$3, ">="&DATE(YEAR($C$2)-1,1,1), NG!$C$3:$AL$3, "<="&EDATE($C$2,-12) ) -> 113530466 | F33: =D33/$F$3 -> 152821.91 | G33: =E33/$G$3 -> 70872.38 | H33: =IFERROR(D33/E33-1,0) -> 0.8502642 | K33: Globacom | L33: =SUMIFS( INDEX(Group!C:AL, MATCH($B33, Group!$B:$B, 0), ), Group!$C$3:$AL$3, ">="&DATE(YEAR($C$2),1,1), Group!$C$3:$AL$3, "<="&$C$2 ) -> 2.1006136e+08 | M33: =SUMIFS( INDEX(Group!C:AL, MATCH($B33, Group!$B:$B, 0), ), Group!$C$3:$AL$3, ">="&DATE(YEAR($C$2)-1,1,1), Group!$C$3:$AL$3, "<="&EDATE($C$2,-12) ) -> 113530466 | N33: =L33/$F$3 -> 152821.91 | O33: =M33/$G$3 -> 70872.38 | P33: =IFERROR(L33/M33-1,0) -> 0.8502642 | U33: Non current Liabilities | V33: ='Segment Report'!Q66 -> 21499461 | W33: =V33/C_RATE -> 15641.09 | X33: ='Segment Report'!P66 -> 0 | Y33: =X33/C_RATE -> 0 | Z33: =V33+X33 -> 21499461 | AA33: =W33+Y33 -> 15641.09
B34: UNN | C34: UNN | D34: =SUMIFS( INDEX(NG!C:AL, MATCH($B34, NG!$B:$B, 0), ), NG!$C$3:$AL$3, ">="&DATE(YEAR($C$2),1,1), NG!$C$3:$AL$3, "<="&$C$2 ) -> 31897727 | E34: =SUMIFS( INDEX(NG!C:AL, MATCH($B34, NG!$B:$B, 0), ), NG!$C$3:$AL$3, ">="&DATE(YEAR($C$2)-1,1,1), NG!$C$3:$AL$3, "<="&EDATE($C$2,-12) ) -> 1.2810687e+08 | F34: =D34/$F$3 -> 23205.941 | G34: =E34/$G$3 -> 79971.827 | H34: =IFERROR(D34/E34-1,0) -> -0.7510069 | K34: UNN | L34: =SUMIFS( INDEX(Group!C:AL, MATCH($B34, Group!$B:$B, 0), ), Group!$C$3:$AL$3, ">="&DATE(YEAR($C$2),1,1), Group!$C$3:$AL$3, "<="&$C$2 ) -> 31897727 | M34: =SUMIFS( INDEX(Group!C:AL, MATCH($B34, Group!$B:$B, 0), ), Group!$C$3:$AL$3, ">="&DATE(YEAR($C$2)-1,1,1), Group!$C$3:$AL$3, "<="&EDATE($C$2,-12) ) -> 1.2810687e+08 | N34: =L34/$F$3 -> 23205.941 | O34: =M34/$G$3 -> 79971.827 | P34: =IFERROR(L34/M34-1,0) -> -0.7510069 | U34: Current Liabilities | V34: =SUM('Segment Report'!Q67:Q70) -> 1.9423232e+09 | W34: =V34/C_RATE -> 1413061.2 | X34: =SUM('Segment Report'!P67:P70) -> 536074.5 | Y34: =X34/C_RATE -> 390 | Z34: =V34+X34 -> 1.9428593e+09 | AA34: =W34+Y34 -> 1413451.2
B35: NIMC | C35: NIMC | D35: =SUMIFS( INDEX(NG!C:AL, MATCH($B35, NG!$B:$B, 0), ), NG!$C$3:$AL$3, ">="&DATE(YEAR($C$2),1,1), NG!$C$3:$AL$3, "<="&$C$2 ) -> 1.0434591e+09 | E35: =SUMIFS( INDEX(NG!C:AL, MATCH($B35, NG!$B:$B, 0), ), NG!$C$3:$AL$3, ">="&DATE(YEAR($C$2)-1,1,1), NG!$C$3:$AL$3, "<="&EDATE($C$2,-12) ) -> 1.9659983e+08 | F35: =D35/$F$3 -> 759127.82 | G35: =E35/$G$3 -> 122729.15 | H35: =IFERROR(D35/E35-1,0) -> 4.3075281 | K35: NIMC | L35: =SUMIFS( INDEX(Group!C:AL, MATCH($B35, Group!$B:$B, 0), ), Group!$C$3:$AL$3, ">="&DATE(YEAR($C$2),1,1), Group!$C$3:$AL$3, "<="&$C$2 ) -> 1.0434591e+09 | M35: =SUMIFS( INDEX(Group!C:AL, MATCH($B35, Group!$B:$B, 0), ), Group!$C$3:$AL$3, ">="&DATE(YEAR($C$2)-1,1,1), Group!$C$3:$AL$3, "<="&EDATE($C$2,-12) ) -> 1.9659983e+08 | N35: =L35/$F$3 -> 759127.82 | O35: =M35/$G$3 -> 122729.15 | P35: =IFERROR(L35/M35-1,0) -> 4.3075281 | R35: =L35/L8 -> 0.44018716 | U35: Total Liabilities | V35: =SUM(V33:V34) -> 1.9638227e+09 | W35: =SUM(W33:W34) -> 1428702.2 | X35: =SUM(X33:X34) -> 536074.5 | Y35: =SUM(Y33:Y34) -> 390 | Z35: =SUM(Z33:Z34) -> 1.9643588e+09 | AA35: =SUM(AA33:AA34) -> 1429092.2
B36: Orange Liberia | C36: Orange Liberia | D36: =SUMIFS( INDEX(NG!C:AL, MATCH($B36, NG!$B:$B, 0), ), NG!$C$3:$AL$3, ">="&DATE(YEAR($C$2),1,1), NG!$C$3:$AL$3, "<="&$C$2 ) -> 44042974 | E36: =SUMIFS( INDEX(NG!C:AL, MATCH($B36, NG!$B:$B, 0), ), NG!$C$3:$AL$3, ">="&DATE(YEAR($C$2)-1,1,1), NG!$C$3:$AL$3, "<="&EDATE($C$2,-12) ) -> 0 | F36: =D36/$F$3 -> 32041.74 | G36: =E36/$G$3 -> 0 | H36: =IFERROR(D36/E36-1,0) -> 0 | K36: Orange Liberia | L36: =SUMIFS( INDEX(Group!C:AL, MATCH($B36, Group!$B:$B, 0), ), Group!$C$3:$AL$3, ">="&DATE(YEAR($C$2),1,1), Group!$C$3:$AL$3, "<="&$C$2 ) -> 44042974 | M36: =SUMIFS( INDEX(Group!C:AL, MATCH($B36, Group!$B:$B, 0), ), Group!$C$3:$AL$3, ">="&DATE(YEAR($C$2)-1,1,1), Group!$C$3:$AL$3, "<="&EDATE($C$2,-12) ) -> 0 | N36: =L36/$F$3 -> 32041.74 | O36: =M36/$G$3 -> 0 | P36: =IFERROR(L36/M36-1,0) -> 0
B37: MTN CIV | C37: MTN CIV | D37: =SUMIFS( INDEX(NG!C:AL, MATCH($B37, NG!$B:$B, 0), ), NG!$C$3:$AL$3, ">="&DATE(YEAR($C$2),1,1), NG!$C$3:$AL$3, "<="&$C$2 ) -> 35992741 | E37: =SUMIFS( INDEX(NG!C:AL, MATCH($B37, NG!$B:$B, 0), ), NG!$C$3:$AL$3, ">="&DATE(YEAR($C$2)-1,1,1), NG!$C$3:$AL$3, "<="&EDATE($C$2,-12) ) -> 0 | F37: =D37/$F$3 -> 26185.109 | G37: =E37/$G$3 -> 0 | H37: =IFERROR(D37/E37-1,0) -> 0 | K37: MTN CIV | L37: =SUMIFS( INDEX(Group!C:AL, MATCH($B37, Group!$B:$B, 0), ), Group!$C$3:$AL$3, ">="&DATE(YEAR($C$2),1,1), Group!$C$3:$AL$3, "<="&$C$2 ) -> 35992741 | M37: =SUMIFS( INDEX(Group!C:AL, MATCH($B37, Group!$B:$B, 0), ), Group!$C$3:$AL$3, ">="&DATE(YEAR($C$2)-1,1,1), Group!$C$3:$AL$3, "<="&EDATE($C$2,-12) ) -> 0 | N37: =L37/$F$3 -> 26185.109 | O37: =M37/$G$3 -> 0 | P37: =IFERROR(L37/M37-1,0) -> 0 | U37: Equity | V37: =SUM('Segment Report'!Q71) -> 2.1702404e+08 | W37: =V37/C_RATE -> 157887.34 | X37: =SUM('Segment Report'!P71) -> 6489017168 | Y37: =X37/C_RATE -> 4720830.2 | Z37: =V37+X37 -> 6.7060412e+09 | AA37: =W37+Y37 -> 4878717.6
B38: Verified Customers | C38: Verified Customers | D38: =SUMIFS( INDEX(NG!C:AL, MATCH($B38, NG!$B:$B, 0), ), NG!$C$3:$AL$3, ">="&DATE(YEAR($C$2),1,1), NG!$C$3:$AL$3, "<="&$C$2 ) -> 0 | E38: =SUMIFS( INDEX(NG!C:AL, MATCH($B38, NG!$B:$B, 0), ), NG!$C$3:$AL$3, ">="&DATE(YEAR($C$2)-1,1,1), NG!$C$3:$AL$3, "<="&EDATE($C$2,-12) ) -> 6942928.8 | F38: =D38/$F$3 -> 0 | G38: =E38/$G$3 -> 4334.1837 | H38: =IFERROR(D38/E38-1,0) -> -1 | K38: Verified Customers | L38: =SUMIFS( INDEX(Group!C:AL, MATCH($B38, Group!$B:$B, 0), ), Group!$C$3:$AL$3, ">="&DATE(YEAR($C$2),1,1), Group!$C$3:$AL$3, "<="&$C$2 ) -> 0 | M38: =SUMIFS( INDEX(Group!C:AL, MATCH($B38, Group!$B:$B, 0), ), Group!$C$3:$AL$3, ">="&DATE(YEAR($C$2)-1,1,1), Group!$C$3:$AL$3, "<="&EDATE($C$2,-12) ) -> 6942928.8 | N38: =L38/$F$3 -> 0 | O38: =M38/$G$3 -> 4334.1837 | P38: =IFERROR(L38/M38-1,0) -> -1 | U38: Retained Earnings | V38: =SUM('Segment Report'!Q72) -> 4.3414477e+08 | W38: =V38/C_RATE -> 315845.02 | X38: =SUM('Segment Report'!P72) -> -2.8206148e+09 | Y38: =X38/C_RATE -> -2052027.8 | Z38: =V38+X38 -> -2.38647e+09 | AA38: =W38+Y38 -> -1736182.7
B39: Others Customers | C39: Others Customers | D39: =SUMIFS( INDEX(NG!C:AL, MATCH($B39, NG!$B:$B, 0), ), NG!$C$3:$AL$3, ">="&DATE(YEAR($C$2),1,1), NG!$C$3:$AL$3, "<="&$C$2 ) -> 8930232.6 | E39: =SUMIFS( INDEX(NG!C:AL, MATCH($B39, NG!$B:$B, 0), ), NG!$C$3:$AL$3, ">="&DATE(YEAR($C$2)-1,1,1), NG!$C$3:$AL$3, "<="&EDATE($C$2,-12) ) -> 40871142 | F39: =D39/$F$3 -> 6496.8408 | G39: =E39/$G$3 -> 25514.166 | H39: =IFERROR(D39/E39-1,0) -> -0.78150274 | K39: Others Customers | L39: =SUMIFS( INDEX(Group!C:AL, MATCH($B39, Group!$B:$B, 0), ), Group!$C$3:$AL$3, ">="&DATE(YEAR($C$2),1,1), Group!$C$3:$AL$3, "<="&$C$2 ) -> 8930232.6 | M39: =SUMIFS( INDEX(Group!C:AL, MATCH($B39, Group!$B:$B, 0), ), Group!$C$3:$AL$3, ">="&DATE(YEAR($C$2)-1,1,1), Group!$C$3:$AL$3, "<="&EDATE($C$2,-12) ) -> 40871142 | N39: =L39/$F$3 -> 6496.8408 | O39: =M39/$G$3 -> 25514.166 | P39: =IFERROR(L39/M39-1,0) -> -0.78150274 | U39: Total Equity | V39: =V37+V38 -> 6.5116881e+08 | W39: =V39/C_RATE -> 473732.36 | X39: =X37+X38 -> 3.6684024e+09 | Y39: =X39/C_RATE -> 2668802.5 | Z39: =Z37+Z38 -> 4.3195712e+09 | AA39: =AA37+AA38 -> 3142534.8
B40: MFA Benin | C40: MFA Benin | D40: =SUMIFS( INDEX(NG!C:AL, MATCH($B40, NG!$B:$B, 0), ), NG!$C$3:$AL$3, ">="&DATE(YEAR($C$2),1,1), NG!$C$3:$AL$3, "<="&$C$2 ) -> 23885962 | E40: =SUMIFS( INDEX(NG!C:AL, MATCH($B40, NG!$B:$B, 0), ), NG!$C$3:$AL$3, ">="&DATE(YEAR($C$2)-1,1,1), NG!$C$3:$AL$3, "<="&EDATE($C$2,-12) ) -> 0 | F40: =D40/$F$3 -> 17377.296 | G40: =E40/$G$3 -> 0 | H40: =IFERROR(D40/E40-1,0) -> 0 | K40: MFA Benin | L40: =SUMIFS( INDEX(Group!C:AL, MATCH($B40, Group!$B:$B, 0), ), Group!$C$3:$AL$3, ">="&DATE(YEAR($C$2),1,1), Group!$C$3:$AL$3, "<="&$C$2 )+869175 -> 24755137 | M40: =SUMIFS( INDEX(Group!C:AL, MATCH($B40, Group!$B:$B, 0), ), Group!$C$3:$AL$3, ">="&DATE(YEAR($C$2)-1,1,1), Group!$C$3:$AL$3, "<="&EDATE($C$2,-12) ) -> 0 | N40: =L40/$F$3 -> 18009.63 | O40: =M40/$G$3 -> 0 | P40: =IFERROR(L40/M40-1,0) -> 0
B41: Fixiam | C41: Fixiam | D41: =SUMIFS( INDEX(NG!C:AL, MATCH($B41, NG!$B:$B, 0), ), NG!$C$3:$AL$3, ">="&DATE(YEAR($C$2),1,1), NG!$C$3:$AL$3, "<="&$C$2 ) -> 0 | E41: =SUMIFS( INDEX(NG!C:AL, MATCH($B41, NG!$B:$B, 0), ), NG!$C$3:$AL$3, ">="&DATE(YEAR($C$2)-1,1,1), NG!$C$3:$AL$3, "<="&EDATE($C$2,-12) ) -> 0 | F41: =D41/$F$3 -> 0 | G41: =E41/$G$3 -> 0 | H41: =IFERROR(D41/E41-1,0) -> 0 | K41: Fixiam | L41: =SUMIFS( INDEX(Group!C:AL, MATCH($B41, Group!$B:$B, 0), ), Group!$C$3:$AL$3, ">="&DATE(YEAR($C$2),1,1), Group!$C$3:$AL$3, "<="&$C$2 ) -> 202857.63 | M41: =SUMIFS( INDEX(Group!C:AL, MATCH($B41, Group!$B:$B, 0), ), Group!$C$3:$AL$3, ">="&DATE(YEAR($C$2)-1,1,1), Group!$C$3:$AL$3, "<="&EDATE($C$2,-12) ) -> 0 | N41: =L41/$F$3 -> 147.58112 | O41: =M41/$G$3 -> 0 | P41: =IFERROR(L41/M41-1,0) -> 0
B42: ONECI | C42: ONECI | D42: =SUMIFS( INDEX(NG!C:AL, MATCH($B42, NG!$B:$B, 0), ), NG!$C$3:$AL$3, ">="&DATE(YEAR($C$2),1,1), NG!$C$3:$AL$3, "<="&$C$2 ) -> 0 | E42: =SUMIFS( INDEX(NG!C:AL, MATCH($B42, NG!$B:$B, 0), ), NG!$C$3:$AL$3, ">="&DATE(YEAR($C$2)-1,1,1), NG!$C$3:$AL$3, "<="&EDATE($C$2,-12) ) -> 0 | F42: =D42/$F$3 -> 0 | G42: =E42/$G$3 -> 0 | H42: =IFERROR(D42/E42-1,0) -> 0 | K42: ONECI | L42: =SUMIFS( INDEX(Group!C:AL, MATCH($B42, Group!$B:$B, 0), ), Group!$C$3:$AL$3, ">="&DATE(YEAR($C$2),1,1), Group!$C$3:$AL$3, "<="&$C$2 ) -> 0 | M42: =SUMIFS( INDEX(Group!C:AL, MATCH($B42, Group!$B:$B, 0), ), Group!$C$3:$AL$3, ">="&DATE(YEAR($C$2)-1,1,1), Group!$C$3:$AL$3, "<="&EDATE($C$2,-12) ) -> 0 | N42: =L42/$F$3 -> 0 | O42: =M42/$G$3 -> 0 | P42: =IFERROR(L42/M42-1,0) -> 0
B43: UK NIMC | K43: UK NIMC | L43: =SUMIFS( INDEX(Group!C:AL, MATCH($B43, Group!$B:$B, 0), ), Group!$C$3:$AL$3, ">="&DATE(YEAR($C$2),1,1), Group!$C$3:$AL$3, "<="&$C$2 ) -> 0 | M43: =SUMIFS( INDEX(Group!C:AL, MATCH($B43, Group!$B:$B, 0), ), Group!$C$3:$AL$3, ">="&DATE(YEAR($C$2)-1,1,1), Group!$C$3:$AL$3, "<="&EDATE($C$2,-12) ) -> 51182418 | N43: =L43/$F$3 -> 0 | O43: =M43/$G$3 -> 31951.069 | P43: =IFERROR(L43/M43-1,0) -> -1 | U43: Total Equity & Liabilities | V43: =V35+V39 -> 2.6149915e+09 | W43: =W35+W39 -> 1902434.6 | X43: =X35+X39 -> 3.6689385e+09 | Y43: =Y35+Y39 -> 2669192.5 | Z43: =Z35+Z39 -> 6.28393e+09 | AA43: =AA35+AA39 -> 4571627.1
B44: UK Verification | K44: UK Verification | L44: =SUMIFS( INDEX(Group!C:AL, MATCH($B44, Group!$B:$B, 0), ), Group!$C$3:$AL$3, ">="&DATE(YEAR($C$2),1,1), Group!$C$3:$AL$3, "<="&$C$2 ) -> 6406879.1 | M44: =SUMIFS( INDEX(Group!C:AL, MATCH($B44, Group!$B:$B, 0), ), Group!$C$3:$AL$3, ">="&DATE(YEAR($C$2)-1,1,1), Group!$C$3:$AL$3, "<="&EDATE($C$2,-12) ) -> 5004939.8 | N44: =L44/$F$3 -> 4661.0739 | O44: =M44/$G$3 -> 3124.3772 | P44: =IFERROR(L44/M44-1,0) -> 0.28011112 | S44: =N35+N43 -> 759127.82
B45: MFA Benin | U45: Deferred Income | V45: =BS_NG!W194+BS_NG!W195+BS_NG!W196 -> 1.4134859e+09 | W45: =V45/C_RATE -> 1028326.3
B46: Fixiam
C47: Total | D47: =SUM(D32:D46) -> 1.4725007e+09 | E47: =SUM(E32:E46) -> 8.7542054e+08 | F47: =SUM(F32:F46) -> 1071260.2 | G47: =SUM(G32:G46) -> 546488.88 | H47: =IFERROR(D47/E47-1,0) -> 0.68204947 | K47: Total | L47: =SUM(L32:L46) -> 1.4799796e+09 | M47: =SUM(M32:M46) -> 9.316079e+08 | N47: =SUM(N32:N46) -> 1076701.2 | O47: =SUM(O32:O46) -> 581564.33 | P47: =IFERROR(L47/M47-1,0) -> 0.58862926
D48: =D8-D47 -> 8.911793e+08 | E48: =E8-E47 -> -0.55490005 | K48: Canada | L48: =L8-L47 -> 8.9051016e+08 | M48: =M8-M47 -> -0.55489981 | V48: =V31-V43 -> 1.8704992e+08 | X48: =X31-X43 -> -74682397 | Z48: =Z31-Z43 -> 1.1236753e+08
C50: Revenue by Country | D50: NGN | E50: NGN | F50: USD | G50: USD | K50: Revenue by Country | L50: NGN | M50: NGN | N50: USD | O50: USD
C51: Nigeria | D51: =D32+D33+D34+D35+D38+D39+D41 -> 1.368579e+09 | E51: =E32+E33+E34+E35+E38+E39 -> 8.7542054e+08 | F51: =D51/$F$3 -> 995656.02 | G51: =E51/$G$3 -> 546488.88 | H51: =IFERROR(D51/E51-1,0) -> 0.56333889 | K51: Nigeria | L51: =L32+L33+L34+L35+L38+L39+L41 -> 1.3687818e+09 | M51: =M32+M33+M34+M35+M38+M39 -> 8.7542054e+08 | N51: =N32+N33+N34+N35+N38+N39 -> 995656.02 | O51: =O32+O33+O34+O35+O38+O39 -> 546488.88 | P51: =IFERROR(L51/M51-1,0) -> 0.56357062 | S51: =N51/N56 -> 0.94059016 | T51: =O51/O56 -> 0.93968776
C52: Liberia | D52: =D36 -> 44042974 | E52: =E36 -> 0 | F52: =D52/$F$3 -> 32041.74 | G52: =E52/$G$3 -> 0 | H52: =IFERROR(D52/E52-1,0) -> 0 | K52: Liberia | L52: =L36 -> 44042974 | M52: =M36 -> 0 | N52: =L52/$F$3 -> 32041.74 | O52: =M52/$G$3 -> 0 | P52: =IFERROR(L52/M52-1,0) -> 0 | S52: =N52/N56 -> 0.030269636 | T52: =O52/O56 -> 0
C53: CIV | D53: =D37+D42 -> 35992741 | E53: =E37 -> 0 | F53: =D53/$F$3 -> 26185.109 | G53: =E53/$G$3 -> 0 | H53: =IFERROR(D53/E53-1,0) -> 0 | K53: CIV | L53: =L37+L42 -> 35992741 | M53: =M37 -> 0 | N53: =L53/$F$3 -> 26185.109 | O53: =M53/$G$3 -> 0 | P53: =IFERROR(L53/M53-1,0) -> 0 | S53: =N53/N56 -> 0.024736912 | T53: =O53/O56 -> 0
C54: Benin | D54: =D40 -> 23885962 | K54: UK | L54: =SUM(L43:L46) -> 6406879.1 | M54: =SUM(M43:M46) -> 56187358 | N54: =SUM(N43:N46) -> 4661.0739 | O54: =SUM(O43:O46) -> 35075.447 | P54: =IFERROR(L54/M54-1,0) -> -0.88597294 | S54: =N54/N56 -> 0.004403288 | T54: =O54/O56 -> 0.060312239 | V54: NGN | W54: USD
K55: Benin | L55: =L40 -> 24755137
C56: Total | D56: =SUM(D51:D54) -> 1.4725007e+09 | E56: =SUM(E51:E54) -> 8.7542054e+08 | F56: =SUM(F51:F54) -> 1053882.9 | G56: =SUM(G51:G54) -> 546488.88 | H56: =IFERROR(D56/E56-1,0) -> 0.68204947 | K56: Total | L56: =SUM(L51:L55) -> 1.4799796e+09 | M56: =SUM(M51:M55) -> 9.316079e+08 | N56: =SUM(N51:N55) -> 1058543.9 | O56: =SUM(O51:O55) -> 581564.33 | P56: =IFERROR(L56/M56-1,0) -> 0.58862926 | U56: Total Revenue | V56: 2.8402461e+09 | W56: 1953522.6
U57: EBITDA | V57: -1.3034038e+09 | W57: -896481.77
U58: EBITDA Margin | V58: -0.45890524 | W58: -0.45890524
C59: Annual Recurring Revenue | D59: NGN | E59: NGN | F59: USD | G59: USD | K59: Annual Recurring Revenue | L59: NGN | M59: NGN | N59: USD | O59: USD | U59: ARR | V59: 1.5591449e+09 | W59: 1072380.6
B60: Total ARR | C60: ARR | D60: =SUMIFS( INDEX(NG!C:AL, MATCH($B60, NG!$B:$B, 0), ), NG!$C$3:$AL$3, ">="&DATE(YEAR($C$2),1,1), NG!$C$3:$AL$3, "<="&$C$2 ) -> 3.6244312e+08 | E60: =SUMIFS( INDEX(NG!C:AL, MATCH($B60, NG!$B:$B, 0), ), NG!$C$3:$AL$3, ">="&DATE(YEAR($C$2)-1,1,1), NG!$C$3:$AL$3, "<="&EDATE($C$2,-12) ) -> 6.9651399e+08 | F60: =D60/$F$3 -> 263681.29 | G60: =E60/$G$3 -> 434804.92 | H60: =IFERROR(D60/E60-1,0) -> -0.47963268 | K60: ARR | L60: =SUMIFS( INDEX(Group!C:AL, MATCH($B60, Group!$B:$B, 0), ), Group!$C$3:$AL$3, ">="&DATE(YEAR($C$2),1,1), Group!$C$3:$AL$3, "<="&$C$2 ) -> 3.6244312e+08 | M60: =SUMIFS( INDEX(Group!C:AL, MATCH($B60, Group!$B:$B, 0), ), Group!$C$3:$AL$3, ">="&DATE(YEAR($C$2)-1,1,1), Group!$C$3:$AL$3, "<="&EDATE($C$2,-12) ) -> 6.9651399e+08 | N60: =L60/$F$3 -> 263681.29 | O60: =M60/$G$3 -> 434804.92 | P60: =IFERROR(L60/M60-1,0) -> -0.47963268 | U60: ARR (%) | V60: 0.54894712 | W60: 0.54894712
C61: ARR (%) | D61: =D60/D8 -> 0.15333849 | E61: =E60/E8 -> 0.7956336 | F61: =F60/F8 -> 0.15333849 | G61: =G60/G8 -> 0.7956336 | H61: =F61-G61 -> -0.6422951 | K61: ARR (%) | L61: =L60/L8 -> 0.15289799 | M61: =M60/M8 -> 0.74764715 | N61: =N60/N8 -> 0.15289799 | O61: =O60/O8 -> 0.74764715 | P61: =N61-O61 -> -0.59474916 | U61: Gross Cash Burn | V61: =(L12+L11+L9+L16-V64-V65)/11 -> -2.3802709e+08 | W61: =V61/C_RATE -> -173167.28
U62: Net Cash Burn | V62: =V61+(V56/11) -> 20177101 | W62: =V62/C_RATE -> 14679.059
C64: Ratios | K64: Ratios | U64: Bind -2025 | V64: 8.3574989e+08
C65: Gross Profit Margin | D65: =D10/D8 -> 0.78624075 | E65: =E10/E8 -> 0.72744872 | F65: =F10/F8 -> 0.78624075 | G65: =G10/G8 -> 0.72744872 | H65: =D65-E65 -> 0.058792022 | K65: Gross Profit Margin | L65: =L10/L8 -> 0.78241765 | M65: =M10/M8 -> 0.72262943 | N65: =N10/N8 -> 0.78241765 | O65: =O10/O8 -> 0.72262943 | P65: =L65-M65 -> 0.05978822 | R65: =P65*100 -> 5.978822 | U65: Capex | V65: 29402634
C66: EBITDA Margin | D66: =D13/D8 -> 0.37115321 | E66: =E13/E8 -> 0.074647287 | F66: =F13/F8 -> 0.37115321 | G66: =G13/G8 -> 0.074647287 | H66: =D66-E66 -> 0.29650592 | K66: EBITDA Margin | L66: =L13/L8 -> 0.26042901 | M66: =M13/M8 -> -0.26185802 | N66: =N13/N8 -> 0.26042901 | O66: =O13/O8 -> -0.26185802 | P66: =L66-M66 -> 0.52228703
C67: NET Income Margin | D67: =D19/D8 -> 0.35048183 | E67: =E19/E8 -> 0.052923351 | F67: =F19/F8 -> 0.35048183 | G67: =G19/G8 -> 0.052923351 | H67: =D67-E67 -> 0.29755848 | K67: NET Income Margin | L67: =L19/L8 -> 0.23940421 | M67: =M19/M8 -> -0.28339918 | N67: =N19/N8 -> 0.23940421 | O67: =O19/O8 -> -0.28339918 | P67: =L67-M67 -> 0.52280339
C68: Opex to Revenue Ratio | D68: =-D12/D8 -> 0.44573318 | E68: =-E12/E8 -> 0.79930774 | F68: =-F12/F8 -> 0.44573318 | G68: =-G12/G8 -> 0.79930774 | H68: =G68-F68 -> 0.35357456 | K68: Opex to Revenue Ratio | L68: =-L12/L8 -> 0.55254625 | M68: =-M12/M8 -> 1.1221616 | N68: =-N12/N8 -> 0.55254625 | O68: =-O12/O8 -> 1.1221616 | P68: =O68-N68 -> 0.5696153
B69: Total Payroll Cost | C69: Payroll Expense | D69: =-SUMIFS( INDEX(NG!C:AL, MATCH($B69, NG!$B:$B, 0), ), NG!$C$3:$AL$3, ">="&DATE(YEAR($C$2),1,1), NG!$C$3:$AL$3, "<="&$C$2 ) -> 6.9729067e+08 | E69: =-SUMIFS( INDEX(NG!C:AL, MATCH($B69, NG!$B:$B, 0), ), NG!$C$3:$AL$3, ">="&DATE(YEAR($C$2)-1,1,1), NG!$C$3:$AL$3, "<="&EDATE($C$2,-12) ) -> 7.1644092e+08 | F69: =D69/$F$3 -> 507286.51 | G69: =E69/$G$3 -> 447244.47 | H69: =D69/E69-1 -> -0.026729693 | K69: Payroll Expense | L69: =-SUMIFS( INDEX(Group!C:AL, MATCH($B69, Group!$B:$B, 0), ), Group!$C$3:$AL$3, ">="&DATE(YEAR($C$2),1,1), Group!$C$3:$AL$3, "<="&$C$2 ) -> 9.125628e+08 | M69: =-SUMIFS( INDEX(Group!C:AL, MATCH($B69, Group!$B:$B, 0), ), Group!$C$3:$AL$3, ">="&DATE(YEAR($C$2)-1,1,1), Group!$C$3:$AL$3, "<="&EDATE($C$2,-12) ) -> 9.8524727e+08 | N69: =L69/$F$3 -> 663899.32 | O69: =M69/$G$3 -> 615049.17 | P69: =L69/M69-1 -> -0.073772813
C70: Payroll % of Revenue | D70: =D69/D8 -> 0.29500215 | E70: =E69/E8 -> 0.81839628 | F70: =F69/F8 -> 0.29500215 | G70: =G69/G8 -> 0.81839628 | H70: =D70-E70 -> -0.52339413 | K70: Payroll % of Revenue | L70: =L69/L8 -> 0.38496805 | M70: =M69/M8 -> 1.0575772 | N70: =N69/N8 -> 0.38496805 | O70: =O69/O8 -> 1.0575772 | P70: =L70-M70 -> -0.67260914
B71: Total Staff count | C71: Employee Count | D71: =L71-6-2 -> -8 | E71: 160 | F71: =D71 -> -8 | G71: =E71 -> 160 | H71: =IFERROR(D71/E71-1,0) -> -1.05 | K71: Employee Count | L71: =SUMIFS(INDEX(Group!$C:$AL, MATCH(Summary!$B71, Group!$B:$B, 0), ),Group!$C$3:$AL$3, Summary!$C$2) -> 0 | M71: =L71 -> 0 | N71: =L71 -> 0 | O71: =M71 -> 0 | P71: =IFERROR(L71/M71-1,0) -> 0
C72: Average Revenue per Employee | D72: =D8/D71/MONTH(D6) -> -73864999 | E72: =E8/E71/MONTH(E6) -> 1367844.6 | F72: =D72/$F$3 -> -53737.586 | G72: =E72/$G$3 -> 853.88888 | H72: =IFERROR(D72/E72-1,0) -> -55.001016 | K72: Average Revenue per Employee | L72: =L8/L71/MONTH(L6) -> #DIV/0! | M72: =M8/M71/MONTH(M6) -> #DIV/0! | N72: =L72/$F$3 -> #DIV/0! | O72: =M72/$G$3 -> #DIV/0! | P72: =IFERROR(L72/M72-1,0) -> 0
B73: Total Commercial Cost | C73: Marketing Expenses | D73: =-SUMIFS( INDEX(NG!C:AL, MATCH($B73, NG!$B:$B, 0), ), NG!$C$3:$AL$3, ">="&DATE(YEAR($C$2),1,1), NG!$C$3:$AL$3, "<="&$C$2 ) -> 1.0916193e+08 | E73: =-SUMIFS( INDEX(NG!C:AL, MATCH($B73, NG!$B:$B, 0), ), NG!$C$3:$AL$3, ">="&DATE(YEAR($C$2)-1,1,1), NG!$C$3:$AL$3, "<="&EDATE($C$2,-12) ) -> 2.7015206e+08 | F73: =D73/$F$3 -> 79416.486 | G73: =E73/$G$3 -> 168644.77 | H73: =D73/E73-1 -> -0.59592412 | K73: Marketing Expenses | L73: =-SUMIFS( INDEX(Group!C:AL, MATCH($B73, Group!$B:$B, 0), ), Group!$C$3:$AL$3, ">="&DATE(YEAR($C$2),1,1), Group!$C$3:$AL$3, "<="&$C$2 ) -> 1.124897e+08 | M73: =-SUMIFS( INDEX(Group!C:AL, MATCH($B73, Group!$B:$B, 0), ), Group!$C$3:$AL$3, ">="&DATE(YEAR($C$2)-1,1,1), Group!$C$3:$AL$3, "<="&EDATE($C$2,-12) ) -> 3.1784234e+08 | N73: =L73/$F$3 -> 81837.474 | O73: =M73/$G$3 -> 198415.84 | P73: =L73/M73-1 -> -0.64608334
C74: Marketing % of Revenue | D74: =D73/D8 -> 0.046183042 | E74: =E73/E8 -> 0.3085969 | F74: =F73/F8 -> 0.046183042 | G74: =G73/G8 -> 0.3085969 | K74: Marketing % of Revenue | L74: =L73/L8 -> 0.047454203 | M74: =M73/M8 -> 0.34117609 | N74: =N73/N8 -> 0.047454203 | O74: =O73/O8 -> 0.34117609
C76: Common Size Analysis | K76: Common Size Analysis
C77: as a % of Revenue | K77: as a % of Revenue
C78: Cost of Sales | D78: =-D9/D8 -> 0.21375925 | E78: =-E9/E8 -> 0.27255128 | F78: =-F9/F8 -> 0.21375925 | G78: =-G9/G8 -> 0.27255128 | H78: =D78-E78 -> -0.058792022 | K78: Cost of Sales | L78: =-L9/L8 -> 0.21758235 | M78: =-M9/M8 -> 0.27737057 | N78: =-N9/N8 -> 0.21758235 | O78: =-O9/O8 -> 0.27737057 | P78: =L78-M78 -> -0.05978822
C79: Operating Expenses | D79: =-D12/D8 -> 0.44573318 | E79: =-E12/E8 -> 0.79930774 | F79: =-F12/F8 -> 0.44573318 | G79: =-G12/G8 -> 0.79930774 | H79: =D79-E79 -> -0.35357456 | K79: Operating Expenses | L79: =-L12/L8 -> 0.55254625 | M79: =-M12/M8 -> 1.1221616 | N79: =-N12/N8 -> 0.55254625 | O79: =-O12/O8 -> 1.1221616 | P79: =L79-M79 -> -0.5696153
C80: Total Cost | D80: =-SUM(D9,D11,D12,D14,D16,D18)/D8 -> 0.64951817 | E80: =-SUM(E9,E11,E12,E14,E16,E18)/E8 -> 0.94707665 | F80: =-SUM(F9,F11,F12,F14,F16,F18)/F8 -> 0.64951817 | G80: =-SUM(G9,G11,G12,G14,G16,G18)/G8 -> 0.94707665 | H80: =D80-E80 -> -0.29755848 | K80: Total Cost | L80: =-SUM(L9,L11,L12,L14,L16,L18)/L8 -> 0.76059579 | M80: =-SUM(M9,M11,M12,M14,M16,M18)/M8 -> 1.2833992 | N80: =-SUM(N9,N11,N12,N14,N16,N18)/N8 -> 0.76059579 | O80: =-SUM(O9,O11,O12,O14,O16,O18)/O8 -> 1.2833992 | P80: =L80-M80 -> -0.52280339
L81: =BS_NG!AE48+BS_NG!AE46 -> 1.9176198e+09 | M81: =L81/C_RATE -> 1395089.1
D82: 2.3790427e+09 | E82: =D82-D87 -> -79616628 | L82: =L81-L87 -> -7.2571859e+08 | M82: =L82/C_RATE -> -527968.13
C83: NIGERIA BALANCE SHEET | K83: GROUP BALANCE SHEET
D84: =D5 -> YTD | E84: =E5 -> YTD | F84: =F5 -> YTD | G84: =G5 -> YTD | H84: =H5 -> Variance (%) | L84: =L5 -> YTD | M84: =M5 -> YTD | N84: =N5 -> YTD | O84: =O5 -> YTD | P84: =P5 -> Variance (%)
C85: Balance Sheet 000 | D85: =D6 -> 46142 | E85: =EOMONTH(D85,-4) -> 46022 | F85: =F6 -> 46142 | G85: =E85 -> 46022 | K85: Balance Sheet 000 | L85: =L6 -> 46142 | M85: =E85 -> 46022 | N85: =N6 -> 46142 | O85: =M85 -> 46022
D86: =D7 -> NGN | E86: =E7 -> NGN | F86: =F7 -> USD | G86: =G7 -> USD | L86: =L7 -> NGN | M86: =M7 -> NGN | N86: =N7 -> USD | O86: =O7 -> USD
B87: TOTAL CASH & CASH EQUIVALENT | C87: Cash & Cash Equivalents | D87: =SUMIFS(INDEX(NG!$C:$AL, MATCH(Summary!$B87, NG!$B:$B, 0), ),NG!$C$3:$AL$3, Summary!$C$2) -> 2.4586593e+09 | E87: =SUMIFS(INDEX(NG!$C:$AL,MATCH(Summary!$B87,NG!$B:$B,0),),NG!$C$3:$AL$3,$E$85) -> 2.3789035e+09 | F87: =D87/$F$3 -> 1788701.3 | G87: =E87/$G$3 -> 1485051.2 | H87: =IFERROR(D87/E87-1,0) -> 0.033526284 | K87: Cash & Cash Equivalents | L87: =SUMIFS(INDEX(Group!$C:$AL, MATCH(Summary!$B87, Group!$B:$B, 0), ),Group!$C$3:$AL$3, Summary!$C$2) -> 2.6433384e+09 | M87: =SUMIFS(INDEX(Group!$C:$AL, MATCH(Summary!$B87, Group!$B:$B, 0), ),Group!$C$3:$AL$3, Summary!$M$85) -> 2.4893752e+09 | N87: =L87/$F$3 -> 1923057.3 | O87: =M87/$G$3 -> 1554014.1 | P87: =IFERROR(L87/M87-1,0) -> 0.061848122 | T87: 3802839
B88: TOTAL ACCOUNT RECEIVABLES | C88: Account Receivables | D88: =SUMIFS(INDEX(NG!$C:$AL, MATCH(Summary!$B88, NG!$B:$B, 0), ),NG!$C$3:$AL$3, Summary!$C$2) -> 5.7330792e+08 | E88: =SUMIFS(INDEX(NG!$C:$AL,MATCH(Summary!$B88,NG!$B:$B,0),),NG!$C$3:$AL$3,$E$85) -> 2.1504615e+08 | F88: =D88/$F$3 -> 417087.71 | G88: =E88/$G$3 -> 134244.43 | H88: =IFERROR(D88/E88-1,0) -> 1.6659762 | K88: Account Receivables | L88: =SUMIFS(INDEX(Group!$C:$AL, MATCH(Summary!$B88, Group!$B:$B, 0), ),Group!$C$3:$AL$3, Summary!$C$2) -> 5.9422194e+08 | M88: =SUMIFS(INDEX(Group!$C:$AL, MATCH(Summary!$B88, Group!$B:$B, 0), ),Group!$C$3:$AL$3, Summary!$M$85) -> 2.3877259e+08 | N88: =L88/$F$3 -> 432302.89 | O88: =M88/$G$3 -> 149055.86 | P88: =IFERROR(L88/M88-1,0) -> 1.4886523 | T88: =N87-T87 -> -1879781.7
B89: TOTAL INVENTORIES | C89: Inventories | D89: =SUMIFS(INDEX(NG!$C:$AL, MATCH(Summary!$B89, NG!$B:$B, 0), ),NG!$C$3:$AL$3, Summary!$C$2) -> 45773938 | E89: =SUMIFS(INDEX(NG!$C:$AL,MATCH(Summary!$B89,NG!$B:$B,0),),NG!$C$3:$AL$3,$E$85) -> 55425070 | F89: =D89/$F$3 -> 33301.035 | G89: =E89/$G$3 -> 34599.581 | H89: =IFERROR(D89/E89-1,0) -> -0.17412936 | K89: Inventories | L89: =SUMIFS(INDEX(Group!$C:$AL, MATCH(Summary!$B89, Group!$B:$B, 0), ),Group!$C$3:$AL$3, Summary!$C$2) -> 49239580 | M89: =SUMIFS(INDEX(Group!$C:$AL, MATCH(Summary!$B89, Group!$B:$B, 0), ),Group!$C$3:$AL$3, Summary!$M$85) -> 59078743 | N89: =L89/$F$3 -> 35822.327 | O89: =M89/$G$3 -> 36880.419 | P89: =IFERROR(L89/M89-1,0) -> -0.1665432
B90: TOTAL PREPAID EXPENSES | C90: Prepaid Expenses | D90: =SUMIFS(INDEX(NG!$C:$AL, MATCH(Summary!$B90, NG!$B:$B, 0), ),NG!$C$3:$AL$3, Summary!$C$2) -> 2.1895554e+08 | E90: =SUMIFS(INDEX(NG!$C:$AL,MATCH(Summary!$B90,NG!$B:$B,0),),NG!$C$3:$AL$3,$E$85) -> 3.4093581e+08 | F90: =D90/$F$3 -> 159292.53 | G90: =E90/$G$3 -> 212832.14 | H90: =IFERROR(D90/E90-1,0) -> -0.35778074 | K90: Prepaid Expenses | L90: =SUMIFS(INDEX(Group!$C:$AL, MATCH(Summary!$B90, Group!$B:$B, 0), ),Group!$C$3:$AL$3, Summary!$C$2) -> 2.2760468e+08 | M90: =SUMIFS(INDEX(Group!$C:$AL, MATCH(Summary!$B90, Group!$B:$B, 0), ),Group!$C$3:$AL$3, Summary!$M$85) -> 3.5341366e+08 | N90: =L90/$F$3 -> 165584.86 | O90: =M90/$G$3 -> 220621.55 | P90: =IFERROR(L90/M90-1,0) -> -0.35598223
B91: TOTAL STAFF ADVANCES | C91: Staff Advances | D91: =SUMIFS(INDEX(NG!$C:$AL, MATCH(Summary!$B91, NG!$B:$B, 0), ),NG!$C$3:$AL$3, Summary!$C$2) -> 7688792.7 | E91: =SUMIFS(INDEX(NG!$C:$AL,MATCH(Summary!$B91,NG!$B:$B,0),),NG!$C$3:$AL$3,$E$85) -> 402004.23 | F91: =D91/$F$3 -> 5593.6799 | G91: =E91/$G$3 -> 250.95464 | H91: =IFERROR(D91/E91-1,0) -> 18.126149 | K91: Staff Advances | L91: =SUMIFS(INDEX(Group!$C:$AL, MATCH(Summary!$B91, Group!$B:$B, 0), ),Group!$C$3:$AL$3, Summary!$C$2) -> 9543892.7 | M91: =SUMIFS(INDEX(Group!$C:$AL, MATCH(Summary!$B91, Group!$B:$B, 0), ),Group!$C$3:$AL$3, Summary!$M$85) -> 402004.23 | N91: =L91/$F$3 -> 6943.2852 | O91: =M91/$G$3 -> 250.95464 | P91: =IFERROR(L91/M91-1,0) -> 22.740777
B92: TOTAL OTHER RECIEVABLES ` | C92: Other Receivables | D92: =SUMIFS(INDEX(NG!$C:$AL, MATCH(Summary!$B92, NG!$B:$B, 0), ),NG!$C$3:$AL$3, Summary!$C$2) -> 5.7228463e+08 | E92: =SUMIFS(INDEX(NG!$C:$AL,MATCH(Summary!$B92,NG!$B:$B,0),),NG!$C$3:$AL$3,$E$85) -> 5.6458349e+08 | F92: =D92/$F$3 -> 416343.26 | G92: =E92/$G$3 -> 352446.15 | H92: =IFERROR(D92/E92-1,0) -> 0.013640393 | K92: Other Receivables | L92: =SUMIFS(INDEX(Group!$C:$AL, MATCH(Summary!$B92, Group!$B:$B, 0), ),Group!$C$3:$AL$3, Summary!$C$2) -> 5.7265593e+08 | M92: =SUMIFS(INDEX(Group!$C:$AL, MATCH(Summary!$B92, Group!$B:$B, 0), ),Group!$C$3:$AL$3, Summary!$M$85) -> 5.6538926e+08 | N92: =L92/$F$3 -> 416613.39 | O92: =M92/$G$3 -> 352949.16 | P92: =IFERROR(L92/M92-1,0) -> 0.012852502
B93: TOTAL OTHER DEBTORS (RELATED PARTY) | C93: Other Debtors (Related Party) | D93: =SUMIFS(INDEX(NG!$C:$AL, MATCH(Summary!$B93, NG!$B:$B, 0), ),NG!$C$3:$AL$3, Summary!$C$2) -> -1.0899058e+09 | E93: =SUMIFS(INDEX(NG!$C:$AL,MATCH(Summary!$B93,NG!$B:$B,0),),NG!$C$3:$AL$3,$E$85) -> -1.1845275e+09 | F93: =D93/$F$3 -> -792918.3 | G93: =E93/$G$3 -> -739451.59 | H93: =IFERROR(D93/E93-1,0) -> -0.079881356 | K93: Other Debtors (Related Party) | L93: =SUMIFS(INDEX(Group!$C:$AL, MATCH(Summary!$B93, Group!$B:$B, 0), ),Group!$C$3:$AL$3, Summary!$C$2) -> -1.0899058e+09 | M93: =SUMIFS(INDEX(Group!$C:$AL, MATCH(Summary!$B93, Group!$B:$B, 0), ),Group!$C$3:$AL$3, Summary!$M$85) -> -1.1845275e+09 | N93: =L93/$F$3 -> -792918.3 | O93: =M93/$G$3 -> -739451.59 | P93: =IFERROR(L93/M93-1,0) -> -0.079881356
C94: Total Current Asset | D94: =SUM(D87:D93) -> 2.7867643e+09 | E94: =SUM(E87:E93) -> 2.3707686e+09 | F94: =SUM(F87:F93) -> 2027401.2 | G94: =SUM(G87:G93) -> 1479972.9 | H94: =IFERROR(D94/E94-1,0) -> 0.17546873 | K94: Total Current Asset | L94: =SUM(L87:L93) -> 3.0066986e+09 | M94: =SUM(M87:M93) -> 2.5219039e+09 | N94: =SUM(N87:N93) -> 2187405.7 | O94: =SUM(O87:O93) -> 1574320.5 | P94: =IFERROR(L94/M94-1,0) -> 0.19223357
B96: TOTAL PROPERTY, PLANT AND EQUIPMENT | C96: Property, Plant & Equipment | D96: =SUMIFS(INDEX(NG!$C:$AL, MATCH(Summary!$B96, NG!$B:$B, 0), ),NG!$C$3:$AL$3, Summary!$C$2) -> 3.3451628e+08 | E96: =SUMIFS(INDEX(NG!$C:$AL,MATCH(Summary!$B96,NG!$B:$B,0),),NG!$C$3:$AL$3,$E$85) -> 3.2630087e+08 | F96: =D96/$F$3 -> 243364.22 | G96: =E96/$G$3 -> 203696.16 | H96: =IFERROR(D96/E96-1,0) -> 0.02517741 | K96: Property, Plant & Equipment | L96: =SUMIFS(INDEX(Group!$C:$AL, MATCH(Summary!$B96, Group!$B:$B, 0), ),Group!$C$3:$AL$3, Summary!$C$2) -> 3.3832073e+08 | M96: =SUMIFS(INDEX(Group!$C:$AL, MATCH(Summary!$B96, Group!$B:$B, 0), ),Group!$C$3:$AL$3, Summary!$M$85) -> 3.3134369e+08 | N96: =L96/$F$3 -> 246132 | O96: =M96/$G$3 -> 206844.18 | P96: =IFERROR(L96/M96-1,0) -> 0.021056819
B97: TOTAL INTANGIBLE ASSETS | C97: Intangible Asset | D97: =SUMIFS(INDEX(NG!$C:$AL, MATCH(Summary!$B97, NG!$B:$B, 0), ),NG!$C$3:$AL$3, Summary!$C$2) -> 2.425516e+09 | E97: =SUMIFS(INDEX(NG!$C:$AL,MATCH(Summary!$B97,NG!$B:$B,0),),NG!$C$3:$AL$3,$E$85) -> 2.3488014e+09 | F97: =D97/$F$3 -> 1764589.1 | G97: =E97/$G$3 -> 1466259.7 | H97: =IFERROR(D97/E97-1,0) -> 0.032661179 | K97: Intangible Asset | L97: =SUMIFS(INDEX(Group!$C:$AL, MATCH(Summary!$B97, Group!$B:$B, 0), ),Group!$C$3:$AL$3, Summary!$C$2) -> 2.425516e+09 | M97: =SUMIFS(INDEX(Group!$C:$AL, MATCH(Summary!$B97, Group!$B:$B, 0), ),Group!$C$3:$AL$3, Summary!$M$85) -> 2.3488014e+09 | N97: =L97/$F$3 -> 1764589.1 | O97: =M97/$G$3 -> 1466259.7 | P97: =IFERROR(L97/M97-1,0) -> 0.032661179
B98: TOTAL OTHER FIXED ASSET | C98: Other Fixed Asset | D98: =SUMIFS(INDEX(NG!$C:$AL, MATCH(Summary!$B98, NG!$B:$B, 0), ),NG!$C$3:$AL$3, Summary!$C$2) -> 2.7389575e+09 | E98: =SUMIFS(INDEX(NG!$C:$AL,MATCH(Summary!$B98,NG!$B:$B,0),),NG!$C$3:$AL$3,$E$85) -> 2.5553856e+09 | F98: =D98/$F$3 -> 1992621.2 | G98: =E98/$G$3 -> 1595221.7 | H98: =IFERROR(D98/E98-1,0) -> 0.071837242 | K98: Other Fixed Asset | L98: =SUMIFS(INDEX(Group!$C:$AL, MATCH(Summary!$B98, Group!$B:$B, 0), ),Group!$C$3:$AL$3, Summary!$C$2) -> 2.7389575e+09 | M98: =SUMIFS(INDEX(Group!$C:$AL, MATCH(Summary!$B98, Group!$B:$B, 0), ),Group!$C$3:$AL$3, Summary!$M$85) -> 2.5553856e+09 | N98: =L98/$F$3 -> 1992621.2 | O98: =M98/$G$3 -> 1595221.7 | P98: =IFERROR(L98/M98-1,0) -> 0.071837242
C99: Total Non Current Asset | D99: =SUM(D96:D98) -> 5.4989897e+09 | E99: =SUM(E96:E98) -> 5.2304878e+09 | F99: =SUM(F96:F98) -> 4000574.5 | G99: =SUM(G96:G98) -> 3265177.5 | H99: =IFERROR(D99/E99-1,0) -> 0.051334005 | K99: Total Non Current Asset | L99: =SUM(L96:L98) -> 5.5027942e+09 | M99: =SUM(M96:M98) -> 5.2355306e+09 | N99: =SUM(N96:N98) -> 4003342.3 | O99: =SUM(O96:O98) -> 3268325.5 | P99: =IFERROR(L99/M99-1,0) -> 0.051048029
C100: TOTAL ASSET | D100: =D94+D99 -> 8.285754e+09 | E100: =E94+E99 -> 7.6012564e+09 | F100: =F94+F99 -> 6027975.7 | G100: =G94+G99 -> 4745150.4 | H100: =IFERROR(D100/E100-1,0) -> 0.090050592 | K100: TOTAL ASSET | L100: =L94+L99 -> 8.5094927e+09 | M100: =M94+M99 -> 7.7574346e+09 | N100: =N94+N99 -> 6190748 | O100: =O94+O99 -> 4842646 | P100: =IFERROR(L100/M100-1,0) -> 0.096946757
B102: TOTAL ACCOUNTS PAYABLES | C102: Accounts Payables | D102: =SUMIFS(INDEX(NG!$C:$AL, MATCH(Summary!$B102, NG!$B:$B, 0), ),NG!$C$3:$AL$3, Summary!$C$2) -> 3.4872957e+08 | E102: =SUMIFS(INDEX(NG!$C:$AL,MATCH(Summary!$B102,NG!$B:$B,0),),NG!$C$3:$AL$3,$E$85) -> 3.2659823e+08 | F102: =D102/$F$3 -> 253704.54 | G102: =E102/$G$3 -> 203881.78 | H102: =IFERROR(D102/E102-1,0) -> 0.067763197 | K102: Accounts Payables | L102: =SUMIFS(INDEX(Group!$C:$AL, MATCH(Summary!$B102, Group!$B:$B, 0), ),Group!$C$3:$AL$3, Summary!$C$2) -> 3.4872957e+08 | M102: =SUMIFS(INDEX(Group!$C:$AL, MATCH(Summary!$B102, Group!$B:$B, 0), ),Group!$C$3:$AL$3, Summary!$M$85) -> 3.2659823e+08 | N102: =L102/$F$3 -> 253704.54 | O102: =M102/$G$3 -> 203881.78 | P102: =IFERROR(L102/M102-1,0) -> 0.067763197
B103: TOTAL TAXES PAYABLE | C103: Taxes Payable | D103: =SUMIFS(INDEX(NG!$C:$AL, MATCH(Summary!$B103, NG!$B:$B, 0), ),NG!$C$3:$AL$3, Summary!$C$2) -> 79280689 | E103: =SUMIFS(INDEX(NG!$C:$AL,MATCH(Summary!$B103,NG!$B:$B,0),),NG!$C$3:$AL$3,$E$85) -> 30487663 | F103: =D103/$F$3 -> 57677.559 | G103: =E103/$G$3 -> 19032.188 | H103: =IFERROR(D103/E103-1,0) -> 1.6004187 | K103: Taxes Payable | L103: =SUMIFS(INDEX(Group!$C:$AL, MATCH(Summary!$B103, Group!$B:$B, 0), ),Group!$C$3:$AL$3, Summary!$C$2) -> 88400695 | M103: =SUMIFS(INDEX(Group!$C:$AL, MATCH(Summary!$B103, Group!$B:$B, 0), ),Group!$C$3:$AL$3, Summary!$M$85) -> 36449101 | N103: =L103/$F$3 -> 64312.462 | O103: =M103/$G$3 -> 22753.668 | P103: =IFERROR(L103/M103-1,0) -> 1.4253189
B104: TOTAL OTHER PAYABLES (RELATED PARTY) | C104: Other Creditors (Related Party) | D104: =SUMIFS(INDEX(NG!$C:$AL, MATCH(Summary!$B104, NG!$B:$B, 0), ),NG!$C$3:$AL$3, Summary!$C$2) -> 0 | E104: =SUMIFS(INDEX(NG!$C:$AL,MATCH(Summary!$B104,NG!$B:$B,0),),NG!$C$3:$AL$3,$E$85) -> 0 | F104: =D104/$F$3 -> 0 | G104: =E104/$G$3 -> 0 | H104: =IFERROR(D104/E104-1,0) -> 0 | K104: Other Creditors (Related Party) | L104: =SUMIFS(INDEX(Group!$C:$AL, MATCH(Summary!$B104, Group!$B:$B, 0), ),Group!$C$3:$AL$3, Summary!$C$2) -> 4.1459499e+08 | M104: =SUMIFS(INDEX(Group!$C:$AL, MATCH(Summary!$B104, Group!$B:$B, 0), ),Group!$C$3:$AL$3, Summary!$M$85) -> 3.7435919e+08 | N104: =L104/$F$3 -> 301622.34 | O104: =M104/$G$3 -> 233696.98 | P104: =IFERROR(L104/M104-1,0) -> 0.10747911
B105: TOTAL OTHER CURRENT LIABILITIES | C105: Other Current Liabilities | D105: =SUMIFS(INDEX(NG!$C:$AL, MATCH(Summary!$B105, NG!$B:$B, 0), ),NG!$C$3:$AL$3, Summary!$C$2) -> 1.0290697e+09 | E105: =SUMIFS(INDEX(NG!$C:$AL,MATCH(Summary!$B105,NG!$B:$B,0),),NG!$C$3:$AL$3,$E$85) -> 1.1971737e+09 | F105: =D105/$F$3 -> 748659.35 | G105: =E105/$G$3 -> 747346.06 | H105: =IFERROR(D105/E105-1,0) -> -0.14041735 | K105: Other Current Liabilities | L105: =SUMIFS(INDEX(Group!$C:$AL, MATCH(Summary!$B105, Group!$B:$B, 0), ),Group!$C$3:$AL$3, Summary!$C$2) -> 1.1449749e+09 | M105: =SUMIFS(INDEX(Group!$C:$AL, MATCH(Summary!$B105, Group!$B:$B, 0), ),Group!$C$3:$AL$3, Summary!$M$85) -> 1.286813e+09 | N105: =L105/$F$3 -> 832981.61 | O105: =M105/$G$3 -> 803304.21 | P105: =IFERROR(L105/M105-1,0) -> -0.11022436
C106: Total Current Liabilities | D106: =SUM(D102:D105) -> 1.45708e+09 | E106: =SUM(E102:E105) -> 1.5542596e+09 | F106: =SUM(F102:F105) -> 1060041.4 | G106: =SUM(G102:G105) -> 970260.04 | H106: =IFERROR(D106/E106-1,0) -> -0.062524682 | K106: Total Current Liabilities | L106: =SUM(L102:L105) -> 1.9967001e+09 | M106: =SUM(M102:M105) -> 2.0242195e+09 | N106: =SUM(N102:N105) -> 1452620.9 | O106: =SUM(O102:O105) -> 1263636.6 | P106: =IFERROR(L106/M106-1,0) -> -0.013595075
...

Sheet NG
U2: =IF(U$3<=Summary!$C$2,_xlfn.XLOOKUP(NG!$B4,PL_NG!$C:$C,PL_NG!V:V),0) -> 2.0916453e+08 | V2: =IF(V$3<=Summary!$C$2,_xlfn.XLOOKUP(NG!$B4,PL_NG!$C:$C,PL_NG!W:W),0) -> 1.8398851e+08 | W2: =IF(W$3<=Summary!$C$2,_xlfn.XLOOKUP(NG!$B4,PL_NG!$C:$C,PL_NG!X:X),0) -> 4.0119621e+08
C3: 45322 | D3: =EOMONTH(C3,1) -> 45351 | E3: =EOMONTH(D3,1) -> 45382 | F3: =EOMONTH(E3,1) -> 45412 | G3: =EOMONTH(F3,1) -> 45443 | H3: =EOMONTH(G3,1) -> 45473 | I3: =EOMONTH(H3,1) -> 45504 | J3: =EOMONTH(I3,1) -> 45535 | K3: =EOMONTH(J3,1) -> 45565 | ... AL3: =EOMONTH(AK3,1) -> 46387
B4: TOTAL REVENUE | C4: =IF(C$3<=Summary!$C$2,_xlfn.XLOOKUP(NG!$B4,PL_NG!$C:$C,PL_NG!D:D),0) -> 1.7517098e+08 | D4: =IF(D$3<=Summary!$C$2,_xlfn.XLOOKUP(NG!$B4,PL_NG!$C:$C,PL_NG!E:E),0) -> 5.1848939e+08 | E4: =IF(E$3<=Summary!$C$2,_xlfn.XLOOKUP(NG!$B4,PL_NG!$C:$C,PL_NG!F:F),0) -> 5.2701424e+08 | F4: =IF(F$3<=Summary!$C$2,_xlfn.XLOOKUP(NG!$B4,PL_NG!$C:$C,PL_NG!G:G),0) -> 5.4183986e+08 | G4: =IF(G$3<=Summary!$C$2,_xlfn.XLOOKUP(NG!$B4,PL_NG!$C:$C,PL_NG!H:H),0) -> 2.067278e+08 | H4: =IF(H$3<=Summary!$C$2,_xlfn.XLOOKUP(NG!$B4,PL_NG!$C:$C,PL_NG!I:I),0) -> 2.1943995e+08 | I4: =IF(I$3<=Summary!$C$2,_xlfn.XLOOKUP(NG!$B4,PL_NG!$C:$C,PL_NG!J:J),0) -> 2.1383883e+08 | J4: =IF(J$3<=Summary!$C$2,_xlfn.XLOOKUP(NG!$B4,PL_NG!$C:$C,PL_NG!K:K),0) -> 3.1320444e+08 | K4: =IF(K$3<=Summary!$C$2,_xlfn.XLOOKUP(NG!$B4,PL_NG!$C:$C,PL_NG!L:L),0) -> 1.2182022e+08 | L4: =IF(L$3<=Summary!$C$2,_xlfn.XLOOKUP(NG!$B4,PL_NG!$C:$C,PL_NG!M:M),0) -> 1.7337772e+08 | M4: =IF(M$3<=Summary!$C$2,_xlfn.XLOOKUP(NG!$B4,PL_NG!$C:$C,PL_NG!N:N),0) -> 2.2699189e+08 | N4: =IF(N$3<=Summary!$C$2,_xlfn.XLOOKUP(NG!$B4,PL_NG!$C:$C,PL_NG!O:O),0) -> 5.92258e+08 | O4: =IF(O$3<=Summary!$C$2,_xlfn.XLOOKUP(NG!$B4,PL_NG!$C:$C,PL_NG!P:P),0) -> 2.1326861e+08 | P4: =IF(P$3<=Summary!$C$2,_xlfn.XLOOKUP(NG!$B4,PL_NG!$C:$C,PL_NG!Q:Q),0) -> 1.9704868e+08 | Q4: =IF(Q$3<=Summary!$C$2,_xlfn.XLOOKUP(NG!$B4,PL_NG!$C:$C,PL_NG!R:R),0) -> 2.2240303e+08 | R4: =IF(R$3<=Summary!$C$2,_xlfn.XLOOKUP(NG!$B4,PL_NG!$C:$C,PL_NG!S:S),0) -> 2.4270022e+08 | S4: =IF(S$3<=Summary!$C$2,_xlfn.XLOOKUP(NG!$B4,PL_NG!$C:$C,PL_NG!T:T),0) -> 1.7449216e+08 | T4: =IF(T$3<=Summary!$C$2,_xlfn.XLOOKUP(NG!$B4,PL_NG!$C:$C,PL_NG!U:U),0) -> 1.1974094e+08 | U4: =IF(U$3<=Summary!$C$2,_xlfn.XLOOKUP(NG!$B4,PL_NG!$C:$C,PL_NG!V:V),0) -> 2.0916453e+08 | V4: =IF(V$3<=Summary!$C$2,_xlfn.XLOOKUP(NG!$B4,PL_NG!$C:$C,PL_NG!W:W),0) -> 1.8398851e+08 | W4: =IF(W$3<=Summary!$C$2,_xlfn.XLOOKUP(NG!$B4,PL_NG!$C:$C,PL_NG!X:X),0) -> 4.0119621e+08 | X4: =IF(X$3<=Summary!$C$2,_xlfn.XLOOKUP(NG!$B4,PL_NG!$C:$C,PL_NG!Y:Y),0) -> 7.5500317e+08 | Y4: =IF(Y$3<=Summary!$C$2,_xlfn.XLOOKUP(NG!$B4,PL_NG!$C:$C,PL_NG!Z:Z),0) -> 3.2266712e+08 | Z4: =IF(Z$3<=Summary!$C$2,_xlfn.XLOOKUP(NG!$B4,PL_NG!$C:$C,PL_NG!AA:AA),0) -> 3.1213675e+08 | AA4: =IF(AA$3<=Summary!$C$2,_xlfn.XLOOKUP(NG!$B4,PL_NG!$C:$C,PL_NG!AB:AB),0) -> 7.1293977e+08 | AB4: =IF(AB$3<=Summary!$C$2,_xlfn.XLOOKUP(NG!$B4,PL_NG!$C:$C,PL_NG!AC:AC),0) -> 7.5719318e+08 | AC4: =IF(AC$3<=Summary!$C$2,_xlfn.XLOOKUP(NG!$B4,PL_NG!$C:$C,PL_NG!AD:AD),0) -> 5.4911753e+08 | AD4: =IF(AD$3<=Summary!$C$2,_xlfn.XLOOKUP(NG!$B4,PL_NG!$C:$C,PL_NG!AE:AE),0) -> 3.4442948e+08 | AE4: =IF(AE$3<=Summary!$C$2,_xlfn.XLOOKUP(NG!$B4,PL_NG!$C:$C,PL_NG!AF:AF),0) -> 0 | AF4: =IF(AF$3<=Summary!$C$2,_xlfn.XLOOKUP(NG!$B4,PL_NG!$C:$C,PL_NG!AG:AG),0) -> 0 | AG4: =IF(AG$3<=Summary!$C$2,_xlfn.XLOOKUP(NG!$B4,PL_NG!$C:$C,PL_NG!AH:AH),0) -> 0 | AH4: =IF(AH$3<=Summary!$C$2,_xlfn.XLOOKUP(NG!$B4,PL_NG!$C:$C,PL_NG!AI:AI),0) -> 0 | AI4: =IF(AI$3<=Summary!$C$2,_xlfn.XLOOKUP(NG!$B4,PL_NG!$C:$C,PL_NG!AJ:AJ),0) -> 0 | AJ4: =IF(AJ$3<=Summary!$C$2,_xlfn.XLOOKUP(NG!$B4,PL_NG!$C:$C,PL_NG!AK:AK),0) -> 0 | AK4: =IF(AK$3<=Summary!$C$2,_xlfn.XLOOKUP(NG!$B4,PL_NG!$C:$C,PL_NG!AL:AL),0) -> 0 | AL4: =IF(AL$3<=Summary!$C$2,_xlfn.XLOOKUP(NG!$B4,PL_NG!$C:$C,PL_NG!AM:AM),0) -> 0
B5: TOTAL COST OF SALES | C5: =IF(C$3<=Summary!$C$2,_xlfn.XLOOKUP(NG!$B5,PL_NG!$C:$C,PL_NG!D:D),0) -> -83261122 | D5: =IF(D$3<=Summary!$C$2,_xlfn.XLOOKUP(NG!$B5,PL_NG!$C:$C,PL_NG!E:E),0) -> -1.0207195e+08 | E5: =IF(E$3<=Summary!$C$2,_xlfn.XLOOKUP(NG!$B5,PL_NG!$C:$C,PL_NG!F:F),0) -> -1.303486e+08 | F5: =IF(F$3<=Summary!$C$2,_xlfn.XLOOKUP(NG!$B5,PL_NG!$C:$C,PL_NG!G:G),0) -> -1.5508989e+08 | G5: =IF(G$3<=Summary!$C$2,_xlfn.XLOOKUP(NG!$B5,PL_NG!$C:$C,PL_NG!H:H),0) -> -1.8365757e+08 | H5: =IF(H$3<=Summary!$C$2,_xlfn.XLOOKUP(NG!$B5,PL_NG!$C:$C,PL_NG!I:I),0) -> -73738085 | I5: =IF(I$3<=Summary!$C$2,_xlfn.XLOOKUP(NG!$B5,PL_NG!$C:$C,PL_NG!J:J),0) -> -63584964 | J5: =IF(J$3<=Summary!$C$2,_xlfn.XLOOKUP(NG!$B5,PL_NG!$C:$C,PL_NG!K:K),0) -> -1.5667029e+08 | K5: =IF(K$3<=Summary!$C$2,_xlfn.XLOOKUP(NG!$B5,PL_NG!$C:$C,PL_NG!L:L),0) -> -80126589 | L5: =IF(L$3<=Summary!$C$2,_xlfn.XLOOKUP(NG!$B5,PL_NG!$C:$C,PL_NG!M:M),0) -> -78233709 | M5: =IF(M$3<=Summary!$C$2,_xlfn.XLOOKUP(NG!$B5,PL_NG!$C:$C,PL_NG!N:N),0) -> -87318733 | N5: =IF(N$3<=Summary!$C$2,_xlfn.XLOOKUP(NG!$B5,PL_NG!$C:$C,PL_NG!O:O),0) -> -1.0404002e+08 | O5: =IF(O$3<=Summary!$C$2,_xlfn.XLOOKUP(NG!$B5,PL_NG!$C:$C,PL_NG!P:P),0) -> -72177218 | P5: =IF(P$3<=Summary!$C$2,_xlfn.XLOOKUP(NG!$B5,PL_NG!$C:$C,PL_NG!Q:Q),0) -> -52445967 | Q5: =IF(Q$3<=Summary!$C$2,_xlfn.XLOOKUP(NG!$B5,PL_NG!$C:$C,PL_NG!R:R),0) -> -56447543 | R5: =IF(R$3<=Summary!$C$2,_xlfn.XLOOKUP(NG!$B5,PL_NG!$C:$C,PL_NG!S:S),0) -> -57526259 | S5: =IF(S$3<=Summary!$C$2,_xlfn.XLOOKUP(NG!$B5,PL_NG!$C:$C,PL_NG!T:T),0) -> -67775465 | T5: =IF(T$3<=Summary!$C$2,_xlfn.XLOOKUP(NG!$B5,PL_NG!$C:$C,PL_NG!U:U),0) -> -62498337 | U5: =IF(U$3<=Summary!$C$2,_xlfn.XLOOKUP(NG!$B5,PL_NG!$C:$C,PL_NG!V:V),0) -> -1.0371963e+08 | V5: =IF(V$3<=Summary!$C$2,_xlfn.XLOOKUP(NG!$B5,PL_NG!$C:$C,PL_NG!W:W),0) -> 9725952.2 | W5: =IF(W$3<=Summary!$C$2,_xlfn.XLOOKUP(NG!$B5,PL_NG!$C:$C,PL_NG!X:X),0) -> -1.0742246e+08 | X5: =IF(X$3<=Summary!$C$2,_xlfn.XLOOKUP(NG!$B5,PL_NG!$C:$C,PL_NG!Y:Y),0) -> -75931737 | Y5: =IF(Y$3<=Summary!$C$2,_xlfn.XLOOKUP(NG!$B5,PL_NG!$C:$C,PL_NG!Z:Z),0) -> -62873576 | Z5: =IF(Z$3<=Summary!$C$2,_xlfn.XLOOKUP(NG!$B5,PL_NG!$C:$C,PL_NG!AA:AA),0) -> -1.4672293e+08 | AA5: =IF(AA$3<=Summary!$C$2,_xlfn.XLOOKUP(NG!$B5,PL_NG!$C:$C,PL_NG!AB:AB),0) -> -1.5200236e+08 | AB5: =IF(AB$3<=Summary!$C$2,_xlfn.XLOOKUP(NG!$B5,PL_NG!$C:$C,PL_NG!AC:AC),0) -> -1.4038357e+08 | AC5: =IF(AC$3<=Summary!$C$2,_xlfn.XLOOKUP(NG!$B5,PL_NG!$C:$C,PL_NG!AD:AD),0) -> -1.4172901e+08 | AD5: =IF(AD$3<=Summary!$C$2,_xlfn.XLOOKUP(NG!$B5,PL_NG!$C:$C,PL_NG!AE:AE),0) -> -71143523 | AE5: =IF(AE$3<=Summary!$C$2,_xlfn.XLOOKUP(NG!$B5,PL_NG!$C:$C,PL_NG!AF:AF),0) -> 0 | AF5: =IF(AF$3<=Summary!$C$2,_xlfn.XLOOKUP(NG!$B5,PL_NG!$C:$C,PL_NG!AG:AG),0) -> 0 | AG5: =IF(AG$3<=Summary!$C$2,_xlfn.XLOOKUP(NG!$B5,PL_NG!$C:$C,PL_NG!AH:AH),0) -> 0 | AH5: =IF(AH$3<=Summary!$C$2,_xlfn.XLOOKUP(NG!$B5,PL_NG!$C:$C,PL_NG!AI:AI),0) -> 0 | AI5: =IF(AI$3<=Summary!$C$2,_xlfn.XLOOKUP(NG!$B5,PL_NG!$C:$C,PL_NG!AJ:AJ),0) -> 0 | AJ5: =IF(AJ$3<=Summary!$C$2,_xlfn.XLOOKUP(NG!$B5,PL_NG!$C:$C,PL_NG!AK:AK),0) -> 0 | AK5: =IF(AK$3<=Summary!$C$2,_xlfn.XLOOKUP(NG!$B5,PL_NG!$C:$C,PL_NG!AL:AL),0) -> 0 | AL5: =IF(AL$3<=Summary!$C$2,_xlfn.XLOOKUP(NG!$B5,PL_NG!$C:$C,PL_NG!AM:AM),0) -> 0
A6: 3.8049509e+08 | B6: TOTAL OTHER REVENUE | C6: =IF(C$3<=Summary!$C$2,_xlfn.XLOOKUP(NG!$B6,PL_NG!$C:$C,PL_NG!D:D),0) -> 54873.98 | D6: =IF(D$3<=Summary!$C$2,_xlfn.XLOOKUP(NG!$B6,PL_NG!$C:$C,PL_NG!E:E),0) -> 28793.59 | E6: =IF(E$3<=Summary!$C$2,_xlfn.XLOOKUP(NG!$B6,PL_NG!$C:$C,PL_NG!F:F),0) -> 36275.65 | F6: =IF(F$3<=Summary!$C$2,_xlfn.XLOOKUP(NG!$B6,PL_NG!$C:$C,PL_NG!G:G),0) -> 308917.02 | G6: =IF(G$3<=Summary!$C$2,_xlfn.XLOOKUP(NG!$B6,PL_NG!$C:$C,PL_NG!H:H),0) -> 9570381.1 | H6: =IF(H$3<=Summary!$C$2,_xlfn.XLOOKUP(NG!$B6,PL_NG!$C:$C,PL_NG!I:I),0) -> 33173690 | I6: =IF(I$3<=Summary!$C$2,_xlfn.XLOOKUP(NG!$B6,PL_NG!$C:$C,PL_NG!J:J),0) -> 31628524 | J6: =IF(J$3<=Summary!$C$2,_xlfn.XLOOKUP(NG!$B6,PL_NG!$C:$C,PL_NG!K:K),0) -> 33151885 | K6: =IF(K$3<=Summary!$C$2,_xlfn.XLOOKUP(NG!$B6,PL_NG!$C:$C,PL_NG!L:L),0) -> 2841293 | L6: =IF(L$3<=Summary!$C$2,_xlfn.XLOOKUP(NG!$B6,PL_NG!$C:$C,PL_NG!M:M),0) -> 77487952 | M6: =IF(M$3<=Summary!$C$2,_xlfn.XLOOKUP(NG!$B6,PL_NG!$C:$C,PL_NG!N:N),0) -> 41107532 | N6: =IF(N$3<=Summary!$C$2,_xlfn.XLOOKUP(NG!$B6,PL_NG!$C:$C,PL_NG!O:O),0) -> 43432413 | O6: =IF(O$3<=Summary!$C$2,_xlfn.XLOOKUP(NG!$B6,PL_NG!$C:$C,PL_NG!P:P),0) -> 39006804 | P6: =IF(P$3<=Summary!$C$2,_xlfn.XLOOKUP(NG!$B6,PL_NG!$C:$C,PL_NG!Q:Q),0) -> 31301634 | Q6: =IF(Q$3<=Summary!$C$2,_xlfn.XLOOKUP(NG!$B6,PL_NG!$C:$C,PL_NG!R:R),0) -> 28246672 | R6: =IF(R$3<=Summary!$C$2,_xlfn.XLOOKUP(NG!$B6,PL_NG!$C:$C,PL_NG!S:S),0) -> 29699520 | S6: =IF(S$3<=Summary!$C$2,_xlfn.XLOOKUP(NG!$B6,PL_NG!$C:$C,PL_NG!T:T),0) -> 23109999 | T6: =IF(T$3<=Summary!$C$2,_xlfn.XLOOKUP(NG!$B6,PL_NG!$C:$C,PL_NG!U:U),0) -> 21501586 | U6: =IF(U$3<=Summary!$C$2,_xlfn.XLOOKUP(NG!$B6,PL_NG!$C:$C,PL_NG!V:V),0) -> 21339894 | V6: =IF(V$3<=Summary!$C$2,_xlfn.XLOOKUP(NG!$B6,PL_NG!$C:$C,PL_NG!W:W),0) -> 31930751 | W6: =IF(W$3<=Summary!$C$2,_xlfn.XLOOKUP(NG!$B6,PL_NG!$C:$C,PL_NG!X:X),0) -> 15620184 | X6: =IF(X$3<=Summary!$C$2,_xlfn.XLOOKUP(NG!$B6,PL_NG!$C:$C,PL_NG!Y:Y),0) -> 16531444 | Y6: =IF(Y$3<=Summary!$C$2,_xlfn.XLOOKUP(NG!$B6,PL_NG!$C:$C,PL_NG!Z:Z),0) -> 16189960 | Z6: =IF(Z$3<=Summary!$C$2,_xlfn.XLOOKUP(NG!$B6,PL_NG!$C:$C,PL_NG!AA:AA),0) -> 1.3506537e+08 | AA6: =IF(AA$3<=Summary!$C$2,_xlfn.XLOOKUP(NG!$B6,PL_NG!$C:$C,PL_NG!AB:AB),0) -> 5399535.4 | AB6: =IF(AB$3<=Summary!$C$2,_xlfn.XLOOKUP(NG!$B6,PL_NG!$C:$C,PL_NG!AC:AC),0) -> 22316487 | AC6: =IF(AC$3<=Summary!$C$2,_xlfn.XLOOKUP(NG!$B6,PL_NG!$C:$C,PL_NG!AD:AD),0) -> -18478033 | AD6: =IF(AD$3<=Summary!$C$2,_xlfn.XLOOKUP(NG!$B6,PL_NG!$C:$C,PL_NG!AE:AE),0) -> 63198520 | AE6: =IF(AE$3<=Summary!$C$2,_xlfn.XLOOKUP(NG!$B6,PL_NG!$C:$C,PL_NG!AF:AF),0) -> 0 | AF6: =IF(AF$3<=Summary!$C$2,_xlfn.XLOOKUP(NG!$B6,PL_NG!$C:$C,PL_NG!AG:AG),0) -> 0 | AG6: =IF(AG$3<=Summary!$C$2,_xlfn.XLOOKUP(NG!$B6,PL_NG!$C:$C,PL_NG!AH:AH),0) -> 0 | AH6: =IF(AH$3<=Summary!$C$2,_xlfn.XLOOKUP(NG!$B6,PL_NG!$C:$C,PL_NG!AI:AI),0) -> 0 | AI6: =IF(AI$3<=Summary!$C$2,_xlfn.XLOOKUP(NG!$B6,PL_NG!$C:$C,PL_NG!AJ:AJ),0) -> 0 | AJ6: =IF(AJ$3<=Summary!$C$2,_xlfn.XLOOKUP(NG!$B6,PL_NG!$C:$C,PL_NG!AK:AK),0) -> 0 | AK6: =IF(AK$3<=Summary!$C$2,_xlfn.XLOOKUP(NG!$B6,PL_NG!$C:$C,PL_NG!AL:AL),0) -> 0 | AL6: =IF(AL$3<=Summary!$C$2,_xlfn.XLOOKUP(NG!$B6,PL_NG!$C:$C,PL_NG!AM:AM),0) -> 0
A7: 13716119 | B7: TOTAL OPERATING EXPENSES | C7: =IF(C$3<=Summary!$C$2,_xlfn.XLOOKUP(NG!$B7,PL_NG!$C:$C,PL_NG!D:D),0) -> -1.0754466e+08 | D7: =IF(D$3<=Summary!$C$2,_xlfn.XLOOKUP(NG!$B7,PL_NG!$C:$C,PL_NG!E:E),0) -> -98190212 | E7: =IF(E$3<=Summary!$C$2,_xlfn.XLOOKUP(NG!$B7,PL_NG!$C:$C,PL_NG!F:F),0) -> -1.3064742e+08 | F7: =IF(F$3<=Summary!$C$2,_xlfn.XLOOKUP(NG!$B7,PL_NG!$C:$C,PL_NG!G:G),0) -> -1.404921e+08 | G7: =IF(G$3<=Summary!$C$2,_xlfn.XLOOKUP(NG!$B7,PL_NG!$C:$C,PL_NG!H:H),0) -> -2.367973e+08 | H7: =IF(H$3<=Summary!$C$2,_xlfn.XLOOKUP(NG!$B7,PL_NG!$C:$C,PL_NG!I:I),0) -> -2.6473028e+08 | I7: =IF(I$3<=Summary!$C$2,_xlfn.XLOOKUP(NG!$B7,PL_NG!$C:$C,PL_NG!J:J),0) -> -2.1825787e+08 | J7: =IF(J$3<=Summary!$C$2,_xlfn.XLOOKUP(NG!$B7,PL_NG!$C:$C,PL_NG!K:K),0) -> -1.0862124e+08 | K7: =IF(K$3<=Summary!$C$2,_xlfn.XLOOKUP(NG!$B7,PL_NG!$C:$C,PL_NG!L:L),0) -> -61752847 | L7: =IF(L$3<=Summary!$C$2,_xlfn.XLOOKUP(NG!$B7,PL_NG!$C:$C,PL_NG!M:M),0) -> -4.3569865e+08 | M7: =IF(M$3<=Summary!$C$2,_xlfn.XLOOKUP(NG!$B7,PL_NG!$C:$C,PL_NG!N:N),0) -> -4.107843e+08 | N7: =IF(N$3<=Summary!$C$2,_xlfn.XLOOKUP(NG!$B7,PL_NG!$C:$C,PL_NG!O:O),0) -> -5.2302543e+08 | O7: =IF(O$3<=Summary!$C$2,_xlfn.XLOOKUP(NG!$B7,PL_NG!$C:$C,PL_NG!P:P),0) -> -1.9283026e+08 | P7: =IF(P$3<=Summary!$C$2,_xlfn.XLOOKUP(NG!$B7,PL_NG!$C:$C,PL_NG!Q:Q),0) -> -2.1932431e+08 | Q7: =IF(Q$3<=Summary!$C$2,_xlfn.XLOOKUP(NG!$B7,PL_NG!$C:$C,PL_NG!R:R),0) -> -1.9066781e+08 | R7: =IF(R$3<=Summary!$C$2,_xlfn.XLOOKUP(NG!$B7,PL_NG!$C:$C,PL_NG!S:S),0) -> -96908036 | S7: =IF(S$3<=Summary!$C$2,_xlfn.XLOOKUP(NG!$B7,PL_NG!$C:$C,PL_NG!T:T),0) -> -3.9144955e+08 | T7: =IF(T$3<=Summary!$C$2,_xlfn.XLOOKUP(NG!$B7,PL_NG!$C:$C,PL_NG!U:U),0) -> -3.2246172e+08 | U7: =IF(U$3<=Summary!$C$2,_xlfn.XLOOKUP(NG!$B7,PL_NG!$C:$C,PL_NG!V:V),0) -> -2.8351007e+08 | V7: =IF(V$3<=Summary!$C$2,_xlfn.XLOOKUP(NG!$B7,PL_NG!$C:$C,PL_NG!W:W),0) -> -2.5699323e+08 | W7: =IF(W$3<=Summary!$C$2,_xlfn.XLOOKUP(NG!$B7,PL_NG!$C:$C,PL_NG!X:X),0) -> -4.3838489e+08 | X7: =IF(X$3<=Summary!$C$2,_xlfn.XLOOKUP(NG!$B7,PL_NG!$C:$C,PL_NG!Y:Y),0) -> -3.2583244e+08 | Y7: =IF(Y$3<=Summary!$C$2,_xlfn.XLOOKUP(NG!$B7,PL_NG!$C:$C,PL_NG!Z:Z),0) -> -3.0577045e+08 | Z7: =IF(Z$3<=Summary!$C$2,_xlfn.XLOOKUP(NG!$B7,PL_NG!$C:$C,PL_NG!AA:AA),0) -> -1.0351769e+09 | AA7: =IF(AA$3<=Summary!$C$2,_xlfn.XLOOKUP(NG!$B7,PL_NG!$C:$C,PL_NG!AB:AB),0) -> -2.9690634e+08 | AB7: =IF(AB$3<=Summary!$C$2,_xlfn.XLOOKUP(NG!$B7,PL_NG!$C:$C,PL_NG!AC:AC),0) -> -2.7563622e+08 | AC7: =IF(AC$3<=Summary!$C$2,_xlfn.XLOOKUP(NG!$B7,PL_NG!$C:$C,PL_NG!AD:AD),0) -> -2.4194446e+08 | AD7: =IF(AD$3<=Summary!$C$2,_xlfn.XLOOKUP(NG!$B7,PL_NG!$C:$C,PL_NG!AE:AE),0) -> -2.3908358e+08 | AE7: =IF(AE$3<=Summary!$C$2,_xlfn.XLOOKUP(NG!$B7,PL_NG!$C:$C,PL_NG!AF:AF),0) -> 0 | AF7: =IF(AF$3<=Summary!$C$2,_xlfn.XLOOKUP(NG!$B7,PL_NG!$C:$C,PL_NG!AG:AG),0) -> 0 | AG7: =IF(AG$3<=Summary!$C$2,_xlfn.XLOOKUP(NG!$B7,PL_NG!$C:$C,PL_NG!AH:AH),0) -> 0 | AH7: =IF(AH$3<=Summary!$C$2,_xlfn.XLOOKUP(NG!$B7,PL_NG!$C:$C,PL_NG!AI:AI),0) -> 0 | AI7: =IF(AI$3<=Summary!$C$2,_xlfn.XLOOKUP(NG!$B7,PL_NG!$C:$C,PL_NG!AJ:AJ),0) -> 0 | AJ7: =IF(AJ$3<=Summary!$C$2,_xlfn.XLOOKUP(NG!$B7,PL_NG!$C:$C,PL_NG!AK:AK),0) -> 0 | AK7: =IF(AK$3<=Summary!$C$2,_xlfn.XLOOKUP(NG!$B7,PL_NG!$C:$C,PL_NG!AL:AL),0) -> 0 | AL7: =IF(AL$3<=Summary!$C$2,_xlfn.XLOOKUP(NG!$B7,PL_NG!$C:$C,PL_NG!AM:AM),0) -> 0
A8: =A6+A7 -> 3.9421121e+08 | B8: TOTAL DEPRECIATION & AMORTISATION | C8: =IF(C$3<=Summary!$C$2,_xlfn.XLOOKUP(NG!$B8,PL_NG!$C:$C,PL_NG!D:D),0) -> -2883128.6 | D8: =IF(D$3<=Summary!$C$2,_xlfn.XLOOKUP(NG!$B8,PL_NG!$C:$C,PL_NG!E:E),0) -> -3092261.8 | E8: =IF(E$3<=Summary!$C$2,_xlfn.XLOOKUP(NG!$B8,PL_NG!$C:$C,PL_NG!F:F),0) -> -2791404 | F8: =IF(F$3<=Summary!$C$2,_xlfn.XLOOKUP(NG!$B8,PL_NG!$C:$C,PL_NG!G:G),0) -> -2466666.5 | G8: =IF(G$3<=Summary!$C$2,_xlfn.XLOOKUP(NG!$B8,PL_NG!$C:$C,PL_NG!H:H),0) -> -2852194 | H8: =IF(H$3<=Summary!$C$2,_xlfn.XLOOKUP(NG!$B8,PL_NG!$C:$C,PL_NG!I:I),0) -> -3230819.9 | I8: =IF(I$3<=Summary!$C$2,_xlfn.XLOOKUP(NG!$B8,PL_NG!$C:$C,PL_NG!J:J),0) -> -3043818.7 | J8: =IF(J$3<=Summary!$C$2,_xlfn.XLOOKUP(NG!$B8,PL_NG!$C:$C,PL_NG!K:K),0) -> -4240446.2 | K8: =IF(K$3<=Summary!$C$2,_xlfn.XLOOKUP(NG!$B8,PL_NG!$C:$C,PL_NG!L:L),0) -> -4195644.7 | L8: =IF(L$3<=Summary!$C$2,_xlfn.XLOOKUP(NG!$B8,PL_NG!$C:$C,PL_NG!M:M),0) -> -4361665.9 | M8: =IF(M$3<=Summary!$C$2,_xlfn.XLOOKUP(NG!$B8,PL_NG!$C:$C,PL_NG!N:N),0) -> -4486868.4 | N8: =IF(N$3<=Summary!$C$2,_xlfn.XLOOKUP(NG!$B8,PL_NG!$C:$C,PL_NG!O:O),0) -> -4477281.8 | O8: =IF(O$3<=Summary!$C$2,_xlfn.XLOOKUP(NG!$B8,PL_NG!$C:$C,PL_NG!P:P),0) -> -4543051 | P8: =IF(P$3<=Summary!$C$2,_xlfn.XLOOKUP(NG!$B8,PL_NG!$C:$C,PL_NG!Q:Q),0) -> -4808597.7 | Q8: =IF(Q$3<=Summary!$C$2,_xlfn.XLOOKUP(NG!$B8,PL_NG!$C:$C,PL_NG!R:R),0) -> -4836131.7 | R8: =IF(R$3<=Summary!$C$2,_xlfn.XLOOKUP(NG!$B8,PL_NG!$C:$C,PL_NG!S:S),0) -> -4829799.5 | S8: =IF(S$3<=Summary!$C$2,_xlfn.XLOOKUP(NG!$B8,PL_NG!$C:$C,PL_NG!T:T),0) -> -4837481.2 | T8: =IF(T$3<=Summary!$C$2,_xlfn.XLOOKUP(NG!$B8,PL_NG!$C:$C,PL_NG!U:U),0) -> -4837481.2 | U8: =IF(U$3<=Summary!$C$2,_xlfn.XLOOKUP(NG!$B8,PL_NG!$C:$C,PL_NG!V:V),0) -> -7470963.8 | V8: =IF(V$3<=Summary!$C$2,_xlfn.XLOOKUP(NG!$B8,PL_NG!$C:$C,PL_NG!W:W),0) -> -6389594.9 | W8: =IF(W$3<=Summary!$C$2,_xlfn.XLOOKUP(NG!$B8,PL_NG!$C:$C,PL_NG!X:X),0) -> -6356357.1 | X8: =IF(X$3<=Summary!$C$2,_xlfn.XLOOKUP(NG!$B8,PL_NG!$C:$C,PL_NG!Y:Y),0) -> -6349940.4 | Y8: =IF(Y$3<=Summary!$C$2,_xlfn.XLOOKUP(NG!$B8,PL_NG!$C:$C,PL_NG!Z:Z),0) -> -6565088.8 | Z8: =IF(Z$3<=Summary!$C$2,_xlfn.XLOOKUP(NG!$B8,PL_NG!$C:$C,PL_NG!AA:AA),0) -> -6608072.1 | AA8: =IF(AA$3<=Summary!$C$2,_xlfn.XLOOKUP(NG!$B8,PL_NG!$C:$C,PL_NG!AB:AB),0) -> -12176015 | AB8: =IF(AB$3<=Summary!$C$2,_xlfn.XLOOKUP(NG!$B8,PL_NG!$C:$C,PL_NG!AC:AC),0) -> -12299363 | AC8: =IF(AC$3<=Summary!$C$2,_xlfn.XLOOKUP(NG!$B8,PL_NG!$C:$C,PL_NG!AD:AD),0) -> -12082020 | AD8: =IF(AD$3<=Summary!$C$2,_xlfn.XLOOKUP(NG!$B8,PL_NG!$C:$C,PL_NG!AE:AE),0) -> -12303124 | AE8: =IF(AE$3<=Summary!$C$2,_xlfn.XLOOKUP(NG!$B8,PL_NG!$C:$C,PL_NG!AF:AF),0) -> 0 | AF8: =IF(AF$3<=Summary!$C$2,_xlfn.XLOOKUP(NG!$B8,PL_NG!$C:$C,PL_NG!AG:AG),0) -> 0 | AG8: =IF(AG$3<=Summary!$C$2,_xlfn.XLOOKUP(NG!$B8,PL_NG!$C:$C,PL_NG!AH:AH),0) -> 0 | AH8: =IF(AH$3<=Summary!$C$2,_xlfn.XLOOKUP(NG!$B8,PL_NG!$C:$C,PL_NG!AI:AI),0) -> 0 | AI8: =IF(AI$3<=Summary!$C$2,_xlfn.XLOOKUP(NG!$B8,PL_NG!$C:$C,PL_NG!AJ:AJ),0) -> 0 | AJ8: =IF(AJ$3<=Summary!$C$2,_xlfn.XLOOKUP(NG!$B8,PL_NG!$C:$C,PL_NG!AK:AK),0) -> 0 | AK8: =IF(AK$3<=Summary!$C$2,_xlfn.XLOOKUP(NG!$B8,PL_NG!$C:$C,PL_NG!AL:AL),0) -> 0 | AL8: =IF(AL$3<=Summary!$C$2,_xlfn.XLOOKUP(NG!$B8,PL_NG!$C:$C,PL_NG!AM:AM),0) -> 0
A9: 4.5453379e+08 | B9: TOTAL INTEREST EXPENSES | C9: =IF(C$3<=Summary!$C$2,_xlfn.XLOOKUP(NG!$B9,PL_NG!$C:$C,PL_NG!D:D),0) -> 0 | D9: =IF(D$3<=Summary!$C$2,_xlfn.XLOOKUP(NG!$B9,PL_NG!$C:$C,PL_NG!E:E),0) -> -321442.6 | E9: =IF(E$3<=Summary!$C$2,_xlfn.XLOOKUP(NG!$B9,PL_NG!$C:$C,PL_NG!F:F),0) -> -1014508.5 | F9: =IF(F$3<=Summary!$C$2,_xlfn.XLOOKUP(NG!$B9,PL_NG!$C:$C,PL_NG!G:G),0) -> 0 | G9: =IF(G$3<=Summary!$C$2,_xlfn.XLOOKUP(NG!$B9,PL_NG!$C:$C,PL_NG!H:H),0) -> 0 | H9: =IF(H$3<=Summary!$C$2,_xlfn.XLOOKUP(NG!$B9,PL_NG!$C:$C,PL_NG!I:I),0) -> 0 | I9: =IF(I$3<=Summary!$C$2,_xlfn.XLOOKUP(NG!$B9,PL_NG!$C:$C,PL_NG!J:J),0) -> 0 | J9: =IF(J$3<=Summary!$C$2,_xlfn.XLOOKUP(NG!$B9,PL_NG!$C:$C,PL_NG!K:K),0) -> 0 | K9: =IF(K$3<=Summary!$C$2,_xlfn.XLOOKUP(NG!$B9,PL_NG!$C:$C,PL_NG!L:L),0) -> 0 | L9: =IF(L$3<=Summary!$C$2,_xlfn.XLOOKUP(NG!$B9,PL_NG!$C:$C,PL_NG!M:M),0) -> 0 | M9: =IF(M$3<=Summary!$C$2,_xlfn.XLOOKUP(NG!$B9,PL_NG!$C:$C,PL_NG!N:N),0) -> 0 | N9: =IF(N$3<=Summary!$C$2,_xlfn.XLOOKUP(NG!$B9,PL_NG!$C:$C,PL_NG!O:O),0) -> 0 | O9: =IF(O$3<=Summary!$C$2,_xlfn.XLOOKUP(NG!$B9,PL_NG!$C:$C,PL_NG!P:P),0) -> 0 | P9: =IF(P$3<=Summary!$C$2,_xlfn.XLOOKUP(NG!$B9,PL_NG!$C:$C,PL_NG!Q:Q),0) -> 0 | Q9: =IF(Q$3<=Summary!$C$2,_xlfn.XLOOKUP(NG!$B9,PL_NG!$C:$C,PL_NG!R:R),0) -> 0 | R9: =IF(R$3<=Summary!$C$2,_xlfn.XLOOKUP(NG!$B9,PL_NG!$C:$C,PL_NG!S:S),0) -> 0 | S9: =IF(S$3<=Summary!$C$2,_xlfn.XLOOKUP(NG!$B9,PL_NG!$C:$C,PL_NG!T:T),0) -> -144180000 | T9: =IF(T$3<=Summary!$C$2,_xlfn.XLOOKUP(NG!$B9,PL_NG!$C:$C,PL_NG!U:U),0) -> 0 | U9: =IF(U$3<=Summary!$C$2,_xlfn.XLOOKUP(NG!$B9,PL_NG!$C:$C,PL_NG!V:V),0) -> 0 | V9: =IF(V$3<=Summary!$C$2,_xlfn.XLOOKUP(NG!$B9,PL_NG!$C:$C,PL_NG!W:W),0) -> 0 | W9: =IF(W$3<=Summary!$C$2,_xlfn.XLOOKUP(NG!$B9,PL_NG!$C:$C,PL_NG!X:X),0) -> 0 | X9: =IF(X$3<=Summary!$C$2,_xlfn.XLOOKUP(NG!$B9,PL_NG!$C:$C,PL_NG!Y:Y),0) -> -134088144 | Y9: =IF(Y$3<=Summary!$C$2,_xlfn.XLOOKUP(NG!$B9,PL_NG!$C:$C,PL_NG!Z:Z),0) -> 0 | Z9: =IF(Z$3<=Summary!$C$2,_xlfn.XLOOKUP(NG!$B9,PL_NG!$C:$C,PL_NG!AA:AA),0) -> 0 | AA9: =IF(AA$3<=Summary!$C$2,_xlfn.XLOOKUP(NG!$B9,PL_NG!$C:$C,PL_NG!AB:AB),0) -> 0 | AB9: =IF(AB$3<=Summary!$C$2,_xlfn.XLOOKUP(NG!$B9,PL_NG!$C:$C,PL_NG!AC:AC),0) -> 0 | AC9: =IF(AC$3<=Summary!$C$2,_xlfn.XLOOKUP(NG!$B9,PL_NG!$C:$C,PL_NG!AD:AD),0) -> 0 | AD9: =IF(AD$3<=Summary!$C$2,_xlfn.XLOOKUP(NG!$B9,PL_NG!$C:$C,PL_NG!AE:AE),0) -> 0 | AE9: =IF(AE$3<=Summary!$C$2,_xlfn.XLOOKUP(NG!$B9,PL_NG!$C:$C,PL_NG!AF:AF),0) -> 0 | AF9: =IF(AF$3<=Summary!$C$2,_xlfn.XLOOKUP(NG!$B9,PL_NG!$C:$C,PL_NG!AG:AG),0) -> 0 | AG9: =IF(AG$3<=Summary!$C$2,_xlfn.XLOOKUP(NG!$B9,PL_NG!$C:$C,PL_NG!AH:AH),0) -> 0 | AH9: =IF(AH$3<=Summary!$C$2,_xlfn.XLOOKUP(NG!$B9,PL_NG!$C:$C,PL_NG!AI:AI),0) -> 0 | AI9: =IF(AI$3<=Summary!$C$2,_xlfn.XLOOKUP(NG!$B9,PL_NG!$C:$C,PL_NG!AJ:AJ),0) -> 0 | AJ9: =IF(AJ$3<=Summary!$C$2,_xlfn.XLOOKUP(NG!$B9,PL_NG!$C:$C,PL_NG!AK:AK),0) -> 0 | AK9: =IF(AK$3<=Summary!$C$2,_xlfn.XLOOKUP(NG!$B9,PL_NG!$C:$C,PL_NG!AL:AL),0) -> 0 | AL9: =IF(AL$3<=Summary!$C$2,_xlfn.XLOOKUP(NG!$B9,PL_NG!$C:$C,PL_NG!AM:AM),0) -> 0
B10: TOTAL TAX EXPENSES | C10: =IF(C$3<=Summary!$C$2,_xlfn.XLOOKUP(NG!$B10,PL_NG!$C:$C,PL_NG!D:D),0) -> 0 | D10: =IF(D$3<=Summary!$C$2,_xlfn.XLOOKUP(NG!$B10,PL_NG!$C:$C,PL_NG!E:E),0) -> 0 | E10: =IF(E$3<=Summary!$C$2,_xlfn.XLOOKUP(NG!$B10,PL_NG!$C:$C,PL_NG!F:F),0) -> 0 | F10: =IF(F$3<=Summary!$C$2,_xlfn.XLOOKUP(NG!$B10,PL_NG!$C:$C,PL_NG!G:G),0) -> 0 | G10: =IF(G$3<=Summary!$C$2,_xlfn.XLOOKUP(NG!$B10,PL_NG!$C:$C,PL_NG!H:H),0) -> 0 | H10: =IF(H$3<=Summary!$C$2,_xlfn.XLOOKUP(NG!$B10,PL_NG!$C:$C,PL_NG!I:I),0) -> 0 | I10: =IF(I$3<=Summary!$C$2,_xlfn.XLOOKUP(NG!$B10,PL_NG!$C:$C,PL_NG!J:J),0) -> 0 | J10: =IF(J$3<=Summary!$C$2,_xlfn.XLOOKUP(NG!$B10,PL_NG!$C:$C,PL_NG!K:K),0) -> 0 | K10: =IF(K$3<=Summary!$C$2,_xlfn.XLOOKUP(NG!$B10,PL_NG!$C:$C,PL_NG!L:L),0) -> 0 | L10: =IF(L$3<=Summary!$C$2,_xlfn.XLOOKUP(NG!$B10,PL_NG!$C:$C,PL_NG!M:M),0) -> 0 | M10: =IF(M$3<=Summary!$C$2,_xlfn.XLOOKUP(NG!$B10,PL_NG!$C:$C,PL_NG!N:N),0) -> 0 | N10: =IF(N$3<=Summary!$C$2,_xlfn.XLOOKUP(NG!$B10,PL_NG!$C:$C,PL_NG!O:O),0) -> -17250130 | O10: =IF(O$3<=Summary!$C$2,_xlfn.XLOOKUP(NG!$B10,PL_NG!$C:$C,PL_NG!P:P),0) -> 0 | P10: =IF(P$3<=Summary!$C$2,_xlfn.XLOOKUP(NG!$B10,PL_NG!$C:$C,PL_NG!Q:Q),0) -> 0 | Q10: =IF(Q$3<=Summary!$C$2,_xlfn.XLOOKUP(NG!$B10,PL_NG!$C:$C,PL_NG!R:R),0) -> 0 | R10: =IF(R$3<=Summary!$C$2,_xlfn.XLOOKUP(NG!$B10,PL_NG!$C:$C,PL_NG!S:S),0) -> 0 | S10: =IF(S$3<=Summary!$C$2,_xlfn.XLOOKUP(NG!$B10,PL_NG!$C:$C,PL_NG!T:T),0) -> 0 | T10: =IF(T$3<=Summary!$C$2,_xlfn.XLOOKUP(NG!$B10,PL_NG!$C:$C,PL_NG!U:U),0) -> 0 | U10: =IF(U$3<=Summary!$C$2,_xlfn.XLOOKUP(NG!$B10,PL_NG!$C:$C,PL_NG!V:V),0) -> 0 | V10: =IF(V$3<=Summary!$C$2,_xlfn.XLOOKUP(NG!$B10,PL_NG!$C:$C,PL_NG!W:W),0) -> 0 | W10: =IF(W$3<=Summary!$C$2,_xlfn.XLOOKUP(NG!$B10,PL_NG!$C:$C,PL_NG!X:X),0) -> 0 | X10: =IF(X$3<=Summary!$C$2,_xlfn.XLOOKUP(NG!$B10,PL_NG!$C:$C,PL_NG!Y:Y),0) -> 0 | Y10: =IF(Y$3<=Summary!$C$2,_xlfn.XLOOKUP(NG!$B10,PL_NG!$C:$C,PL_NG!Z:Z),0) -> 0 | Z10: =IF(Z$3<=Summary!$C$2,_xlfn.XLOOKUP(NG!$B10,PL_NG!$C:$C,PL_NG!AA:AA),0) -> 0 | AA10: =IF(AA$3<=Summary!$C$2,_xlfn.XLOOKUP(NG!$B10,PL_NG!$C:$C,PL_NG!AB:AB),0) -> 0 | AB10: =IF(AB$3<=Summary!$C$2,_xlfn.XLOOKUP(NG!$B10,PL_NG!$C:$C,PL_NG!AC:AC),0) -> 0 | AC10: =IF(AC$3<=Summary!$C$2,_xlfn.XLOOKUP(NG!$B10,PL_NG!$C:$C,PL_NG!AD:AD),0) -> 0 | AD10: =IF(AD$3<=Summary!$C$2,_xlfn.XLOOKUP(NG!$B10,PL_NG!$C:$C,PL_NG!AE:AE),0) -> 0 | AE10: =IF(AE$3<=Summary!$C$2,_xlfn.XLOOKUP(NG!$B10,PL_NG!$C:$C,PL_NG!AF:AF),0) -> 0 | AF10: =IF(AF$3<=Summary!$C$2,_xlfn.XLOOKUP(NG!$B10,PL_NG!$C:$C,PL_NG!AG:AG),0) -> 0 | AG10: =IF(AG$3<=Summary!$C$2,_xlfn.XLOOKUP(NG!$B10,PL_NG!$C:$C,PL_NG!AH:AH),0) -> 0 | AH10: =IF(AH$3<=Summary!$C$2,_xlfn.XLOOKUP(NG!$B10,PL_NG!$C:$C,PL_NG!AI:AI),0) -> 0 | AI10: =IF(AI$3<=Summary!$C$2,_xlfn.XLOOKUP(NG!$B10,PL_NG!$C:$C,PL_NG!AJ:AJ),0) -> 0 | AJ10: =IF(AJ$3<=Summary!$C$2,_xlfn.XLOOKUP(NG!$B10,PL_NG!$C:$C,PL_NG!AK:AK),0) -> 0 | AK10: =IF(AK$3<=Summary!$C$2,_xlfn.XLOOKUP(NG!$B10,PL_NG!$C:$C,PL_NG!AL:AL),0) -> 0 | AL10: =IF(AL$3<=Summary!$C$2,_xlfn.XLOOKUP(NG!$B10,PL_NG!$C:$C,PL_NG!AM:AM),0) -> 0
A12: =A7+A9 -> 4.6824991e+08
B13: TOTAL PERSONNEL EXPENSES | C13: =IF(C$3<=Summary!$C$2,_xlfn.XLOOKUP(NG!$B13,PL_NG!$C:$C,PL_NG!D:D),0) -> -51864750 | D13: =IF(D$3<=Summary!$C$2,_xlfn.XLOOKUP(NG!$B13,PL_NG!$C:$C,PL_NG!E:E),0) -> -61847010 | E13: =IF(E$3<=Summary!$C$2,_xlfn.XLOOKUP(NG!$B13,PL_NG!$C:$C,PL_NG!F:F),0) -> -71658409 | F13: =IF(F$3<=Summary!$C$2,_xlfn.XLOOKUP(NG!$B13,PL_NG!$C:$C,PL_NG!G:G),0) -> -89289691 | G13: =IF(G$3<=Summary!$C$2,_xlfn.XLOOKUP(NG!$B13,PL_NG!$C:$C,PL_NG!H:H),0) -> -1.1442064e+08 | H13: =IF(H$3<=Summary!$C$2,_xlfn.XLOOKUP(NG!$B13,PL_NG!$C:$C,PL_NG!I:I),0) -> -89891456 | I13: =IF(I$3<=Summary!$C$2,_xlfn.XLOOKUP(NG!$B13,PL_NG!$C:$C,PL_NG!J:J),0) -> -89441102 | J13: =IF(J$3<=Summary!$C$2,_xlfn.XLOOKUP(NG!$B13,PL_NG!$C:$C,PL_NG!K:K),0) -> -94662026 | K13: =IF(K$3<=Summary!$C$2,_xlfn.XLOOKUP(NG!$B13,PL_NG!$C:$C,PL_NG!L:L),0) -> -1.3042169e+08 | L13: =IF(L$3<=Summary!$C$2,_xlfn.XLOOKUP(NG!$B13,PL_NG!$C:$C,PL_NG!M:M),0) -> -1.8381104e+08 | M13: =IF(M$3<=Summary!$C$2,_xlfn.XLOOKUP(NG!$B13,PL_NG!$C:$C,PL_NG!N:N),0) -> -1.8158012e+08 | N13: =IF(N$3<=Summary!$C$2,_xlfn.XLOOKUP(NG!$B13,PL_NG!$C:$C,PL_NG!O:O),0) -> -6.2461776e+08 | O13: =IF(O$3<=Summary!$C$2,_xlfn.XLOOKUP(NG!$B13,PL_NG!$C:$C,PL_NG!P:P),0) -> -1.2981928e+08 | P13: =IF(P$3<=Summary!$C$2,_xlfn.XLOOKUP(NG!$B13,PL_NG!$C:$C,PL_NG!Q:Q),0) -> -1.2888931e+08 | Q13: =IF(Q$3<=Summary!$C$2,_xlfn.XLOOKUP(NG!$B13,PL_NG!$C:$C,PL_NG!R:R),0) -> -1.4931323e+08 | R13: =IF(R$3<=Summary!$C$2,_xlfn.XLOOKUP(NG!$B13,PL_NG!$C:$C,PL_NG!S:S),0) -> -1.4823746e+08 | S13: =IF(S$3<=Summary!$C$2,_xlfn.XLOOKUP(NG!$B13,PL_NG!$C:$C,PL_NG!T:T),0) -> -1.9034696e+08 | T13: =IF(T$3<=Summary!$C$2,_xlfn.XLOOKUP(NG!$B13,PL_NG!$C:$C,PL_NG!U:U),0) -> -1.4224424e+08 | U13: =IF(U$3<=Summary!$C$2,_xlfn.XLOOKUP(NG!$B13,PL_NG!$C:$C,PL_NG!V:V),0) -> -1.6162011e+08 | V13: =IF(V$3<=Summary!$C$2,_xlfn.XLOOKUP(NG!$B13,PL_NG!$C:$C,PL_NG!W:W),0) -> -1.3050721e+08 | W13: =IF(W$3<=Summary!$C$2,_xlfn.XLOOKUP(NG!$B13,PL_NG!$C:$C,PL_NG!X:X),0) -> -1.9610815e+08 | X13: =IF(X$3<=Summary!$C$2,_xlfn.XLOOKUP(NG!$B13,PL_NG!$C:$C,PL_NG!Y:Y),0) -> -1.6539341e+08 | Y13: =IF(Y$3<=Summary!$C$2,_xlfn.XLOOKUP(NG!$B13,PL_NG!$C:$C,PL_NG!Z:Z),0) -> -1.6673965e+08 | Z13: =IF(Z$3<=Summary!$C$2,_xlfn.XLOOKUP(NG!$B13,PL_NG!$C:$C,PL_NG!AA:AA),0) -> -8.5198104e+08 | AA13: =IF(AA$3<=Summary!$C$2,_xlfn.XLOOKUP(NG!$B13,PL_NG!$C:$C,PL_NG!AB:AB),0) -> -1.4493926e+08 | AB13: =IF(AB$3<=Summary!$C$2,_xlfn.XLOOKUP(NG!$B13,PL_NG!$C:$C,PL_NG!AC:AC),0) -> -1.3589213e+08 | AC13: =IF(AC$3<=Summary!$C$2,_xlfn.XLOOKUP(NG!$B13,PL_NG!$C:$C,PL_NG!AD:AD),0) -> -1.3954911e+08 | AD13: =IF(AD$3<=Summary!$C$2,_xlfn.XLOOKUP(NG!$B13,PL_NG!$C:$C,PL_NG!AE:AE),0) -> -1.3937574e+08 | AE13: =IF(AE$3<=Summary!$C$2,_xlfn.XLOOKUP(NG!$B13,PL_NG!$C:$C,PL_NG!AF:AF),0) -> 0 | AF13: =IF(AF$3<=Summary!$C$2,_xlfn.XLOOKUP(NG!$B13,PL_NG!$C:$C,PL_NG!AG:AG),0) -> 0 | AG13: =IF(AG$3<=Summary!$C$2,_xlfn.XLOOKUP(NG!$B13,PL_NG!$C:$C,PL_NG!AH:AH),0) -> 0 | AH13: =IF(AH$3<=Summary!$C$2,_xlfn.XLOOKUP(NG!$B13,PL_NG!$C:$C,PL_NG!AI:AI),0) -> 0 | AI13: =IF(AI$3<=Summary!$C$2,_xlfn.XLOOKUP(NG!$B13,PL_NG!$C:$C,PL_NG!AJ:AJ),0) -> 0 | AJ13: =IF(AJ$3<=Summary!$C$2,_xlfn.XLOOKUP(NG!$B13,PL_NG!$C:$C,PL_NG!AK:AK),0) -> 0 | AK13: =IF(AK$3<=Summary!$C$2,_xlfn.XLOOKUP(NG!$B13,PL_NG!$C:$C,PL_NG!AL:AL),0) -> 0 | AL13: =IF(AL$3<=Summary!$C$2,_xlfn.XLOOKUP(NG!$B13,PL_NG!$C:$C,PL_NG!AM:AM),0) -> 0
B15: Customer list & Total Revenue check | C15: =C4-C31 -> 0 | D15: =D4-D31 -> 0 | E15: =E4-E31 -> 0 | F15: =F4-F31 -> -0.34000003 | G15: =G4-G31 -> 0 | H15: =H4-H31 -> -0.13999996 | I15: =I4-I31 -> 0 | J15: =J4-J31 -> 0 | ... AL15: =AL4-AL31 -> 0
X16: =SUM(O32:X32,O21:X21) -> 1.025412e+09 | Y16: =X16/C_RATE -> 745998.31
B17: Customer List | X17: =SUM(O28:X28) -> 71836015 | Y17: =X17/C_RATE -> 52261.478
B18: MTN Nigeria | C18: 1.247151e+08 | D18: 4.8905651e+08 | E18: 224553901 | F18: 2.8426313e+08 | G18: 73213175 | H18: 1.0846408e+08 | I18: 1.1360249e+08 | J18: 1.786125e+08 | K18: 50610980 | L18: 1.0963379e+08 | M18: 1.0064863e+08 | N18: 90783812 | O18: 1.0430766e+08 | P18: 104307662 | Q18: 104307662 | R18: 76446317 | S18: 50613317 | T18: 50613317 | U18: 50613317 | V18: 50613317 | W18: 50613317 | X18: 50613317 | Y18: 93705345 | Z18: 63173577 | AA18: 63173577 | AB18: 11056943
B19: Globacom | C19: 0 | D19: 11605135 | E19: 77090000 | F19: 0 | G19: 0 | H19: 0 | I19: 60750000 | J19: 89276753 | K19: 20250000 | L19: 20250000 | M19: 20250000 | N19: 20250000 | O19: 20250000 | P19: 20250000 | Q19: 34939455 | R19: 38091011 | S19: 38091011 | T19: 38091011 | U19: 38091011 | V19: 49342678 | W19: 1.2605632e+08 | X19: 97419685 | Y19: 97419685 | Z19: 97419685 | AA19: 1.1264167e+08 | AB19: 97419685
B20: UNN | C20: 8878855.9 | D20: 16609333 | E20: 12845297 | F20: 20538678 | G20: 42505482 | H20: 22862550 | I20: 28714968 | J20: 15427407 | K20: 11248086 | L20: 12735471 | M20: 13413174 | N20: 10387589 | O20: 25835047 | P20: 35006935 | Q20: 29632231 | R20: 37632657 | S20: 27231754 | T20: 14311033 | U20: 16657932 | V20: 18560060 | W20: 17620243 | X20: 16933829 | Y20: 13792951 | Z20: 9825049.4 | AA20: 3257006.6 | AB20: 28640720
B21: NIMC | C21: 40971907 | D21: 0 | E21: 0 | F21: 0 | G21: 0 | H21: 0 | I21: 0 | J21: 0 | K21: 0 | L21: 0 | M21: 29287870 | N21: 4.5453379e+08 | O21: 34023296 | P21: 36595467 | Q21: 44660140 | R21: 81320930 | S21: 43579335 | T21: 16725582 | U21: 43646512 | V21: 24709345 | W21: 1.7885401e+08 | X21: 4.69377e+08 | Y21: 74257389 | Z21: 70085310 | AA21: 4.92194e+08 | AB21: 5.5126514e+08
B22: Orange Liberia | C22: 0 | D22: 0 | E22: 0 | F22: 0 | G22: 0 | H22: 0 | I22: 0 | J22: 0 | K22: 0 | L22: 0 | M22: 0 | N22: 0 | U22: 20915225 | V22: 40763110 | W22: 18546765 | X22: 18118640 | Y22: 18090639 | Z22: 18120764 | AA22: 27079335 | AB22: 16963639
B23: MTN CIV | C23: 0 | D23: 0 | E23: 0 | F23: 2.1958027e+08 | G23: 0 | H23: 73508891 | I23: 0 | J23: 0 | K23: 5485724.9 | L23: 0 | M23: 0 | N23: 0 | U23: 25241328 | W23: 7003252.8 | X23: =77212642.61+3420796.4 -> 80633439 | Y23: 3415510 | Z23: 3421197.6 | AA23: 0 | AB23: 35992741
B24: Verified Customers | C24: 287016.74 | D24: 359151.63 | E24: 2011322 | F24: 5504050.3 | G24: 6745064 | H24: 7782409.6 | I24: 580358.16 | J24: 14243306 | K24: 10393353 | L24: 9483034.2 | M24: 8765688.3 | N24: 10247311 | O24: 6185881.8 | P24: 0 | Q24: 757047 | R24: 0 | S24: 0 | T24: 0 | Z24: 35503908
B25: MFA Benin | X25: =22420641.88-X26 -> 22241092 | Y25: =20363235.64-Y26 -> 20303249 | Z25: 12065628 | AA25: 13756964 | AB25: 10128998
B26: Fixiam_NG | X26: 179550 | Y26: 59987
B27: ONECI | Y27: 1447250
B28: Others Customers | C28: 318104.65 | D28: 859255.82 | E28: 2.1051372e+08 | F28: 11953728 | G28: 84264081 | H28: 6822014.8 | I28: 10191008 | J28: 15644474 | K28: 23832074 | L28: 21275426 | M28: 54626533 | N28: 6055500.1 | O28: 22666727 | P28: 888611.79 | Q28: 8106499.8 | R28: 9209303 | S28: 14976745 | T28: 0 | U28: 13999209 | W28: 2502297.7 | X28: -513378.89 | Y28: 175116.63 | Z28: 2521627.9 | AA28: 837209.3 | AB28: 8093023.3
B31: NG Revenue | C31: =SUM(C18:C28) -> 1.7517098e+08 | D31: =SUM(D18:D28) -> 5.1848939e+08 | E31: =SUM(E18:E28) -> 5.2701424e+08 | F31: =SUM(F18:F28) -> 5.4183986e+08 | G31: =SUM(G18:G28) -> 2.067278e+08 | H31: =SUM(H18:H28) -> 2.1943995e+08 | I31: =SUM(I18:I28) -> 2.1383883e+08 | J31: =SUM(J18:J28) -> 3.1320444e+08 | ... AL31: =SUM(AL18:AL28) -> 0
B32: UK NIMC | C32: =PL_UK!D11-SUM(Group!C31:C33) -> 21737164 | D32: =PL_UK!E11-SUM(Group!D31:D33) -> 36431174 | E32: =PL_UK!F11-SUM(Group!E31:E33) -> 34515318 | F32: =PL_UK!G11-SUM(Group!F31:F33) -> 24276553 | G32: =PL_UK!H11-SUM(Group!G31:G33) -> 23585130 | H32: =PL_UK!I11-SUM(Group!H31:H33) -> 21654607 | I32: =PL_UK!J11-SUM(Group!I31:I33) -> 7095997 | J32: =PL_UK!K11-SUM(Group!J31:J33) -> 45135912 | ... AL32: =PL_UK!AM11-SUM(Group!AL31:AL33) -> 0
B33: UK Verification | C33: =PL_UK!D9 -> 1550706.1 | D33: =PL_UK!E9 -> 2826992.6 | E33: =PL_UK!F9 -> 2029040 | F33: =PL_UK!G9 -> 1704868.3 | G33: =PL_UK!H9 -> 2042263.4 | H33: =PL_UK!I9 -> 2718067.8 | I33: =PL_UK!J9 -> 0 | J33: =PL_UK!K9 -> 1788631.8 | ... AL33: =PL_UK!AM9 -> 0
B34: MFA Benin | C34: =PL_UK!D7 -> 0 | D34: =PL_UK!E7 -> 0 | E34: =PL_UK!F7 -> 0 | F34: =PL_UK!G7 -> 0 | G34: =PL_UK!H7 -> 0 | H34: =PL_UK!I7 -> 0 | I34: =PL_UK!J7 -> 0 | J34: =PL_UK!K7 -> 0 | ... AL34: =PL_UK!AM7 -> 0
B35: Fixiam_UK | C35: =PL_UK!D8 -> 0 | D35: =PL_UK!E8 -> 0 | E35: =PL_UK!F8 -> 0 | F35: =PL_UK!G8 -> 0 | G35: =PL_UK!H8 -> 0 | H35: =PL_UK!I8 -> 0 | I35: =PL_UK!J8 -> 0 | J35: =PL_UK!K8 -> 0 | ... AL35: =PL_UK!AM8 -> 0
B36: Total Revenue | C36: =SUM(C31:C35) -> 1.9845885e+08 | D36: =SUM(D31:D35) -> 5.5774756e+08 | E36: =SUM(E31:E35) -> 5.635586e+08 | F36: =SUM(F31:F35) -> 5.6782128e+08 | G36: =SUM(G31:G35) -> 2.3235519e+08 | H36: =SUM(H31:H35) -> 2.4381262e+08 | I36: =SUM(I31:I35) -> 2.2093482e+08 | J36: =SUM(J31:J35) -> 3.6012899e+08 | ... AL36: =SUM(AL31:AL35) -> 0
B38: ARR
A39: S/n | B39: Vertical | C39: =C3 -> 45322 | D39: =D3 -> 45351 | E39: =E3 -> 45382 | F39: =F3 -> 45412 | G39: =G3 -> 45443 | H39: =H3 -> 45473 | I39: =I3 -> 45504 | J39: =J3 -> 45535 | ... AL39: =AL3 -> 46387
A40: 1 | B40: Verify_ARR | C40: 1837847.8 | D40: 3185380.4 | E40: 4039975.5 | F40: 7549221.7 | G40: 8787327.4 | H40: 10500477 | I40: 2674670.4 | J40: 16325944 | K40: 12198994 | L40: 11905698 | M40: 10640305 | N40: 12348783 | O40: 7059630.5 | P40: 1094716 | Q40: 1946966.6 | R40: 1819954 | S40: 1234893 | T40: 791656.54 | U40: 1658214.5 | V40: 21681059 | W40: 3558623.4 | X40: 0
A41: 2 | B41: Telco_ARR | C41: 26844760 | D41: 26844760 | E41: 26844760 | F41: 47095107 | G41: 47095107 | H41: 82631080 | I41: 1.1507505e+08 | J41: 1.2141066e+08 | K41: 97992855 | L41: 95065629 | M41: 95065629 | N41: 84088531 | O41: 98724662 | P41: 98724662 | Q41: 1.1341412e+08 | R41: 88704328 | S41: 88704328 | T41: 88704328 | U41: 1.1033365e+08 | V41: 99955995 | W41: 183672893 | X41: 1.2539548e+08 | Y41: 1.7542998e+08 | Z41: 1.3795614e+08 | AA41: 1.7904227e+08 | AB41: 1.2773423e+08
A42: 3 | B42: Public Sector_ARR | C42: 27967144 | D42: 53091001 | E42: 48486369 | F42: 45652377 | G42: 92591448 | H42: 70521450 | I42: 83366194 | J42: 68617373 | K42: 57643328 | L42: 58227840 | M42: 84480505 | N42: 46936587 | O42: 73893399 | P42: 79096782 | Q42: 66018140 | R42: 63465657 | S42: 28313965 | T42: 13964537 | U42: 17975952 | V42: 26144649 | W42: 21768153 | X42: =Group!X40-Group!X32 -> 39611313 | Y42: 33992247 | Z42: 9825049.4 | AA42: 16954228 | AB42: 38712400
A43: 4 | B43: Others_ARR | C43: 318104.65 | D43: 282511.63 | E43: 0 | F43: 293333.33 | G43: 963798.45 | H43: 384775.19 | I43: 386356.59 | J43: 754217.05 | K43: 525891.47 | L43: 479379.84 | M43: 293333.33 | N43: 653600.77 | O43: 570542.63 | P43: 571612.4 | Q43: 1129756.8 | R43: 279069.77 | S43: 0 | T43: 0 | U43: 45720.93 | V43: 0 | W43: -46511.63
B44: Total ARR | C44: =SUM(C40:C43) -> 56967857 | D44: =SUM(D40:D43) -> 83403653 | E44: =SUM(E40:E43) -> 79371104 | F44: =SUM(F40:F43) -> 1.0059004e+08 | G44: =SUM(G40:G43) -> 1.4943768e+08 | H44: =SUM(H40:H43) -> 1.6403778e+08 | I44: =SUM(I40:I43) -> 2.0150227e+08 | J44: =SUM(J40:J43) -> 2.071082e+08 | ... AL44: =SUM(AL40:AL43) -> 0
B45: Total Revenue | C45: =C36 -> 1.9845885e+08 | D45: =D36 -> 5.5774756e+08 | E45: =E36 -> 5.635586e+08 | F45: =F36 -> 5.6782128e+08 | G45: =G36 -> 2.3235519e+08 | H45: =H36 -> 2.4381262e+08 | I45: =I36 -> 2.2093482e+08 | J45: =J36 -> 3.6012899e+08 | ... AL45: =AL36 -> 0
B46: ARR | C46: =C44/C45 -> 0.28705123 | D46: =D44/D45 -> 0.14953656 | E46: =E44/E45 -> 0.14083913 | F46: =F44/F45 -> 0.17715088 | G46: =G44/G45 -> 0.64314327 | H46: =H44/H45 -> 0.67280267 | I46: =I44/I45 -> 0.91204395 | J46: =J44/J45 -> 0.57509449 | ... AL46: =AL44/AL45 -> #DIV/0!
B48: Verify | C48: 64801682 | D48: 4.0915042e+08 | E48: 203769463 | F48: 2.4267207e+08 | G48: 16202777 | H48: 7782409.6 | I48: 580358.16 | J48: 14243306 | K48: -42571522 | L48: 9199126.2 | M48: 51922181 | N48: 15612001 | O48: 28282067 | P48: 0 | Q48: 757047 | R48: 0 | S48: 0 | T48: 0 | U48: 0 | W48: 1711600 | X48: -453529 | Y48: 0 | Z48: 35565201
B49: Telco | C49: 60200431 | D49: 91870381 | E49: 299729712 | F49: 2.6667538e+08 | G49: 47095107 | H49: 1.5613997e+08 | I49: 1.4851949e+08 | J49: 2.4916047e+08 | K49: 1.1640337e+08 | L49: 1.0436795e+08 | M49: 95065629 | N49: 111033812 | O49: 98724662 | P49: 98724662 | Q49: 113414117 | R49: 88704328 | S49: 88704328 | T49: 88704328 | U49: 134860881 | V49: =99955995+40763110 -> 140719105 | W49: 202219658 | X49: 246785080 | Y49: 212631179 | Z49: 182135224 | AA49: 2.0295433e+08 | AB49: 1.6149033e+08
B50: Public Sector | C50: 49850763 | D50: 17186078 | E50: 23515064 | F50: 32199077 | G50: 1.4246612e+08 | H50: 55132796 | I50: 64352619 | J50: 49046454 | K50: 47462481 | L50: 59331262 | M50: 79710751 | N50: 4.6492138e+08 | O50: 85691343 | P50: 97435402 | Q50: 100125370 | R50: 144786587 | S50: 70811090 | T50: 31036614 | U50: 59746304 | V50: 43269404 | W50: 196474253 | X50: 508492067 | Y50: 109696886 | Z50: 94147253 | AA50: 5.0914823e+08 | AB50: 5.9807057e+08
B51: Others | C51: 318104.65 | D51: 282511.63 | E51: 0 | F51: 293333.33 | G51: 963798.45 | H51: 384775.19 | I51: 386356.59 | J51: 754217.05 | K51: 525891.47 | L51: 479379.84 | M51: 293333 | N51: 690810 | O51: 570543 | P51: 888612 | Q51: 8106501 | R51: 9209302 | S51: 14976744 | T51: 0 | U51: 14557349 | V51: 0 | W51: 790698 | X51: 0 | Y51: 279070 | Z51: 289070 | AA51: 837209.3
B52: Fixiam | X52: 179550 | Y52: 59987
B53: Total | C53: =SUM(C48:C51) -> 1.7517098e+08 | D53: =SUM(D48:D51) -> 5.1848939e+08 | E53: =SUM(E48:E51) -> 5.2701424e+08 | F53: =SUM(F48:F51) -> 5.4183986e+08 | G53: =SUM(G48:G51) -> 2.067278e+08 | H53: =SUM(H48:H51) -> 2.1943995e+08 | I53: =SUM(I48:I51) -> 2.1383883e+08 | J53: =SUM(J48:J51) -> 3.1320444e+08 | ... W53: =SUM(W48:W51) -> 401196209 | X53: =SUM(X48:X52) -> 755003168 | Y53: =SUM(Y48:Y52) -> 322667122 | Z53: =SUM(Z48:Z51) -> 312136748 | AA53: =SUM(AA48:AA51) -> 7.1293977e+08 | AB53: =SUM(AB48:AB51) -> 7.5956089e+08
H54: =H53-H4 -> 6.14 | I54: =I53-I4 -> 0 | J54: =J53-J4 -> 0 | K54: =K53-K4 -> -6.36 | L54: =L53-L4 -> 0 | M54: =M53-M4 -> -0.45999998 | N54: =N53-N4 -> 0.0099999905 | O54: =O53-O4 -> 1.05 | ... AN54: =AN53-AN4 -> 0
B56: Balance Sheet
B57: TOTAL CASH & CASH EQUIVALENT | C57: =IF(C$3<=Summary!$C$2,_xlfn.XLOOKUP(NG!$B57,BS_NG!$C:$C,BS_NG!D:D),0) -> 1.110083e+08 | D57: =IF(D$3<=Summary!$C$2,_xlfn.XLOOKUP(NG!$B57,BS_NG!$C:$C,BS_NG!E:E),0) -> 1.0015991e+08 | E57: =IF(E$3<=Summary!$C$2,_xlfn.XLOOKUP(NG!$B57,BS_NG!$C:$C,BS_NG!F:F),0) -> 7.0888803e+09 | F57: =IF(F$3<=Summary!$C$2,_xlfn.XLOOKUP(NG!$B57,BS_NG!$C:$C,BS_NG!G:G),0) -> 5.9241002e+09 | G57: =IF(G$3<=Summary!$C$2,_xlfn.XLOOKUP(NG!$B57,BS_NG!$C:$C,BS_NG!H:H),0) -> 5.7231196e+09 | H57: =IF(H$3<=Summary!$C$2,_xlfn.XLOOKUP(NG!$B57,BS_NG!$C:$C,BS_NG!I:I),0) -> 7.2876377e+09 | I57: =IF(I$3<=Summary!$C$2,_xlfn.XLOOKUP(NG!$B57,BS_NG!$C:$C,BS_NG!J:J),0) -> 7.017709e+09 | J57: =IF(J$3<=Summary!$C$2,_xlfn.XLOOKUP(NG!$B57,BS_NG!$C:$C,BS_NG!K:K),0) -> 6.9365305e+09 | K57: =IF(K$3<=Summary!$C$2,_xlfn.XLOOKUP(NG!$B57,BS_NG!$C:$C,BS_NG!L:L),0) -> 6.9744732e+09 | L57: =IF(L$3<=Summary!$C$2,_xlfn.XLOOKUP(NG!$B57,BS_NG!$C:$C,BS_NG!M:M),0) -> 6.4329428e+09 | M57: =IF(M$3<=Summary!$C$2,_xlfn.XLOOKUP(NG!$B57,BS_NG!$C:$C,BS_NG!N:N),0) -> 6.6090977e+09 | N57: =IF(N$3<=Summary!$C$2,_xlfn.XLOOKUP(NG!$B57,BS_NG!$C:$C,BS_NG!O:O),0) -> 5.8710874e+09 | O57: =IF(O$3<=Summary!$C$2,_xlfn.XLOOKUP(NG!$B57,BS_NG!$C:$C,BS_NG!P:P),0) -> 5.4263506e+09 | P57: =IF(P$3<=Summary!$C$2,_xlfn.XLOOKUP(NG!$B57,BS_NG!$C:$C,BS_NG!Q:Q),0) -> 4.9292593e+09 | Q57: =IF(Q$3<=Summary!$C$2,_xlfn.XLOOKUP(NG!$B57,BS_NG!$C:$C,BS_NG!R:R),0) -> 5.687264e+09 | R57: =IF(R$3<=Summary!$C$2,_xlfn.XLOOKUP(NG!$B57,BS_NG!$C:$C,BS_NG!S:S),0) -> 5.0466712e+09 | S57: =IF(S$3<=Summary!$C$2,_xlfn.XLOOKUP(NG!$B57,BS_NG!$C:$C,BS_NG!T:T),0) -> 4.2698483e+09 | T57: =IF(T$3<=Summary!$C$2,_xlfn.XLOOKUP(NG!$B57,BS_NG!$C:$C,BS_NG!U:U),0) -> 4.3286269e+09 | U57: =IF(U$3<=Summary!$C$2,_xlfn.XLOOKUP(NG!$B57,BS_NG!$C:$C,BS_NG!V:V),0) -> 3.7083119e+09 | V57: =IF(V$3<=Summary!$C$2,_xlfn.XLOOKUP(NG!$B57,BS_NG!$C:$C,BS_NG!W:W),0) -> 3.7477342e+09 | W57: =IF(W$3<=Summary!$C$2,_xlfn.XLOOKUP(NG!$B57,BS_NG!$C:$C,BS_NG!X:X),0) -> 3.3092353e+09 | X57: =IF(X$3<=Summary!$C$2,_xlfn.XLOOKUP(NG!$B57,BS_NG!$C:$C,BS_NG!Y:Y),0) -> 3.3178316e+09 | Y57: =IF(Y$3<=Summary!$C$2,_xlfn.XLOOKUP(NG!$B57,BS_NG!$C:$C,BS_NG!Z:Z),0) -> 2.8664976e+09 | Z57: =IF(Z$3<=Summary!$C$2,_xlfn.XLOOKUP(NG!$B57,BS_NG!$C:$C,BS_NG!AA:AA),0) -> 2.3789035e+09 | AA57: =IF(AA$3<=Summary!$C$2,_xlfn.XLOOKUP(NG!$B57,BS_NG!$C:$C,BS_NG!AB:AB),0) -> 2.351082e+09 | AB57: =IF(AB$3<=Summary!$C$2,_xlfn.XLOOKUP(NG!$B57,BS_NG!$C:$C,BS_NG!AC:AC),0) -> 2.4992885e+09 | AC57: =IF(AC$3<=Summary!$C$2,_xlfn.XLOOKUP(NG!$B57,BS_NG!$C:$C,BS_NG!AD:AD),0) -> 2709729523 | AD57: =IF(AD$3<=Summary!$C$2,_xlfn.XLOOKUP(NG!$B57,BS_NG!$C:$C,BS_NG!AE:AE),0) -> 2.4586593e+09 | AE57: =IF(AE$3<=Summary!$C$2,_xlfn.XLOOKUP(NG!$B57,BS_NG!$C:$C,BS_NG!AF:AF),0) -> 0 | AF57: =IF(AF$3<=Summary!$C$2,_xlfn.XLOOKUP(NG!$B57,BS_NG!$C:$C,BS_NG!AG:AG),0) -> 0 | AG57: =IF(AG$3<=Summary!$C$2,_xlfn.XLOOKUP(NG!$B57,BS_NG!$C:$C,BS_NG!AH:AH),0) -> 0 | AH57: =IF(AH$3<=Summary!$C$2,_xlfn.XLOOKUP(NG!$B57,BS_NG!$C:$C,BS_NG!AI:AI),0) -> 0 | AI57: =IF(AI$3<=Summary!$C$2,_xlfn.XLOOKUP(NG!$B57,BS_NG!$C:$C,BS_NG!AJ:AJ),0) -> 0 | AJ57: =IF(AJ$3<=Summary!$C$2,_xlfn.XLOOKUP(NG!$B57,BS_NG!$C:$C,BS_NG!AK:AK),0) -> 0 | AK57: =IF(AK$3<=Summary!$C$2,_xlfn.XLOOKUP(NG!$B57,BS_NG!$C:$C,BS_NG!AL:AL),0) -> 0 | AL57: =IF(AL$3<=Summary!$C$2,_xlfn.XLOOKUP(NG!$B57,BS_NG!$C:$C,BS_NG!AM:AM),0) -> 0
B58: TOTAL ACCOUNT RECEIVABLES | C58: =IF(C$3<=Summary!$C$2,_xlfn.XLOOKUP(NG!$B58,BS_NG!$C:$C,BS_NG!D:D),0) -> 1.5626427e+08 | D58: =IF(D$3<=Summary!$C$2,_xlfn.XLOOKUP(NG!$B58,BS_NG!$C:$C,BS_NG!E:E),0) -> 5.6486368e+08 | E58: =IF(E$3<=Summary!$C$2,_xlfn.XLOOKUP(NG!$B58,BS_NG!$C:$C,BS_NG!F:F),0) -> 8.5502295e+08 | F58: =IF(F$3<=Summary!$C$2,_xlfn.XLOOKUP(NG!$B58,BS_NG!$C:$C,BS_NG!G:G),0) -> 8.4595559e+08 | G58: =IF(G$3<=Summary!$C$2,_xlfn.XLOOKUP(NG!$B58,BS_NG!$C:$C,BS_NG!H:H),0) -> 6.7761395e+08 | H58: =IF(H$3<=Summary!$C$2,_xlfn.XLOOKUP(NG!$B58,BS_NG!$C:$C,BS_NG!I:I),0) -> 6.4184599e+08 | I58: =IF(I$3<=Summary!$C$2,_xlfn.XLOOKUP(NG!$B58,BS_NG!$C:$C,BS_NG!J:J),0) -> 6.8084604e+08 | J58: =IF(J$3<=Summary!$C$2,_xlfn.XLOOKUP(NG!$B58,BS_NG!$C:$C,BS_NG!K:K),0) -> 5.0305817e+08 | K58: =IF(K$3<=Summary!$C$2,_xlfn.XLOOKUP(NG!$B58,BS_NG!$C:$C,BS_NG!L:L),0) -> 3.8427372e+08 | L58: =IF(L$3<=Summary!$C$2,_xlfn.XLOOKUP(NG!$B58,BS_NG!$C:$C,BS_NG!M:M),0) -> 2.613186e+08 | M58: =IF(M$3<=Summary!$C$2,_xlfn.XLOOKUP(NG!$B58,BS_NG!$C:$C,BS_NG!N:N),0) -> 2.2602477e+08 | N58: =IF(N$3<=Summary!$C$2,_xlfn.XLOOKUP(NG!$B58,BS_NG!$C:$C,BS_NG!O:O),0) -> 1.3026208e+09 | O58: =IF(O$3<=Summary!$C$2,_xlfn.XLOOKUP(NG!$B58,BS_NG!$C:$C,BS_NG!P:P),0) -> 1.236828e+09 | P58: =IF(P$3<=Summary!$C$2,_xlfn.XLOOKUP(NG!$B58,BS_NG!$C:$C,BS_NG!Q:Q),0) -> 1.2732701e+09 | Q58: =IF(Q$3<=Summary!$C$2,_xlfn.XLOOKUP(NG!$B58,BS_NG!$C:$C,BS_NG!R:R),0) -> 5.1877894e+08 | R58: =IF(R$3<=Summary!$C$2,_xlfn.XLOOKUP(NG!$B58,BS_NG!$C:$C,BS_NG!S:S),0) -> 4.3882843e+08 | S58: =IF(S$3<=Summary!$C$2,_xlfn.XLOOKUP(NG!$B58,BS_NG!$C:$C,BS_NG!T:T),0) -> 4.9002547e+08 | T58: =IF(T$3<=Summary!$C$2,_xlfn.XLOOKUP(NG!$B58,BS_NG!$C:$C,BS_NG!U:U),0) -> 83560600 | U58: =IF(U$3<=Summary!$C$2,_xlfn.XLOOKUP(NG!$B58,BS_NG!$C:$C,BS_NG!V:V),0) -> 85682881 | V58: =IF(V$3<=Summary!$C$2,_xlfn.XLOOKUP(NG!$B58,BS_NG!$C:$C,BS_NG!W:W),0) -> 1.3249569e+08 | W58: =IF(W$3<=Summary!$C$2,_xlfn.XLOOKUP(NG!$B58,BS_NG!$C:$C,BS_NG!X:X),0) -> 1.4547427e+08 | X58: =IF(X$3<=Summary!$C$2,_xlfn.XLOOKUP(NG!$B58,BS_NG!$C:$C,BS_NG!Y:Y),0) -> 1.7530864e+08 | Y58: =IF(Y$3<=Summary!$C$2,_xlfn.XLOOKUP(NG!$B58,BS_NG!$C:$C,BS_NG!Z:Z),0) -> 1.7266238e+08 | Z58: =IF(Z$3<=Summary!$C$2,_xlfn.XLOOKUP(NG!$B58,BS_NG!$C:$C,BS_NG!AA:AA),0) -> 2.1504615e+08 | AA58: =IF(AA$3<=Summary!$C$2,_xlfn.XLOOKUP(NG!$B58,BS_NG!$C:$C,BS_NG!AB:AB),0) -> 4.7002837e+08 | AB58: =IF(AB$3<=Summary!$C$2,_xlfn.XLOOKUP(NG!$B58,BS_NG!$C:$C,BS_NG!AC:AC),0) -> 7.3881364e+08 | AC58: =IF(AC$3<=Summary!$C$2,_xlfn.XLOOKUP(NG!$B58,BS_NG!$C:$C,BS_NG!AD:AD),0) -> 7.0140483e+08 | AD58: =IF(AD$3<=Summary!$C$2,_xlfn.XLOOKUP(NG!$B58,BS_NG!$C:$C,BS_NG!AE:AE),0) -> 5.7330792e+08 | AE58: =IF(AE$3<=Summary!$C$2,_xlfn.XLOOKUP(NG!$B58,BS_NG!$C:$C,BS_NG!AF:AF),0) -> 0 | AF58: =IF(AF$3<=Summary!$C$2,_xlfn.XLOOKUP(NG!$B58,BS_NG!$C:$C,BS_NG!AG:AG),0) -> 0 | AG58: =IF(AG$3<=Summary!$C$2,_xlfn.XLOOKUP(NG!$B58,BS_NG!$C:$C,BS_NG!AH:AH),0) -> 0 | AH58: =IF(AH$3<=Summary!$C$2,_xlfn.XLOOKUP(NG!$B58,BS_NG!$C:$C,BS_NG!AI:AI),0) -> 0 | AI58: =IF(AI$3<=Summary!$C$2,_xlfn.XLOOKUP(NG!$B58,BS_NG!$C:$C,BS_NG!AJ:AJ),0) -> 0 | AJ58: =IF(AJ$3<=Summary!$C$2,_xlfn.XLOOKUP(NG!$B58,BS_NG!$C:$C,BS_NG!AK:AK),0) -> 0 | AK58: =IF(AK$3<=Summary!$C$2,_xlfn.XLOOKUP(NG!$B58,BS_NG!$C:$C,BS_NG!AL:AL),0) -> 0 | AL58: =IF(AL$3<=Summary!$C$2,_xlfn.XLOOKUP(NG!$B58,BS_NG!$C:$C,BS_NG!AM:AM),0) -> 0
B59: TOTAL INVENTORIES | C59: =IF(C$3<=Summary!$C$2,_xlfn.XLOOKUP(NG!$B59,BS_NG!$C:$C,BS_NG!D:D),0) -> 94581089 | D59: =IF(D$3<=Summary!$C$2,_xlfn.XLOOKUP(NG!$B59,BS_NG!$C:$C,BS_NG!E:E),0) -> 94581089 | E59: =IF(E$3<=Summary!$C$2,_xlfn.XLOOKUP(NG!$B59,BS_NG!$C:$C,BS_NG!F:F),0) -> 94581089 | F59: =IF(F$3<=Summary!$C$2,_xlfn.XLOOKUP(NG!$B59,BS_NG!$C:$C,BS_NG!G:G),0) -> 94581089 | G59: =IF(G$3<=Summary!$C$2,_xlfn.XLOOKUP(NG!$B59,BS_NG!$C:$C,BS_NG!H:H),0) -> 94581089 | H59: =IF(H$3<=Summary!$C$2,_xlfn.XLOOKUP(NG!$B59,BS_NG!$C:$C,BS_NG!I:I),0) -> 94581089 | I59: =IF(I$3<=Summary!$C$2,_xlfn.XLOOKUP(NG!$B59,BS_NG!$C:$C,BS_NG!J:J),0) -> 94581089 | J59: =IF(J$3<=Summary!$C$2,_xlfn.XLOOKUP(NG!$B59,BS_NG!$C:$C,BS_NG!K:K),0) -> 94581089 | K59: =IF(K$3<=Summary!$C$2,_xlfn.XLOOKUP(NG!$B59,BS_NG!$C:$C,BS_NG!L:L),0) -> 94581089 | L59: =IF(L$3<=Summary!$C$2,_xlfn.XLOOKUP(NG!$B59,BS_NG!$C:$C,BS_NG!M:M),0) -> 94581089 | M59: =IF(M$3<=Summary!$C$2,_xlfn.XLOOKUP(NG!$B59,BS_NG!$C:$C,BS_NG!N:N),0) -> 94581089 | N59: =IF(N$3<=Summary!$C$2,_xlfn.XLOOKUP(NG!$B59,BS_NG!$C:$C,BS_NG!O:O),0) -> 94581089 | O59: =IF(O$3<=Summary!$C$2,_xlfn.XLOOKUP(NG!$B59,BS_NG!$C:$C,BS_NG!P:P),0) -> 94581089 | P59: =IF(P$3<=Summary!$C$2,_xlfn.XLOOKUP(NG!$B59,BS_NG!$C:$C,BS_NG!Q:Q),0) -> 94581089 | Q59: =IF(Q$3<=Summary!$C$2,_xlfn.XLOOKUP(NG!$B59,BS_NG!$C:$C,BS_NG!R:R),0) -> 87411677 | R59: =IF(R$3<=Summary!$C$2,_xlfn.XLOOKUP(NG!$B59,BS_NG!$C:$C,BS_NG!S:S),0) -> 78587785 | S59: =IF(S$3<=Summary!$C$2,_xlfn.XLOOKUP(NG!$B59,BS_NG!$C:$C,BS_NG!T:T),0) -> 71142627 | T59: =IF(T$3<=Summary!$C$2,_xlfn.XLOOKUP(NG!$B59,BS_NG!$C:$C,BS_NG!U:U),0) -> 71142627 | U59: =IF(U$3<=Summary!$C$2,_xlfn.XLOOKUP(NG!$B59,BS_NG!$C:$C,BS_NG!V:V),0) -> 56803803 | V59: =IF(V$3<=Summary!$C$2,_xlfn.XLOOKUP(NG!$B59,BS_NG!$C:$C,BS_NG!W:W),0) -> 56803803 | W59: =IF(W$3<=Summary!$C$2,_xlfn.XLOOKUP(NG!$B59,BS_NG!$C:$C,BS_NG!X:X),0) -> 55976563 | X59: =IF(X$3<=Summary!$C$2,_xlfn.XLOOKUP(NG!$B59,BS_NG!$C:$C,BS_NG!Y:Y),0) -> 55976563 | Y59: =IF(Y$3<=Summary!$C$2,_xlfn.XLOOKUP(NG!$B59,BS_NG!$C:$C,BS_NG!Z:Z),0) -> 55700816 | Z59: =IF(Z$3<=Summary!$C$2,_xlfn.XLOOKUP(NG!$B59,BS_NG!$C:$C,BS_NG!AA:AA),0) -> 55425070 | AA59: =IF(AA$3<=Summary!$C$2,_xlfn.XLOOKUP(NG!$B59,BS_NG!$C:$C,BS_NG!AB:AB),0) -> 54597830 | AB59: =IF(AB$3<=Summary!$C$2,_xlfn.XLOOKUP(NG!$B59,BS_NG!$C:$C,BS_NG!AC:AC),0) -> 46325431 | AC59: =IF(AC$3<=Summary!$C$2,_xlfn.XLOOKUP(NG!$B59,BS_NG!$C:$C,BS_NG!AD:AD),0) -> 46325431 | AD59: =IF(AD$3<=Summary!$C$2,_xlfn.XLOOKUP(NG!$B59,BS_NG!$C:$C,BS_NG!AE:AE),0) -> 45773938 | AE59: =IF(AE$3<=Summary!$C$2,_xlfn.XLOOKUP(NG!$B59,BS_NG!$C:$C,BS_NG!AF:AF),0) -> 0 | AF59: =IF(AF$3<=Summary!$C$2,_xlfn.XLOOKUP(NG!$B59,BS_NG!$C:$C,BS_NG!AG:AG),0) -> 0 | AG59: =IF(AG$3<=Summary!$C$2,_xlfn.XLOOKUP(NG!$B59,BS_NG!$C:$C,BS_NG!AH:AH),0) -> 0 | AH59: =IF(AH$3<=Summary!$C$2,_xlfn.XLOOKUP(NG!$B59,BS_NG!$C:$C,BS_NG!AI:AI),0) -> 0 | AI59: =IF(AI$3<=Summary!$C$2,_xlfn.XLOOKUP(NG!$B59,BS_NG!$C:$C,BS_NG!AJ:AJ),0) -> 0 | AJ59: =IF(AJ$3<=Summary!$C$2,_xlfn.XLOOKUP(NG!$B59,BS_NG!$C:$C,BS_NG!AK:AK),0) -> 0 | AK59: =IF(AK$3<=Summary!$C$2,_xlfn.XLOOKUP(NG!$B59,BS_NG!$C:$C,BS_NG!AL:AL),0) -> 0 | AL59: =IF(AL$3<=Summary!$C$2,_xlfn.XLOOKUP(NG!$B59,BS_NG!$C:$C,BS_NG!AM:AM),0) -> 0
B60: TOTAL PREPAID EXPENSES | C60: =IF(C$3<=Summary!$C$2,_xlfn.XLOOKUP(NG!$B60,BS_NG!$C:$C,BS_NG!D:D),0) -> 22077179 | D60: =IF(D$3<=Summary!$C$2,_xlfn.XLOOKUP(NG!$B60,BS_NG!$C:$C,BS_NG!E:E),0) -> 74059780 | E60: =IF(E$3<=Summary!$C$2,_xlfn.XLOOKUP(NG!$B60,BS_NG!$C:$C,BS_NG!F:F),0) -> 38620600 | F60: =IF(F$3<=Summary!$C$2,_xlfn.XLOOKUP(NG!$B60,BS_NG!$C:$C,BS_NG!G:G),0) -> 40346674 | G60: =IF(G$3<=Summary!$C$2,_xlfn.XLOOKUP(NG!$B60,BS_NG!$C:$C,BS_NG!H:H),0) -> 65250461 | H60: =IF(H$3<=Summary!$C$2,_xlfn.XLOOKUP(NG!$B60,BS_NG!$C:$C,BS_NG!I:I),0) -> 83092593 | I60: =IF(I$3<=Summary!$C$2,_xlfn.XLOOKUP(NG!$B60,BS_NG!$C:$C,BS_NG!J:J),0) -> 80098873 | J60: =IF(J$3<=Summary!$C$2,_xlfn.XLOOKUP(NG!$B60,BS_NG!$C:$C,BS_NG!K:K),0) -> 68906334 | K60: =IF(K$3<=Summary!$C$2,_xlfn.XLOOKUP(NG!$B60,BS_NG!$C:$C,BS_NG!L:L),0) -> 72906301 | L60: =IF(L$3<=Summary!$C$2,_xlfn.XLOOKUP(NG!$B60,BS_NG!$C:$C,BS_NG!M:M),0) -> 1.2851512e+08 | M60: =IF(M$3<=Summary!$C$2,_xlfn.XLOOKUP(NG!$B60,BS_NG!$C:$C,BS_NG!N:N),0) -> 97518943 | N60: =IF(N$3<=Summary!$C$2,_xlfn.XLOOKUP(NG!$B60,BS_NG!$C:$C,BS_NG!O:O),0) -> 92286504 | O60: =IF(O$3<=Summary!$C$2,_xlfn.XLOOKUP(NG!$B60,BS_NG!$C:$C,BS_NG!P:P),0) -> 96661499 | P60: =IF(P$3<=Summary!$C$2,_xlfn.XLOOKUP(NG!$B60,BS_NG!$C:$C,BS_NG!Q:Q),0) -> 1.1100954e+08 | Q60: =IF(Q$3<=Summary!$C$2,_xlfn.XLOOKUP(NG!$B60,BS_NG!$C:$C,BS_NG!R:R),0) -> 92711272 | R60: =IF(R$3<=Summary!$C$2,_xlfn.XLOOKUP(NG!$B60,BS_NG!$C:$C,BS_NG!S:S),0) -> 80427568 | S60: =IF(S$3<=Summary!$C$2,_xlfn.XLOOKUP(NG!$B60,BS_NG!$C:$C,BS_NG!T:T),0) -> 85238327 | T60: =IF(T$3<=Summary!$C$2,_xlfn.XLOOKUP(NG!$B60,BS_NG!$C:$C,BS_NG!U:U),0) -> 83813368 | U60: =IF(U$3<=Summary!$C$2,_xlfn.XLOOKUP(NG!$B60,BS_NG!$C:$C,BS_NG!V:V),0) -> 90286615 | V60: =IF(V$3<=Summary!$C$2,_xlfn.XLOOKUP(NG!$B60,BS_NG!$C:$C,BS_NG!W:W),0) -> 1.2847838e+08 | W60: =IF(W$3<=Summary!$C$2,_xlfn.XLOOKUP(NG!$B60,BS_NG!$C:$C,BS_NG!X:X),0) -> 3.0088284e+08 | X60: =IF(X$3<=Summary!$C$2,_xlfn.XLOOKUP(NG!$B60,BS_NG!$C:$C,BS_NG!Y:Y),0) -> 2.8332232e+08 | Y60: =IF(Y$3<=Summary!$C$2,_xlfn.XLOOKUP(NG!$B60,BS_NG!$C:$C,BS_NG!Z:Z),0) -> 2.6218698e+08 | Z60: =IF(Z$3<=Summary!$C$2,_xlfn.XLOOKUP(NG!$B60,BS_NG!$C:$C,BS_NG!AA:AA),0) -> 3.4093581e+08 | AA60: =IF(AA$3<=Summary!$C$2,_xlfn.XLOOKUP(NG!$B60,BS_NG!$C:$C,BS_NG!AB:AB),0) -> 3.0334772e+08 | AB60: =IF(AB$3<=Summary!$C$2,_xlfn.XLOOKUP(NG!$B60,BS_NG!$C:$C,BS_NG!AC:AC),0) -> 2.6391507e+08 | AC60: =IF(AC$3<=Summary!$C$2,_xlfn.XLOOKUP(NG!$B60,BS_NG!$C:$C,BS_NG!AD:AD),0) -> 2.5335284e+08 | AD60: =IF(AD$3<=Summary!$C$2,_xlfn.XLOOKUP(NG!$B60,BS_NG!$C:$C,BS_NG!AE:AE),0) -> 2.1895554e+08 | AE60: =IF(AE$3<=Summary!$C$2,_xlfn.XLOOKUP(NG!$B60,BS_NG!$C:$C,BS_NG!AF:AF),0) -> 0 | AF60: =IF(AF$3<=Summary!$C$2,_xlfn.XLOOKUP(NG!$B60,BS_NG!$C:$C,BS_NG!AG:AG),0) -> 0 | AG60: =IF(AG$3<=Summary!$C$2,_xlfn.XLOOKUP(NG!$B60,BS_NG!$C:$C,BS_NG!AH:AH),0) -> 0 | AH60: =IF(AH$3<=Summary!$C$2,_xlfn.XLOOKUP(NG!$B60,BS_NG!$C:$C,BS_NG!AI:AI),0) -> 0 | AI60: =IF(AI$3<=Summary!$C$2,_xlfn.XLOOKUP(NG!$B60,BS_NG!$C:$C,BS_NG!AJ:AJ),0) -> 0 | AJ60: =IF(AJ$3<=Summary!$C$2,_xlfn.XLOOKUP(NG!$B60,BS_NG!$C:$C,BS_NG!AK:AK),0) -> 0 | AK60: =IF(AK$3<=Summary!$C$2,_xlfn.XLOOKUP(NG!$B60,BS_NG!$C:$C,BS_NG!AL:AL),0) -> 0 | AL60: =IF(AL$3<=Summary!$C$2,_xlfn.XLOOKUP(NG!$B60,BS_NG!$C:$C,BS_NG!AM:AM),0) -> 0
B61: TOTAL STAFF ADVANCES | C61: =IF(C$3<=Summary!$C$2,_xlfn.XLOOKUP(NG!$B61,BS_NG!$C:$C,BS_NG!D:D),0) -> 12611004 | D61: =IF(D$3<=Summary!$C$2,_xlfn.XLOOKUP(NG!$B61,BS_NG!$C:$C,BS_NG!E:E),0) -> 14833354 | E61: =IF(E$3<=Summary!$C$2,_xlfn.XLOOKUP(NG!$B61,BS_NG!$C:$C,BS_NG!F:F),0) -> 12888439 | F61: =IF(F$3<=Summary!$C$2,_xlfn.XLOOKUP(NG!$B61,BS_NG!$C:$C,BS_NG!G:G),0) -> 13837455 | G61: =IF(G$3<=Summary!$C$2,_xlfn.XLOOKUP(NG!$B61,BS_NG!$C:$C,BS_NG!H:H),0) -> 27468685 | H61: =IF(H$3<=Summary!$C$2,_xlfn.XLOOKUP(NG!$B61,BS_NG!$C:$C,BS_NG!I:I),0) -> 3572489.4 | I61: =IF(I$3<=Summary!$C$2,_xlfn.XLOOKUP(NG!$B61,BS_NG!$C:$C,BS_NG!J:J),0) -> 4016143 | J61: =IF(J$3<=Summary!$C$2,_xlfn.XLOOKUP(NG!$B61,BS_NG!$C:$C,BS_NG!K:K),0) -> 7014445 | K61: =IF(K$3<=Summary!$C$2,_xlfn.XLOOKUP(NG!$B61,BS_NG!$C:$C,BS_NG!L:L),0) -> 345714.9 | L61: =IF(L$3<=Summary!$C$2,_xlfn.XLOOKUP(NG!$B61,BS_NG!$C:$C,BS_NG!M:M),0) -> 9045220.8 | M61: =IF(M$3<=Summary!$C$2,_xlfn.XLOOKUP(NG!$B61,BS_NG!$C:$C,BS_NG!N:N),0) -> 794390.73 | N61: =IF(N$3<=Summary!$C$2,_xlfn.XLOOKUP(NG!$B61,BS_NG!$C:$C,BS_NG!O:O),0) -> 3260413.5 | O61: =IF(O$3<=Summary!$C$2,_xlfn.XLOOKUP(NG!$B61,BS_NG!$C:$C,BS_NG!P:P),0) -> 3311256.8 | P61: =IF(P$3<=Summary!$C$2,_xlfn.XLOOKUP(NG!$B61,BS_NG!$C:$C,BS_NG!Q:Q),0) -> 5951146 | Q61: =IF(Q$3<=Summary!$C$2,_xlfn.XLOOKUP(NG!$B61,BS_NG!$C:$C,BS_NG!R:R),0) -> 2977547.2 | R61: =IF(R$3<=Summary!$C$2,_xlfn.XLOOKUP(NG!$B61,BS_NG!$C:$C,BS_NG!S:S),0) -> 3125317.2 | S61: =IF(S$3<=Summary!$C$2,_xlfn.XLOOKUP(NG!$B61,BS_NG!$C:$C,BS_NG!T:T),0) -> 6571230.7 | T61: =IF(T$3<=Summary!$C$2,_xlfn.XLOOKUP(NG!$B61,BS_NG!$C:$C,BS_NG!U:U),0) -> 3137992 | U61: =IF(U$3<=Summary!$C$2,_xlfn.XLOOKUP(NG!$B61,BS_NG!$C:$C,BS_NG!V:V),0) -> 5480720.5 | V61: =IF(V$3<=Summary!$C$2,_xlfn.XLOOKUP(NG!$B61,BS_NG!$C:$C,BS_NG!W:W),0) -> 2548373.1 | W61: =IF(W$3<=Summary!$C$2,_xlfn.XLOOKUP(NG!$B61,BS_NG!$C:$C,BS_NG!X:X),0) -> 210000 | X61: =IF(X$3<=Summary!$C$2,_xlfn.XLOOKUP(NG!$B61,BS_NG!$C:$C,BS_NG!Y:Y),0) -> 2499043.8 | Y61: =IF(Y$3<=Summary!$C$2,_xlfn.XLOOKUP(NG!$B61,BS_NG!$C:$C,BS_NG!Z:Z),0) -> 18152149 | Z61: =IF(Z$3<=Summary!$C$2,_xlfn.XLOOKUP(NG!$B61,BS_NG!$C:$C,BS_NG!AA:AA),0) -> 402004.23 | AA61: =IF(AA$3<=Summary!$C$2,_xlfn.XLOOKUP(NG!$B61,BS_NG!$C:$C,BS_NG!AB:AB),0) -> 732616.21 | AB61: =IF(AB$3<=Summary!$C$2,_xlfn.XLOOKUP(NG!$B61,BS_NG!$C:$C,BS_NG!AC:AC),0) -> 4418410.5 | AC61: =IF(AC$3<=Summary!$C$2,_xlfn.XLOOKUP(NG!$B61,BS_NG!$C:$C,BS_NG!AD:AD),0) -> 1737292.6 | AD61: =IF(AD$3<=Summary!$C$2,_xlfn.XLOOKUP(NG!$B61,BS_NG!$C:$C,BS_NG!AE:AE),0) -> 7688792.7 | AE61: =IF(AE$3<=Summary!$C$2,_xlfn.XLOOKUP(NG!$B61,BS_NG!$C:$C,BS_NG!AF:AF),0) -> 0 | AF61: =IF(AF$3<=Summary!$C$2,_xlfn.XLOOKUP(NG!$B61,BS_NG!$C:$C,BS_NG!AG:AG),0) -> 0 | AG61: =IF(AG$3<=Summary!$C$2,_xlfn.XLOOKUP(NG!$B61,BS_NG!$C:$C,BS_NG!AH:AH),0) -> 0 | AH61: =IF(AH$3<=Summary!$C$2,_xlfn.XLOOKUP(NG!$B61,BS_NG!$C:$C,BS_NG!AI:AI),0) -> 0 | AI61: =IF(AI$3<=Summary!$C$2,_xlfn.XLOOKUP(NG!$B61,BS_NG!$C:$C,BS_NG!AJ:AJ),0) -> 0 | AJ61: =IF(AJ$3<=Summary!$C$2,_xlfn.XLOOKUP(NG!$B61,BS_NG!$C:$C,BS_NG!AK:AK),0) -> 0 | AK61: =IF(AK$3<=Summary!$C$2,_xlfn.XLOOKUP(NG!$B61,BS_NG!$C:$C,BS_NG!AL:AL),0) -> 0 | AL61: =IF(AL$3<=Summary!$C$2,_xlfn.XLOOKUP(NG!$B61,BS_NG!$C:$C,BS_NG!AM:AM),0) -> 0
B62: TOTAL OTHER RECIEVABLES ` | C62: =IF(C$3<=Summary!$C$2,_xlfn.XLOOKUP(NG!$B62,BS_NG!$C:$C,BS_NG!D:D),0) -> 5.0239586e+08 | D62: =IF(D$3<=Summary!$C$2,_xlfn.XLOOKUP(NG!$B62,BS_NG!$C:$C,BS_NG!E:E),0) -> 5.1887844e+08 | E62: =IF(E$3<=Summary!$C$2,_xlfn.XLOOKUP(NG!$B62,BS_NG!$C:$C,BS_NG!F:F),0) -> 5.8605444e+08 | F62: =IF(F$3<=Summary!$C$2,_xlfn.XLOOKUP(NG!$B62,BS_NG!$C:$C,BS_NG!G:G),0) -> 6.7500227e+08 | G62: =IF(G$3<=Summary!$C$2,_xlfn.XLOOKUP(NG!$B62,BS_NG!$C:$C,BS_NG!H:H),0) -> 7.1945777e+08 | H62: =IF(H$3<=Summary!$C$2,_xlfn.XLOOKUP(NG!$B62,BS_NG!$C:$C,BS_NG!I:I),0) -> 7.1606199e+08 | I62: =IF(I$3<=Summary!$C$2,_xlfn.XLOOKUP(NG!$B62,BS_NG!$C:$C,BS_NG!J:J),0) -> 7.1839552e+08 | J62: =IF(J$3<=Summary!$C$2,_xlfn.XLOOKUP(NG!$B62,BS_NG!$C:$C,BS_NG!K:K),0) -> 7.6065332e+08 | K62: =IF(K$3<=Summary!$C$2,_xlfn.XLOOKUP(NG!$B62,BS_NG!$C:$C,BS_NG!L:L),0) -> 7.4702691e+08 | L62: =IF(L$3<=Summary!$C$2,_xlfn.XLOOKUP(NG!$B62,BS_NG!$C:$C,BS_NG!M:M),0) -> 7.734756e+08 | M62: =IF(M$3<=Summary!$C$2,_xlfn.XLOOKUP(NG!$B62,BS_NG!$C:$C,BS_NG!N:N),0) -> 7.8912442e+08 | N62: =IF(N$3<=Summary!$C$2,_xlfn.XLOOKUP(NG!$B62,BS_NG!$C:$C,BS_NG!O:O),0) -> 8.0049954e+08 | O62: =IF(O$3<=Summary!$C$2,_xlfn.XLOOKUP(NG!$B62,BS_NG!$C:$C,BS_NG!P:P),0) -> 8.3090725e+08 | P62: =IF(P$3<=Summary!$C$2,_xlfn.XLOOKUP(NG!$B62,BS_NG!$C:$C,BS_NG!Q:Q),0) -> 8.2747363e+08 | Q62: =IF(Q$3<=Summary!$C$2,_xlfn.XLOOKUP(NG!$B62,BS_NG!$C:$C,BS_NG!R:R),0) -> 9.130247e+08 | R62: =IF(R$3<=Summary!$C$2,_xlfn.XLOOKUP(NG!$B62,BS_NG!$C:$C,BS_NG!S:S),0) -> 9.1674579e+08 | S62: =IF(S$3<=Summary!$C$2,_xlfn.XLOOKUP(NG!$B62,BS_NG!$C:$C,BS_NG!T:T),0) -> 9.3171272e+08 | T62: =IF(T$3<=Summary!$C$2,_xlfn.XLOOKUP(NG!$B62,BS_NG!$C:$C,BS_NG!U:U),0) -> 9.7429821e+08 | U62: =IF(U$3<=Summary!$C$2,_xlfn.XLOOKUP(NG!$B62,BS_NG!$C:$C,BS_NG!V:V),0) -> 9.7843118e+08 | V62: =IF(V$3<=Summary!$C$2,_xlfn.XLOOKUP(NG!$B62,BS_NG!$C:$C,BS_NG!W:W),0) -> 9.5471681e+08 | W62: =IF(W$3<=Summary!$C$2,_xlfn.XLOOKUP(NG!$B62,BS_NG!$C:$C,BS_NG!X:X),0) -> 9.5283137e+08 | X62: =IF(X$3<=Summary!$C$2,_xlfn.XLOOKUP(NG!$B62,BS_NG!$C:$C,BS_NG!Y:Y),0) -> 9.5253159e+08 | Y62: =IF(Y$3<=Summary!$C$2,_xlfn.XLOOKUP(NG!$B62,BS_NG!$C:$C,BS_NG!Z:Z),0) -> 9.6221039e+08 | Z62: =IF(Z$3<=Summary!$C$2,_xlfn.XLOOKUP(NG!$B62,BS_NG!$C:$C,BS_NG!AA:AA),0) -> 5.6458349e+08 | AA62: =IF(AA$3<=Summary!$C$2,_xlfn.XLOOKUP(NG!$B62,BS_NG!$C:$C,BS_NG!AB:AB),0) -> 5.6173938e+08 | AB62: =IF(AB$3<=Summary!$C$2,_xlfn.XLOOKUP(NG!$B62,BS_NG!$C:$C,BS_NG!AC:AC),0) -> 5.6453073e+08 | AC62: =IF(AC$3<=Summary!$C$2,_xlfn.XLOOKUP(NG!$B62,BS_NG!$C:$C,BS_NG!AD:AD),0) -> 5.6979642e+08 | AD62: =IF(AD$3<=Summary!$C$2,_xlfn.XLOOKUP(NG!$B62,BS_NG!$C:$C,BS_NG!AE:AE),0) -> 5.7228463e+08 | AE62: =IF(AE$3<=Summary!$C$2,_xlfn.XLOOKUP(NG!$B62,BS_NG!$C:$C,BS_NG!AF:AF),0) -> 0 | AF62: =IF(AF$3<=Summary!$C$2,_xlfn.XLOOKUP(NG!$B62,BS_NG!$C:$C,BS_NG!AG:AG),0) -> 0 | AG62: =IF(AG$3<=Summary!$C$2,_xlfn.XLOOKUP(NG!$B62,BS_NG!$C:$C,BS_NG!AH:AH),0) -> 0 | AH62: =IF(AH$3<=Summary!$C$2,_xlfn.XLOOKUP(NG!$B62,BS_NG!$C:$C,BS_NG!AI:AI),0) -> 0 | AI62: =IF(AI$3<=Summary!$C$2,_xlfn.XLOOKUP(NG!$B62,BS_NG!$C:$C,BS_NG!AJ:AJ),0) -> 0 | AJ62: =IF(AJ$3<=Summary!$C$2,_xlfn.XLOOKUP(NG!$B62,BS_NG!$C:$C,BS_NG!AK:AK),0) -> 0 | AK62: =IF(AK$3<=Summary!$C$2,_xlfn.XLOOKUP(NG!$B62,BS_NG!$C:$C,BS_NG!AL:AL),0) -> 0 | AL62: =IF(AL$3<=Summary!$C$2,_xlfn.XLOOKUP(NG!$B62,BS_NG!$C:$C,BS_NG!AM:AM),0) -> 0
B63: TOTAL OTHER DEBTORS (RELATED PARTY) | C63: =IF(C$3<=Summary!$C$2,_xlfn.XLOOKUP(NG!$B63,BS_NG!$C:$C,BS_NG!D:D),0) -> -2.2322933e+08 | D63: =IF(D$3<=Summary!$C$2,_xlfn.XLOOKUP(NG!$B63,BS_NG!$C:$C,BS_NG!E:E),0) -> -2.3797171e+08 | E63: =IF(E$3<=Summary!$C$2,_xlfn.XLOOKUP(NG!$B63,BS_NG!$C:$C,BS_NG!F:F),0) -> -2.4714801e+08 | F63: =IF(F$3<=Summary!$C$2,_xlfn.XLOOKUP(NG!$B63,BS_NG!$C:$C,BS_NG!G:G),0) -> -2.3567926e+08 | G63: =IF(G$3<=Summary!$C$2,_xlfn.XLOOKUP(NG!$B63,BS_NG!$C:$C,BS_NG!H:H),0) -> -2.2556047e+08 | H63: =IF(H$3<=Summary!$C$2,_xlfn.XLOOKUP(NG!$B63,BS_NG!$C:$C,BS_NG!I:I),0) -> -2.2043691e+08 | I63: =IF(I$3<=Summary!$C$2,_xlfn.XLOOKUP(NG!$B63,BS_NG!$C:$C,BS_NG!J:J),0) -> -2.0135479e+08 | J63: =IF(J$3<=Summary!$C$2,_xlfn.XLOOKUP(NG!$B63,BS_NG!$C:$C,BS_NG!K:K),0) -> -2.0335905e+08 | K63: =IF(K$3<=Summary!$C$2,_xlfn.XLOOKUP(NG!$B63,BS_NG!$C:$C,BS_NG!L:L),0) -> -1.6229977e+08 | L63: =IF(L$3<=Summary!$C$2,_xlfn.XLOOKUP(NG!$B63,BS_NG!$C:$C,BS_NG!M:M),0) -> -1.4746883e+08 | M63: =IF(M$3<=Summary!$C$2,_xlfn.XLOOKUP(NG!$B63,BS_NG!$C:$C,BS_NG!N:N),0) -> -2.3359963e+08 | N63: =IF(N$3<=Summary!$C$2,_xlfn.XLOOKUP(NG!$B63,BS_NG!$C:$C,BS_NG!O:O),0) -> -6.8602046e+08 | O63: =IF(O$3<=Summary!$C$2,_xlfn.XLOOKUP(NG!$B63,BS_NG!$C:$C,BS_NG!P:P),0) -> -6.8092284e+08 | P63: =IF(P$3<=Summary!$C$2,_xlfn.XLOOKUP(NG!$B63,BS_NG!$C:$C,BS_NG!Q:Q),0) -> -6.3110952e+08 | Q63: =IF(Q$3<=Summary!$C$2,_xlfn.XLOOKUP(NG!$B63,BS_NG!$C:$C,BS_NG!R:R),0) -> -6.2623487e+08 | R63: =IF(R$3<=Summary!$C$2,_xlfn.XLOOKUP(NG!$B63,BS_NG!$C:$C,BS_NG!S:S),0) -> -6.2168516e+08 | S63: =IF(S$3<=Summary!$C$2,_xlfn.XLOOKUP(NG!$B63,BS_NG!$C:$C,BS_NG!T:T),0) -> -6.1707394e+08 | T63: =IF(T$3<=Summary!$C$2,_xlfn.XLOOKUP(NG!$B63,BS_NG!$C:$C,BS_NG!U:U),0) -> -6.1216583e+08 | U63: =IF(U$3<=Summary!$C$2,_xlfn.XLOOKUP(NG!$B63,BS_NG!$C:$C,BS_NG!V:V),0) -> -6.076001e+08 | V63: =IF(V$3<=Summary!$C$2,_xlfn.XLOOKUP(NG!$B63,BS_NG!$C:$C,BS_NG!W:W),0) -> -6.0461043e+08 | W63: =IF(W$3<=Summary!$C$2,_xlfn.XLOOKUP(NG!$B63,BS_NG!$C:$C,BS_NG!X:X),0) -> -6.304927e+08 | X63: =IF(X$3<=Summary!$C$2,_xlfn.XLOOKUP(NG!$B63,BS_NG!$C:$C,BS_NG!Y:Y),0) -> -6.1184751e+08 | Y63: =IF(Y$3<=Summary!$C$2,_xlfn.XLOOKUP(NG!$B63,BS_NG!$C:$C,BS_NG!Z:Z),0) -> -6.0789301e+08 | Z63: =IF(Z$3<=Summary!$C$2,_xlfn.XLOOKUP(NG!$B63,BS_NG!$C:$C,BS_NG!AA:AA),0) -> -1.1845275e+09 | AA63: =IF(AA$3<=Summary!$C$2,_xlfn.XLOOKUP(NG!$B63,BS_NG!$C:$C,BS_NG!AB:AB),0) -> -1.1574578e+09 | AB63: =IF(AB$3<=Summary!$C$2,_xlfn.XLOOKUP(NG!$B63,BS_NG!$C:$C,BS_NG!AC:AC),0) -> -1.1351268e+09 | AC63: =IF(AC$3<=Summary!$C$2,_xlfn.XLOOKUP(NG!$B63,BS_NG!$C:$C,BS_NG!AD:AD),0) -> -1.1097155e+09 | AD63: =IF(AD$3<=Summary!$C$2,_xlfn.XLOOKUP(NG!$B63,BS_NG!$C:$C,BS_NG!AE:AE),0) -> -1.0899058e+09 | AE63: =IF(AE$3<=Summary!$C$2,_xlfn.XLOOKUP(NG!$B63,BS_NG!$C:$C,BS_NG!AF:AF),0) -> 0 | AF63: =IF(AF$3<=Summary!$C$2,_xlfn.XLOOKUP(NG!$B63,BS_NG!$C:$C,BS_NG!AG:AG),0) -> 0 | AG63: =IF(AG$3<=Summary!$C$2,_xlfn.XLOOKUP(NG!$B63,BS_NG!$C:$C,BS_NG!AH:AH),0) -> 0 | AH63: =IF(AH$3<=Summary!$C$2,_xlfn.XLOOKUP(NG!$B63,BS_NG!$C:$C,BS_NG!AI:AI),0) -> 0 | AI63: =IF(AI$3<=Summary!$C$2,_xlfn.XLOOKUP(NG!$B63,BS_NG!$C:$C,BS_NG!AJ:AJ),0) -> 0 | AJ63: =IF(AJ$3<=Summary!$C$2,_xlfn.XLOOKUP(NG!$B63,BS_NG!$C:$C,BS_NG!AK:AK),0) -> 0 | AK63: =IF(AK$3<=Summary!$C$2,_xlfn.XLOOKUP(NG!$B63,BS_NG!$C:$C,BS_NG!AL:AL),0) -> 0 | AL63: =IF(AL$3<=Summary!$C$2,_xlfn.XLOOKUP(NG!$B63,BS_NG!$C:$C,BS_NG!AM:AM),0) -> 0
B64: TOTAL PROPERTY, PLANT AND EQUIPMENT | C64: =IF(C$3<=Summary!$C$2,_xlfn.XLOOKUP(NG!$B64,BS_NG!$C:$C,BS_NG!D:D),0) -> 2.8689168e+08 | D64: =IF(D$3<=Summary!$C$2,_xlfn.XLOOKUP(NG!$B64,BS_NG!$C:$C,BS_NG!E:E),0) -> 2.8407821e+08 | E64: =IF(E$3<=Summary!$C$2,_xlfn.XLOOKUP(NG!$B64,BS_NG!$C:$C,BS_NG!F:F),0) -> 2.8128681e+08 | F64: =IF(F$3<=Summary!$C$2,_xlfn.XLOOKUP(NG!$B64,BS_NG!$C:$C,BS_NG!G:G),0) -> 2.8242954e+08 | G64: =IF(G$3<=Summary!$C$2,_xlfn.XLOOKUP(NG!$B64,BS_NG!$C:$C,BS_NG!H:H),0) -> 2.9302831e+08 | H64: =IF(H$3<=Summary!$C$2,_xlfn.XLOOKUP(NG!$B64,BS_NG!$C:$C,BS_NG!I:I),0) -> 2.8979749e+08 | I64: =IF(I$3<=Summary!$C$2,_xlfn.XLOOKUP(NG!$B64,BS_NG!$C:$C,BS_NG!J:J),0) -> 2.9223617e+08 | J64: =IF(J$3<=Summary!$C$2,_xlfn.XLOOKUP(NG!$B64,BS_NG!$C:$C,BS_NG!K:K),0) -> 2.9322268e+08 | K64: =IF(K$3<=Summary!$C$2,_xlfn.XLOOKUP(NG!$B64,BS_NG!$C:$C,BS_NG!L:L),0) -> 2.9022811e+08 | L64: =IF(L$3<=Summary!$C$2,_xlfn.XLOOKUP(NG!$B64,BS_NG!$C:$C,BS_NG!M:M),0) -> 2.9998902e+08 | M64: =IF(M$3<=Summary!$C$2,_xlfn.XLOOKUP(NG!$B64,BS_NG!$C:$C,BS_NG!N:N),0) -> 3.0477273e+08 | N64: =IF(N$3<=Summary!$C$2,_xlfn.XLOOKUP(NG!$B64,BS_NG!$C:$C,BS_NG!O:O),0) -> 3.1684221e+08 | O64: =IF(O$3<=Summary!$C$2,_xlfn.XLOOKUP(NG!$B64,BS_NG!$C:$C,BS_NG!P:P),0) -> 3.1326373e+08 | P64: =IF(P$3<=Summary!$C$2,_xlfn.XLOOKUP(NG!$B64,BS_NG!$C:$C,BS_NG!Q:Q),0) -> 3.256182e+08 | Q64: =IF(Q$3<=Summary!$C$2,_xlfn.XLOOKUP(NG!$B64,BS_NG!$C:$C,BS_NG!R:R),0) -> 3.2356539e+08 | R64: =IF(R$3<=Summary!$C$2,_xlfn.XLOOKUP(NG!$B64,BS_NG!$C:$C,BS_NG!S:S),0) -> 3.1993667e+08 | S64: =IF(S$3<=Summary!$C$2,_xlfn.XLOOKUP(NG!$B64,BS_NG!$C:$C,BS_NG!T:T),0) -> 3.1692026e+08 | T64: =IF(T$3<=Summary!$C$2,_xlfn.XLOOKUP(NG!$B64,BS_NG!$C:$C,BS_NG!U:U),0) -> 3.1328386e+08 | U64: =IF(U$3<=Summary!$C$2,_xlfn.XLOOKUP(NG!$B64,BS_NG!$C:$C,BS_NG!V:V),0) -> 3.2054859e+08 | V64: =IF(V$3<=Summary!$C$2,_xlfn.XLOOKUP(NG!$B64,BS_NG!$C:$C,BS_NG!W:W),0) -> 3.2585888e+08 | W64: =IF(W$3<=Summary!$C$2,_xlfn.XLOOKUP(NG!$B64,BS_NG!$C:$C,BS_NG!X:X),0) -> 3.2201841e+08 | X64: =IF(X$3<=Summary!$C$2,_xlfn.XLOOKUP(NG!$B64,BS_NG!$C:$C,BS_NG!Y:Y),0) -> 3.1808436e+08 | Y64: =IF(Y$3<=Summary!$C$2,_xlfn.XLOOKUP(NG!$B64,BS_NG!$C:$C,BS_NG!Z:Z),0) -> 3.2751406e+08 | Z64: =IF(Z$3<=Summary!$C$2,_xlfn.XLOOKUP(NG!$B64,BS_NG!$C:$C,BS_NG!AA:AA),0) -> 3.2630087e+08 | AA64: =IF(AA$3<=Summary!$C$2,_xlfn.XLOOKUP(NG!$B64,BS_NG!$C:$C,BS_NG!AB:AB),0) -> 3.0777732e+08 | AB64: =IF(AB$3<=Summary!$C$2,_xlfn.XLOOKUP(NG!$B64,BS_NG!$C:$C,BS_NG!AC:AC),0) -> 3.1040524e+08 | AC64: =IF(AC$3<=Summary!$C$2,_xlfn.XLOOKUP(NG!$B64,BS_NG!$C:$C,BS_NG!AD:AD),0) -> 3.2383082e+08 | AD64: =IF(AD$3<=Summary!$C$2,_xlfn.XLOOKUP(NG!$B64,BS_NG!$C:$C,BS_NG!AE:AE),0) -> 3.3451628e+08 | AE64: =IF(AE$3<=Summary!$C$2,_xlfn.XLOOKUP(NG!$B64,BS_NG!$C:$C,BS_NG!AF:AF),0) -> 0 | AF64: =IF(AF$3<=Summary!$C$2,_xlfn.XLOOKUP(NG!$B64,BS_NG!$C:$C,BS_NG!AG:AG),0) -> 0 | AG64: =IF(AG$3<=Summary!$C$2,_xlfn.XLOOKUP(NG!$B64,BS_NG!$C:$C,BS_NG!AH:AH),0) -> 0 | AH64: =IF(AH$3<=Summary!$C$2,_xlfn.XLOOKUP(NG!$B64,BS_NG!$C:$C,BS_NG!AI:AI),0) -> 0 | AI64: =IF(AI$3<=Summary!$C$2,_xlfn.XLOOKUP(NG!$B64,BS_NG!$C:$C,BS_NG!AJ:AJ),0) -> 0 | AJ64: =IF(AJ$3<=Summary!$C$2,_xlfn.XLOOKUP(NG!$B64,BS_NG!$C:$C,BS_NG!AK:AK),0) -> 0 | AK64: =IF(AK$3<=Summary!$C$2,_xlfn.XLOOKUP(NG!$B64,BS_NG!$C:$C,BS_NG!AL:AL),0) -> 0 | AL64: =IF(AL$3<=Summary!$C$2,_xlfn.XLOOKUP(NG!$B64,BS_NG!$C:$C,BS_NG!AM:AM),0) -> 0
B65: TOTAL INTANGIBLE ASSETS | C65: =IF(C$3<=Summary!$C$2,_xlfn.XLOOKUP(NG!$B65,BS_NG!$C:$C,BS_NG!D:D),0) -> 3.5673319e+08 | D65: =IF(D$3<=Summary!$C$2,_xlfn.XLOOKUP(NG!$B65,BS_NG!$C:$C,BS_NG!E:E),0) -> 3.7576751e+08 | E65: =IF(E$3<=Summary!$C$2,_xlfn.XLOOKUP(NG!$B65,BS_NG!$C:$C,BS_NG!F:F),0) -> 4.0104206e+08 | F65: =IF(F$3<=Summary!$C$2,_xlfn.XLOOKUP(NG!$B65,BS_NG!$C:$C,BS_NG!G:G),0) -> 4.222662e+08 | G65: =IF(G$3<=Summary!$C$2,_xlfn.XLOOKUP(NG!$B65,BS_NG!$C:$C,BS_NG!H:H),0) -> 4.4451126e+08 | H65: =IF(H$3<=Summary!$C$2,_xlfn.XLOOKUP(NG!$B65,BS_NG!$C:$C,BS_NG!I:I),0) -> 5.1501929e+08 | I65: =IF(I$3<=Summary!$C$2,_xlfn.XLOOKUP(NG!$B65,BS_NG!$C:$C,BS_NG!J:J),0) -> 6.2670187e+08 | J65: =IF(J$3<=Summary!$C$2,_xlfn.XLOOKUP(NG!$B65,BS_NG!$C:$C,BS_NG!K:K),0) -> 7.0731688e+08 | K65: =IF(K$3<=Summary!$C$2,_xlfn.XLOOKUP(NG!$B65,BS_NG!$C:$C,BS_NG!L:L),0) -> 8.3263151e+08 | L65: =IF(L$3<=Summary!$C$2,_xlfn.XLOOKUP(NG!$B65,BS_NG!$C:$C,BS_NG!M:M),0) -> 9.9287626e+08 | M65: =IF(M$3<=Summary!$C$2,_xlfn.XLOOKUP(NG!$B65,BS_NG!$C:$C,BS_NG!N:N),0) -> 1.0301576e+09 | N65: =IF(N$3<=Summary!$C$2,_xlfn.XLOOKUP(NG!$B65,BS_NG!$C:$C,BS_NG!O:O),0) -> 1.0682298e+09 | O65: =IF(O$3<=Summary!$C$2,_xlfn.XLOOKUP(NG!$B65,BS_NG!$C:$C,BS_NG!P:P),0) -> 1.2057744e+09 | P65: =IF(P$3<=Summary!$C$2,_xlfn.XLOOKUP(NG!$B65,BS_NG!$C:$C,BS_NG!Q:Q),0) -> 1.3084204e+09 | Q65: =IF(Q$3<=Summary!$C$2,_xlfn.XLOOKUP(NG!$B65,BS_NG!$C:$C,BS_NG!R:R),0) -> 1.3709682e+09 | R65: =IF(R$3<=Summary!$C$2,_xlfn.XLOOKUP(NG!$B65,BS_NG!$C:$C,BS_NG!S:S),0) -> 1.56522e+09 | S65: =IF(S$3<=Summary!$C$2,_xlfn.XLOOKUP(NG!$B65,BS_NG!$C:$C,BS_NG!T:T),0) -> 1.5699297e+09 | T65: =IF(T$3<=Summary!$C$2,_xlfn.XLOOKUP(NG!$B65,BS_NG!$C:$C,BS_NG!U:U),0) -> 1.6440995e+09 | U65: =IF(U$3<=Summary!$C$2,_xlfn.XLOOKUP(NG!$B65,BS_NG!$C:$C,BS_NG!V:V),0) -> 1.7414644e+09 | V65: =IF(V$3<=Summary!$C$2,_xlfn.XLOOKUP(NG!$B65,BS_NG!$C:$C,BS_NG!W:W),0) -> 1.9327395e+09 | W65: =IF(W$3<=Summary!$C$2,_xlfn.XLOOKUP(NG!$B65,BS_NG!$C:$C,BS_NG!X:X),0) -> 2.0616904e+09 | X65: =IF(X$3<=Summary!$C$2,_xlfn.XLOOKUP(NG!$B65,BS_NG!$C:$C,BS_NG!Y:Y),0) -> 2.1457428e+09 | Y65: =IF(Y$3<=Summary!$C$2,_xlfn.XLOOKUP(NG!$B65,BS_NG!$C:$C,BS_NG!Z:Z),0) -> 2.1715944e+09 | Z65: =IF(Z$3<=Summary!$C$2,_xlfn.XLOOKUP(NG!$B65,BS_NG!$C:$C,BS_NG!AA:AA),0) -> 2.3488014e+09 | AA65: =IF(AA$3<=Summary!$C$2,_xlfn.XLOOKUP(NG!$B65,BS_NG!$C:$C,BS_NG!AB:AB),0) -> 2.3621915e+09 | AB65: =IF(AB$3<=Summary!$C$2,_xlfn.XLOOKUP(NG!$B65,BS_NG!$C:$C,BS_NG!AC:AC),0) -> 2.358463e+09 | AC65: =IF(AC$3<=Summary!$C$2,_xlfn.XLOOKUP(NG!$B65,BS_NG!$C:$C,BS_NG!AD:AD),0) -> 2.4328338e+09 | AD65: =IF(AD$3<=Summary!$C$2,_xlfn.XLOOKUP(NG!$B65,BS_NG!$C:$C,BS_NG!AE:AE),0) -> 2.425516e+09 | AE65: =IF(AE$3<=Summary!$C$2,_xlfn.XLOOKUP(NG!$B65,BS_NG!$C:$C,BS_NG!AF:AF),0) -> 0 | AF65: =IF(AF$3<=Summary!$C$2,_xlfn.XLOOKUP(NG!$B65,BS_NG!$C:$C,BS_NG!AG:AG),0) -> 0 | AG65: =IF(AG$3<=Summary!$C$2,_xlfn.XLOOKUP(NG!$B65,BS_NG!$C:$C,BS_NG!AH:AH),0) -> 0 | AH65: =IF(AH$3<=Summary!$C$2,_xlfn.XLOOKUP(NG!$B65,BS_NG!$C:$C,BS_NG!AI:AI),0) -> 0 | AI65: =IF(AI$3<=Summary!$C$2,_xlfn.XLOOKUP(NG!$B65,BS_NG!$C:$C,BS_NG!AJ:AJ),0) -> 0 | AJ65: =IF(AJ$3<=Summary!$C$2,_xlfn.XLOOKUP(NG!$B65,BS_NG!$C:$C,BS_NG!AK:AK),0) -> 0 | AK65: =IF(AK$3<=Summary!$C$2,_xlfn.XLOOKUP(NG!$B65,BS_NG!$C:$C,BS_NG!AL:AL),0) -> 0 | AL65: =IF(AL$3<=Summary!$C$2,_xlfn.XLOOKUP(NG!$B65,BS_NG!$C:$C,BS_NG!AM:AM),0) -> 0
B66: TOTAL OTHER FIXED ASSET | C66: =IF(C$3<=Summary!$C$2,_xlfn.XLOOKUP(NG!$B66,BS_NG!$C:$C,BS_NG!D:D),0) -> 5.2005654e+08 | D66: =IF(D$3<=Summary!$C$2,_xlfn.XLOOKUP(NG!$B66,BS_NG!$C:$C,BS_NG!E:E),0) -> 7.9681561e+08 | E66: =IF(E$3<=Summary!$C$2,_xlfn.XLOOKUP(NG!$B66,BS_NG!$C:$C,BS_NG!F:F),0) -> 8.1181561e+08 | F66: =IF(F$3<=Summary!$C$2,_xlfn.XLOOKUP(NG!$B66,BS_NG!$C:$C,BS_NG!G:G),0) -> 1.099042e+09 | G66: =IF(G$3<=Summary!$C$2,_xlfn.XLOOKUP(NG!$B66,BS_NG!$C:$C,BS_NG!H:H),0) -> 1.2260456e+09 | H66: =IF(H$3<=Summary!$C$2,_xlfn.XLOOKUP(NG!$B66,BS_NG!$C:$C,BS_NG!I:I),0) -> 1.2260456e+09 | I66: =IF(I$3<=Summary!$C$2,_xlfn.XLOOKUP(NG!$B66,BS_NG!$C:$C,BS_NG!J:J),0) -> 1.2260456e+09 | J66: =IF(J$3<=Summary!$C$2,_xlfn.XLOOKUP(NG!$B66,BS_NG!$C:$C,BS_NG!K:K),0) -> 1.4778917e+09 | K66: =IF(K$3<=Summary!$C$2,_xlfn.XLOOKUP(NG!$B66,BS_NG!$C:$C,BS_NG!L:L),0) -> 1.4778917e+09 | L66: =IF(L$3<=Summary!$C$2,_xlfn.XLOOKUP(NG!$B66,BS_NG!$C:$C,BS_NG!M:M),0) -> 1.4800353e+09 | M66: =IF(M$3<=Summary!$C$2,_xlfn.XLOOKUP(NG!$B66,BS_NG!$C:$C,BS_NG!N:N),0) -> 1.4810353e+09 | N66: =IF(N$3<=Summary!$C$2,_xlfn.XLOOKUP(NG!$B66,BS_NG!$C:$C,BS_NG!O:O),0) -> 1.4995475e+09 | O66: =IF(O$3<=Summary!$C$2,_xlfn.XLOOKUP(NG!$B66,BS_NG!$C:$C,BS_NG!P:P),0) -> 1.7106309e+09 | P66: =IF(P$3<=Summary!$C$2,_xlfn.XLOOKUP(NG!$B66,BS_NG!$C:$C,BS_NG!Q:Q),0) -> 1.7106309e+09 | Q66: =IF(Q$3<=Summary!$C$2,_xlfn.XLOOKUP(NG!$B66,BS_NG!$C:$C,BS_NG!R:R),0) -> 1.7106309e+09 | R66: =IF(R$3<=Summary!$C$2,_xlfn.XLOOKUP(NG!$B66,BS_NG!$C:$C,BS_NG!S:S),0) -> 1.8926302e+09 | S66: =IF(S$3<=Summary!$C$2,_xlfn.XLOOKUP(NG!$B66,BS_NG!$C:$C,BS_NG!T:T),0) -> 1.8926302e+09 | T66: =IF(T$3<=Summary!$C$2,_xlfn.XLOOKUP(NG!$B66,BS_NG!$C:$C,BS_NG!U:U),0) -> 2.051255e+09 | U66: =IF(U$3<=Summary!$C$2,_xlfn.XLOOKUP(NG!$B66,BS_NG!$C:$C,BS_NG!V:V),0) -> 2.3877074e+09 | V66: =IF(V$3<=Summary!$C$2,_xlfn.XLOOKUP(NG!$B66,BS_NG!$C:$C,BS_NG!W:W),0) -> 2.3877074e+09 | W66: =IF(W$3<=Summary!$C$2,_xlfn.XLOOKUP(NG!$B66,BS_NG!$C:$C,BS_NG!X:X),0) -> 2.3889247e+09 | X66: =IF(X$3<=Summary!$C$2,_xlfn.XLOOKUP(NG!$B66,BS_NG!$C:$C,BS_NG!Y:Y),0) -> 2.3889247e+09 | Y66: =IF(Y$3<=Summary!$C$2,_xlfn.XLOOKUP(NG!$B66,BS_NG!$C:$C,BS_NG!Z:Z),0) -> 2.5553856e+09 | Z66: =IF(Z$3<=Summary!$C$2,_xlfn.XLOOKUP(NG!$B66,BS_NG!$C:$C,BS_NG!AA:AA),0) -> 2.5553856e+09 | AA66: =IF(AA$3<=Summary!$C$2,_xlfn.XLOOKUP(NG!$B66,BS_NG!$C:$C,BS_NG!AB:AB),0) -> 2.6192379e+09 | AB66: =IF(AB$3<=Summary!$C$2,_xlfn.XLOOKUP(NG!$B66,BS_NG!$C:$C,BS_NG!AC:AC),0) -> 2.6192379e+09 | AC66: =IF(AC$3<=Summary!$C$2,_xlfn.XLOOKUP(NG!$B66,BS_NG!$C:$C,BS_NG!AD:AD),0) -> 2.6203493e+09 | AD66: =IF(AD$3<=Summary!$C$2,_xlfn.XLOOKUP(NG!$B66,BS_NG!$C:$C,BS_NG!AE:AE),0) -> 2.7389575e+09 | AE66: =IF(AE$3<=Summary!$C$2,_xlfn.XLOOKUP(NG!$B66,BS_NG!$C:$C,BS_NG!AF:AF),0) -> 0 | AF66: =IF(AF$3<=Summary!$C$2,_xlfn.XLOOKUP(NG!$B66,BS_NG!$C:$C,BS_NG!AG:AG),0) -> 0 | AG66: =IF(AG$3<=Summary!$C$2,_xlfn.XLOOKUP(NG!$B66,BS_NG!$C:$C,BS_NG!AH:AH),0) -> 0 | AH66: =IF(AH$3<=Summary!$C$2,_xlfn.XLOOKUP(NG!$B66,BS_NG!$C:$C,BS_NG!AI:AI),0) -> 0 | AI66: =IF(AI$3<=Summary!$C$2,_xlfn.XLOOKUP(NG!$B66,BS_NG!$C:$C,BS_NG!AJ:AJ),0) -> 0 | AJ66: =IF(AJ$3<=Summary!$C$2,_xlfn.XLOOKUP(NG!$B66,BS_NG!$C:$C,BS_NG!AK:AK),0) -> 0 | AK66: =IF(AK$3<=Summary!$C$2,_xlfn.XLOOKUP(NG!$B66,BS_NG!$C:$C,BS_NG!AL:AL),0) -> 0 | AL66: =IF(AL$3<=Summary!$C$2,_xlfn.XLOOKUP(NG!$B66,BS_NG!$C:$C,BS_NG!AM:AM),0) -> 0
B67: TOTAL NON CURRENT LIABILITIES | C67: =IF(C$3<=Summary!$C$2,_xlfn.XLOOKUP(NG!$B67,BS_NG!$C:$C,BS_NG!D:D),0) -> 42242924 | D67: =IF(D$3<=Summary!$C$2,_xlfn.XLOOKUP(NG!$B67,BS_NG!$C:$C,BS_NG!E:E),0) -> 42242924 | E67: =IF(E$3<=Summary!$C$2,_xlfn.XLOOKUP(NG!$B67,BS_NG!$C:$C,BS_NG!F:F),0) -> 42242924 | F67: =IF(F$3<=Summary!$C$2,_xlfn.XLOOKUP(NG!$B67,BS_NG!$C:$C,BS_NG!G:G),0) -> 42242924 | G67: =IF(G$3<=Summary!$C$2,_xlfn.XLOOKUP(NG!$B67,BS_NG!$C:$C,BS_NG!H:H),0) -> 42242924 | H67: =IF(H$3<=Summary!$C$2,_xlfn.XLOOKUP(NG!$B67,BS_NG!$C:$C,BS_NG!I:I),0) -> 42242924 | I67: =IF(I$3<=Summary!$C$2,_xlfn.XLOOKUP(NG!$B67,BS_NG!$C:$C,BS_NG!J:J),0) -> 42242924 | J67: =IF(J$3<=Summary!$C$2,_xlfn.XLOOKUP(NG!$B67,BS_NG!$C:$C,BS_NG!K:K),0) -> 42242924 | K67: =IF(K$3<=Summary!$C$2,_xlfn.XLOOKUP(NG!$B67,BS_NG!$C:$C,BS_NG!L:L),0) -> 42242924 | L67: =IF(L$3<=Summary!$C$2,_xlfn.XLOOKUP(NG!$B67,BS_NG!$C:$C,BS_NG!M:M),0) -> 42242924 | M67: =IF(M$3<=Summary!$C$2,_xlfn.XLOOKUP(NG!$B67,BS_NG!$C:$C,BS_NG!N:N),0) -> 42242924 | N67: =IF(N$3<=Summary!$C$2,_xlfn.XLOOKUP(NG!$B67,BS_NG!$C:$C,BS_NG!O:O),0) -> 32949171 | O67: =IF(O$3<=Summary!$C$2,_xlfn.XLOOKUP(NG!$B67,BS_NG!$C:$C,BS_NG!P:P),0) -> 32949171 | P67: =IF(P$3<=Summary!$C$2,_xlfn.XLOOKUP(NG!$B67,BS_NG!$C:$C,BS_NG!Q:Q),0) -> 32949171 | Q67: =IF(Q$3<=Summary!$C$2,_xlfn.XLOOKUP(NG!$B67,BS_NG!$C:$C,BS_NG!R:R),0) -> 32949171 | R67: =IF(R$3<=Summary!$C$2,_xlfn.XLOOKUP(NG!$B67,BS_NG!$C:$C,BS_NG!S:S),0) -> 32949171 | S67: =IF(S$3<=Summary!$C$2,_xlfn.XLOOKUP(NG!$B67,BS_NG!$C:$C,BS_NG!T:T),0) -> 32949171 | T67: =IF(T$3<=Summary!$C$2,_xlfn.XLOOKUP(NG!$B67,BS_NG!$C:$C,BS_NG!U:U),0) -> 32949171 | U67: =IF(U$3<=Summary!$C$2,_xlfn.XLOOKUP(NG!$B67,BS_NG!$C:$C,BS_NG!V:V),0) -> 32949171 | V67: =IF(V$3<=Summary!$C$2,_xlfn.XLOOKUP(NG!$B67,BS_NG!$C:$C,BS_NG!W:W),0) -> 32949171 | W67: =IF(W$3<=Summary!$C$2,_xlfn.XLOOKUP(NG!$B67,BS_NG!$C:$C,BS_NG!X:X),0) -> 32949171 | X67: =IF(X$3<=Summary!$C$2,_xlfn.XLOOKUP(NG!$B67,BS_NG!$C:$C,BS_NG!Y:Y),0) -> 32949171 | Y67: =IF(Y$3<=Summary!$C$2,_xlfn.XLOOKUP(NG!$B67,BS_NG!$C:$C,BS_NG!Z:Z),0) -> 32949171 | Z67: =IF(Z$3<=Summary!$C$2,_xlfn.XLOOKUP(NG!$B67,BS_NG!$C:$C,BS_NG!AA:AA),0) -> 32949171 | AA67: =IF(AA$3<=Summary!$C$2,_xlfn.XLOOKUP(NG!$B67,BS_NG!$C:$C,BS_NG!AB:AB),0) -> 21499461 | AB67: =IF(AB$3<=Summary!$C$2,_xlfn.XLOOKUP(NG!$B67,BS_NG!$C:$C,BS_NG!AC:AC),0) -> 21499461 | AC67: =IF(AC$3<=Summary!$C$2,_xlfn.XLOOKUP(NG!$B67,BS_NG!$C:$C,BS_NG!AD:AD),0) -> 21499461 | AD67: =IF(AD$3<=Summary!$C$2,_xlfn.XLOOKUP(NG!$B67,BS_NG!$C:$C,BS_NG!AE:AE),0) -> 21499461 | AE67: =IF(AE$3<=Summary!$C$2,_xlfn.XLOOKUP(NG!$B67,BS_NG!$C:$C,BS_NG!AF:AF),0) -> 0 | AF67: =IF(AF$3<=Summary!$C$2,_xlfn.XLOOKUP(NG!$B67,BS_NG!$C:$C,BS_NG!AG:AG),0) -> 0 | AG67: =IF(AG$3<=Summary!$C$2,_xlfn.XLOOKUP(NG!$B67,BS_NG!$C:$C,BS_NG!AH:AH),0) -> 0 | AH67: =IF(AH$3<=Summary!$C$2,_xlfn.XLOOKUP(NG!$B67,BS_NG!$C:$C,BS_NG!AI:AI),0) -> 0 | AI67: =IF(AI$3<=Summary!$C$2,_xlfn.XLOOKUP(NG!$B67,BS_NG!$C:$C,BS_NG!AJ:AJ),0) -> 0 | AJ67: =IF(AJ$3<=Summary!$C$2,_xlfn.XLOOKUP(NG!$B67,BS_NG!$C:$C,BS_NG!AK:AK),0) -> 0 | AK67: =IF(AK$3<=Summary!$C$2,_xlfn.XLOOKUP(NG!$B67,BS_NG!$C:$C,BS_NG!AL:AL),0) -> 0 | AL67: =IF(AL$3<=Summary!$C$2,_xlfn.XLOOKUP(NG!$B67,BS_NG!$C:$C,BS_NG!AM:AM),0) -> 0
B68: TOTAL ACCOUNTS PAYABLES | C68: =IF(C$3<=Summary!$C$2,_xlfn.XLOOKUP(NG!$B68,BS_NG!$C:$C,BS_NG!D:D),0) -> 3.1376537e+08 | D68: =IF(D$3<=Summary!$C$2,_xlfn.XLOOKUP(NG!$B68,BS_NG!$C:$C,BS_NG!E:E),0) -> 3.2634925e+08 | E68: =IF(E$3<=Summary!$C$2,_xlfn.XLOOKUP(NG!$B68,BS_NG!$C:$C,BS_NG!F:F),0) -> 3.3878724e+08 | F68: =IF(F$3<=Summary!$C$2,_xlfn.XLOOKUP(NG!$B68,BS_NG!$C:$C,BS_NG!G:G),0) -> 2.9782e+08 | G68: =IF(G$3<=Summary!$C$2,_xlfn.XLOOKUP(NG!$B68,BS_NG!$C:$C,BS_NG!H:H),0) -> 3.9739129e+08 | H68: =IF(H$3<=Summary!$C$2,_xlfn.XLOOKUP(NG!$B68,BS_NG!$C:$C,BS_NG!I:I),0) -> 4.374569e+08 | I68: =IF(I$3<=Summary!$C$2,_xlfn.XLOOKUP(NG!$B68,BS_NG!$C:$C,BS_NG!J:J),0) -> 5.1040657e+08 | J68: =IF(J$3<=Summary!$C$2,_xlfn.XLOOKUP(NG!$B68,BS_NG!$C:$C,BS_NG!K:K),0) -> 5.0605233e+08 | K68: =IF(K$3<=Summary!$C$2,_xlfn.XLOOKUP(NG!$B68,BS_NG!$C:$C,BS_NG!L:L),0) -> 3.3478353e+08 | L68: =IF(L$3<=Summary!$C$2,_xlfn.XLOOKUP(NG!$B68,BS_NG!$C:$C,BS_NG!M:M),0) -> 3.5766078e+08 | M68: =IF(M$3<=Summary!$C$2,_xlfn.XLOOKUP(NG!$B68,BS_NG!$C:$C,BS_NG!N:N),0) -> 4.5786379e+08 | N68: =IF(N$3<=Summary!$C$2,_xlfn.XLOOKUP(NG!$B68,BS_NG!$C:$C,BS_NG!O:O),0) -> 1.1460005e+09 | O68: =IF(O$3<=Summary!$C$2,_xlfn.XLOOKUP(NG!$B68,BS_NG!$C:$C,BS_NG!P:P),0) -> 1.152898e+09 | P68: =IF(P$3<=Summary!$C$2,_xlfn.XLOOKUP(NG!$B68,BS_NG!$C:$C,BS_NG!Q:Q),0) -> 1.176576e+09 | Q68: =IF(Q$3<=Summary!$C$2,_xlfn.XLOOKUP(NG!$B68,BS_NG!$C:$C,BS_NG!R:R),0) -> 1.1687159e+09 | R68: =IF(R$3<=Summary!$C$2,_xlfn.XLOOKUP(NG!$B68,BS_NG!$C:$C,BS_NG!S:S),0) -> 8.3833712e+08 | S68: =IF(S$3<=Summary!$C$2,_xlfn.XLOOKUP(NG!$B68,BS_NG!$C:$C,BS_NG!T:T),0) -> 6.0642809e+08 | T68: =IF(T$3<=Summary!$C$2,_xlfn.XLOOKUP(NG!$B68,BS_NG!$C:$C,BS_NG!U:U),0) -> 5.8356789e+08 | U68: =IF(U$3<=Summary!$C$2,_xlfn.XLOOKUP(NG!$B68,BS_NG!$C:$C,BS_NG!V:V),0) -> 3.95386e+08 | V68: =IF(V$3<=Summary!$C$2,_xlfn.XLOOKUP(NG!$B68,BS_NG!$C:$C,BS_NG!W:W),0) -> 3.9546068e+08 | W68: =IF(W$3<=Summary!$C$2,_xlfn.XLOOKUP(NG!$B68,BS_NG!$C:$C,BS_NG!X:X),0) -> 3.6503437e+08 | X68: =IF(X$3<=Summary!$C$2,_xlfn.XLOOKUP(NG!$B68,BS_NG!$C:$C,BS_NG!Y:Y),0) -> 3.8299783e+08 | Y68: =IF(Y$3<=Summary!$C$2,_xlfn.XLOOKUP(NG!$B68,BS_NG!$C:$C,BS_NG!Z:Z),0) -> 3.5139238e+08 | Z68: =IF(Z$3<=Summary!$C$2,_xlfn.XLOOKUP(NG!$B68,BS_NG!$C:$C,BS_NG!AA:AA),0) -> 3.2659823e+08 | AA68: =IF(AA$3<=Summary!$C$2,_xlfn.XLOOKUP(NG!$B68,BS_NG!$C:$C,BS_NG!AB:AB),0) -> 4.1010268e+08 | AB68: =IF(AB$3<=Summary!$C$2,_xlfn.XLOOKUP(NG!$B68,BS_NG!$C:$C,BS_NG!AC:AC),0) -> 4.0792245e+08 | AC68: =IF(AC$3<=Summary!$C$2,_xlfn.XLOOKUP(NG!$B68,BS_NG!$C:$C,BS_NG!AD:AD),0) -> 4.8567273e+08 | AD68: =IF(AD$3<=Summary!$C$2,_xlfn.XLOOKUP(NG!$B68,BS_NG!$C:$C,BS_NG!AE:AE),0) -> 3.4872957e+08 | AE68: =IF(AE$3<=Summary!$C$2,_xlfn.XLOOKUP(NG!$B68,BS_NG!$C:$C,BS_NG!AF:AF),0) -> 0 | AF68: =IF(AF$3<=Summary!$C$2,_xlfn.XLOOKUP(NG!$B68,BS_NG!$C:$C,BS_NG!AG:AG),0) -> 0 | AG68: =IF(AG$3<=Summary!$C$2,_xlfn.XLOOKUP(NG!$B68,BS_NG!$C:$C,BS_NG!AH:AH),0) -> 0 | AH68: =IF(AH$3<=Summary!$C$2,_xlfn.XLOOKUP(NG!$B68,BS_NG!$C:$C,BS_NG!AI:AI),0) -> 0 | AI68: =IF(AI$3<=Summary!$C$2,_xlfn.XLOOKUP(NG!$B68,BS_NG!$C:$C,BS_NG!AJ:AJ),0) -> 0 | AJ68: =IF(AJ$3<=Summary!$C$2,_xlfn.XLOOKUP(NG!$B68,BS_NG!$C:$C,BS_NG!AK:AK),0) -> 0 | AK68: =IF(AK$3<=Summary!$C$2,_xlfn.XLOOKUP(NG!$B68,BS_NG!$C:$C,BS_NG!AL:AL),0) -> 0 | AL68: =IF(AL$3<=Summary!$C$2,_xlfn.XLOOKUP(NG!$B68,BS_NG!$C:$C,BS_NG!AM:AM),0) -> 0
... B73: TOTAL RETAINED EARNINGS | C73: =IF(C$3<=Summary!$C$2,_xlfn.XLOOKUP(NG!$B73,BS_NG!$C:$C,BS_NG!D:D),0) -> 9.9084064e+08 | D73: =IF(D$3<=Summary!$C$2,_xlfn.XLOOKUP(NG!$B73,BS_NG!$C:$C,BS_NG!E:E),0) -> 1.305683e+09 | E73: =IF(E$3<=Summary!$C$2,_xlfn.XLOOKUP(NG!$B73,BS_NG!$C:$C,BS_NG!F:F),0) -> 1.5679315e+09 | F73: =IF(F$3<=Summary!$C$2,_xlfn.XLOOKUP(NG!$B73,BS_NG!$C:$C,BS_NG!G:G),0) -> 1.8120317e+09 | G73: =IF(G$3<=Summary!$C$2,_xlfn.XLOOKUP(NG!$B73,BS_NG!$C:$C,BS_NG!H:H),0) -> 1.6050228e+09 | H73: =IF(H$3<=Summary!$C$2,_xlfn.XLOOKUP(NG!$B73,BS_NG!$C:$C,BS_NG!I:I),0) -> 1.5159372e+09 | I73: =IF(I$3<=Summary!$C$2,_xlfn.XLOOKUP(NG!$B73,BS_NG!$C:$C,BS_NG!J:J),0) -> 1.4765179e+09 | J73: =IF(J$3<=Summary!$C$2,_xlfn.XLOOKUP(NG!$B73,BS_NG!$C:$C,BS_NG!K:K),0) -> 1.5533423e+09 | K73: =IF(K$3<=Summary!$C$2,_xlfn.XLOOKUP(NG!$B73,BS_NG!$C:$C,BS_NG!L:L),0) -> 1.5319287e+09 | L73: =IF(L$3<=Summary!$C$2,_xlfn.XLOOKUP(NG!$B73,BS_NG!$C:$C,BS_NG!M:M),0) -> 1.2645004e+09 | M73: =IF(M$3<=Summary!$C$2,_xlfn.XLOOKUP(NG!$B73,BS_NG!$C:$C,BS_NG!N:N),0) -> 1.0300099e+09 | N73: =IF(N$3<=Summary!$C$2,_xlfn.XLOOKUP(NG!$B73,BS_NG!$C:$C,BS_NG!O:O),0) -> 1.0169074e+09 | O73: =IF(O$3<=Summary!$C$2,_xlfn.XLOOKUP(NG!$B73,BS_NG!$C:$C,BS_NG!P:P),0) -> 9.9963234e+08 | P73: =IF(P$3<=Summary!$C$2,_xlfn.XLOOKUP(NG!$B73,BS_NG!$C:$C,BS_NG!Q:Q),0) -> 9.5140377e+08 | Q73: =IF(Q$3<=Summary!$C$2,_xlfn.XLOOKUP(NG!$B73,BS_NG!$C:$C,BS_NG!R:R),0) -> 9.5010199e+08 | R73: =IF(R$3<=Summary!$C$2,_xlfn.XLOOKUP(NG!$B73,BS_NG!$C:$C,BS_NG!S:S),0) -> 1.0632376e+09 | S73: =IF(S$3<=Summary!$C$2,_xlfn.XLOOKUP(NG!$B73,BS_NG!$C:$C,BS_NG!T:T),0) -> 6.525973e+08 | T73: =IF(T$3<=Summary!$C$2,_xlfn.XLOOKUP(NG!$B73,BS_NG!$C:$C,BS_NG!U:U),0) -> 4.0404229e+08 | U73: =IF(U$3<=Summary!$C$2,_xlfn.XLOOKUP(NG!$B73,BS_NG!$C:$C,BS_NG!V:V),0) -> 2.3984605e+08 | V73: =IF(V$3<=Summary!$C$2,_xlfn.XLOOKUP(NG!$B73,BS_NG!$C:$C,BS_NG!W:W),0) -> 2.0493147e+08 | W73: =IF(W$3<=Summary!$C$2,_xlfn.XLOOKUP(NG!$B73,BS_NG!$C:$C,BS_NG!X:X),0) -> 69584163 | X73: =IF(X$3<=Summary!$C$2,_xlfn.XLOOKUP(NG!$B73,BS_NG!$C:$C,BS_NG!Y:Y),0) -> 2.9891651e+08 | Y73: =IF(Y$3<=Summary!$C$2,_xlfn.XLOOKUP(NG!$B73,BS_NG!$C:$C,BS_NG!Z:Z),0) -> 2.6256448e+08 | Z73: =IF(Z$3<=Summary!$C$2,_xlfn.XLOOKUP(NG!$B73,BS_NG!$C:$C,BS_NG!AA:AA),0) -> -6.9199354e+08 | AA73: =IF(AA$3<=Summary!$C$2,_xlfn.XLOOKUP(NG!$B73,BS_NG!$C:$C,BS_NG!AB:AB),0) -> -4.7003891e+08 | AB73: =IF(AB$3<=Summary!$C$2,_xlfn.XLOOKUP(NG!$B73,BS_NG!$C:$C,BS_NG!AC:AC),0) -> -1.1884839e+08 | AC73: =IF(AC$3<=Summary!$C$2,_xlfn.XLOOKUP(NG!$B73,BS_NG!$C:$C,BS_NG!AD:AD),0) -> 16035617 | AD73: =IF(AD$3<=Summary!$C$2,_xlfn.XLOOKUP(NG!$B73,BS_NG!$C:$C,BS_NG!AE:AE),0) -> 1.0113339e+08 | AE73: =IF(AE$3<=Summary!$C$2,_xlfn.XLOOKUP(NG!$B73,BS_NG!$C:$C,BS_NG!AF:AF),0) -> 0 | AF73: =IF(AF$3<=Summary!$C$2,_xlfn.XLOOKUP(NG!$B73,BS_NG!$C:$C,BS_NG!AG:AG),0) -> 0 | AG73: =IF(AG$3<=Summary!$C$2,_xlfn.XLOOKUP(NG!$B73,BS_NG!$C:$C,BS_NG!AH:AH),0) -> 0 | AH73: =IF(AH$3<=Summary!$C$2,_xlfn.XLOOKUP(NG!$B73,BS_NG!$C:$C,BS_NG!AI:AI),0) -> 0 | AI73: =IF(AI$3<=Summary!$C$2,_xlfn.XLOOKUP(NG!$B73,BS_NG!$C:$C,BS_NG!AJ:AJ),0) -> 0 | AJ73: =IF(AJ$3<=Summary!$C$2,_xlfn.XLOOKUP(NG!$B73,BS_NG!$C:$C,BS_NG!AK:AK),0) -> 0 | AK73: =IF(AK$3<=Summary!$C$2,_xlfn.XLOOKUP(NG!$B73,BS_NG!$C:$C,BS_NG!AL:AL),0) -> 0 | AL73: =IF(AL$3<=Summary!$C$2,_xlfn.XLOOKUP(NG!$B73,BS_NG!$C:$C,BS_NG!AM:AM),0) -> 0
B84: Total Payroll Cost | C84: =PL_NG!D38+PL_NG!D77 -> -89465978 | D84: =PL_NG!E38+PL_NG!E77 -> -95077068 | E84: =PL_NG!F38+PL_NG!F77 -> -1.0495428e+08 | F84: =PL_NG!G38+PL_NG!G77 -> -1.3532969e+08 | G84: =PL_NG!H38+PL_NG!H77 -> -1.6245268e+08 | H84: =PL_NG!I38+PL_NG!I77 -> -1.4255883e+08 | I84: =PL_NG!J38+PL_NG!J77 -> -1.4066824e+08 | J84: =PL_NG!K38+PL_NG!K77 -> -1.4777352e+08 | ... AL84: =PL_NG!AM38+PL_NG!AM77 -> 0
B85: Total Commercial Cost | C85: =PL_NG!D99-PL_NG!D97-PL_NG!D98 -> -118290.11 | D85: =PL_NG!E99-PL_NG!E97-PL_NG!E98 -> -4284812.5 | E85: =PL_NG!F99-PL_NG!F97-PL_NG!F98 -> -7492140 | F85: =PL_NG!G99-PL_NG!G97-PL_NG!G98 -> -37831870 | G85: =PL_NG!H99-PL_NG!H97-PL_NG!H98 -> -19475706 | H85: =PL_NG!I99-PL_NG!I97-PL_NG!I98 -> -40166988 | I85: =PL_NG!J99-PL_NG!J97-PL_NG!J98 -> -21977313 | J85: =PL_NG!K99-PL_NG!K97-PL_NG!K98 -> -36197740 | ... AL85: =PL_NG!AM99-PL_NG!AM97-PL_NG!AM98 -> 0
B87: NFIs
B89: Human Resources
B90: Total Staff count | O90: 175 | P90: 177 | Q90: 177 | R90: 174 | S90: 164 | T90: 164 | U90: 158 | V90: 163 | W90: 158 | X90: 160
B91: Total Male staff count | O91: 119 | P91: 121 | Q91: 120 | R91: 120 | S91: 121 | T91: 124 | U91: 120 | V91: 123 | W91: 119 | X91: 121
B92: Total Female Staff count | O92: 45 | P92: 47 | Q92: 46 | R92: 45 | S92: 42 | T92: 40 | U92: 38 | V92: 40 | W92: 39 | X92: 39
B93: -% of current female to male ratio at SEAMFIX | O93: =IFERROR(O92/O90,"") -> 0.25714286 | P93: =IFERROR(P92/P90,"") -> 0.26553672 | Q93: =IFERROR(Q92/Q90,"") -> 0.25988701 | R93: =IFERROR(R92/R90,"") -> 0.25862069 | S93: =IFERROR(S92/S90,"") -> 0.25609756 | T93: =IFERROR(T92/T90,"") -> 0.24390244 | U93: =IFERROR(U92/U90,"") -> 0.24050633 | V93: 0.2454 | W93: 0.2468 | X93: 0.2468
B94: Count of new Joiners | O94: 8 | P94: 7 | Q94: 3 | R94: 3 | S94: 3 | T94: 4 | U94: 6 | V94: 5 | W94: 2 | X94: 2
B95: Count of exit | O95: 13 | P95: 4 | Q95: 7 | R95: 9 | S95: 4 | T95: 4 | U95: 8 | V95: 6 | W95: 7 | X95: 0
B96: Attrition rate (Count of exit/total staff)% | O96: =IFERROR(O95/AVERAGE($O$90:O90),"") -> 0.074285714 | P96: =IFERROR(P95/AVERAGE($O$90:P90),"") -> 0.022727273 | Q96: =IFERROR(Q95/AVERAGE($O$90:Q90),"") -> 0.039697543 | R96: =IFERROR(R95/AVERAGE($O$90:R90),"") -> 0.051209104 | S96: =IFERROR(S95/AVERAGE($O$90:S90),"") -> 0.023068051 | T96: =IFERROR(T95/AVERAGE($O$90:T90),"") -> 0.023278371 | U96: =IFERROR(U95/AVERAGE($O$90:U90),"") -> 0.047098402 | V96: 0.0368 | W96: 0.0443 | X96: 0.0443
B102: Marketing
B107: Sales
B112: Partnership
B117: Products
B123: Projects

Sheet Group
U2: =BS_NG!V161+BS_UK!V72+BS_UAE!V78 -> 9.1731373e+09 | V2: =IF(V$3<=Summary!$C$2,_xlfn.XLOOKUP(Group!$B4,PL_NG!$C:$C,PL_NG!W:W),0) -> 1.8398851e+08 | W2: =IF(W$3<=Summary!$C$2,_xlfn.XLOOKUP(Group!$B4,PL_NG!$C:$C,PL_NG!X:X),0) -> 4.0119621e+08
C3: 45322 | D3: =EOMONTH(C3,1) -> 45351 | E3: =EOMONTH(D3,1) -> 45382 | F3: =EOMONTH(E3,1) -> 45412 | G3: =EOMONTH(F3,1) -> 45443 | H3: =EOMONTH(G3,1) -> 45473 | I3: =EOMONTH(H3,1) -> 45504 | J3: =EOMONTH(I3,1) -> 45535 | K3: =EOMONTH(J3,1) -> 45565 | ... AL3: =EOMONTH(AK3,1) -> 46387
B4: TOTAL REVENUE | C4: =IF(C$3<=Summary!$C$2,(_xlfn.XLOOKUP(Group!$B4,PL_NG!$C:$C,PL_NG!D:D)+_xlfn.XLOOKUP(Group!$B4,PL_UK!$C:$C,PL_UK!D:D)+_xlfn.XLOOKUP(Group!$B4,PL_UAE!$C:$C,PL_UAE!D:D)),0) -> 1.9845885e+08 | D4: =IF(D$3<=Summary!$C$2,(_xlfn.XLOOKUP(Group!$B4,PL_NG!$C:$C,PL_NG!E:E)+_xlfn.XLOOKUP(Group!$B4,PL_UK!$C:$C,PL_UK!E:E)+_xlfn.XLOOKUP(Group!$B4,PL_UAE!$C:$C,PL_UAE!E:E)),0) -> 5.5774756e+08 | E4: =IF(E$3<=Summary!$C$2,(_xlfn.XLOOKUP(Group!$B4,PL_NG!$C:$C,PL_NG!F:F)+_xlfn.XLOOKUP(Group!$B4,PL_UK!$C:$C,PL_UK!F:F)+_xlfn.XLOOKUP(Group!$B4,PL_UAE!$C:$C,PL_UAE!F:F)),0) -> 5.635586e+08 | F4: =IF(F$3<=Summary!$C$2,(_xlfn.XLOOKUP(Group!$B4,PL_NG!$C:$C,PL_NG!G:G)+_xlfn.XLOOKUP(Group!$B4,PL_UK!$C:$C,PL_UK!G:G)+_xlfn.XLOOKUP(Group!$B4,PL_UAE!$C:$C,PL_UAE!G:G)),0) -> 5.6782128e+08 | G4: =IF(G$3<=Summary!$C$2,(_xlfn.XLOOKUP(Group!$B4,PL_NG!$C:$C,PL_NG!H:H)+_xlfn.XLOOKUP(Group!$B4,PL_UK!$C:$C,PL_UK!H:H)+_xlfn.XLOOKUP(Group!$B4,PL_UAE!$C:$C,PL_UAE!H:H)),0) -> 2.3235519e+08 | H4: =IF(H$3<=Summary!$C$2,(_xlfn.XLOOKUP(Group!$B4,PL_NG!$C:$C,PL_NG!I:I)+_xlfn.XLOOKUP(Group!$B4,PL_UK!$C:$C,PL_UK!I:I)+_xlfn.XLOOKUP(Group!$B4,PL_UAE!$C:$C,PL_UAE!I:I)),0) -> 2.4381262e+08 | I4: =IF(I$3<=Summary!$C$2,(_xlfn.XLOOKUP(Group!$B4,PL_NG!$C:$C,PL_NG!J:J)+_xlfn.XLOOKUP(Group!$B4,PL_UK!$C:$C,PL_UK!J:J)+_xlfn.XLOOKUP(Group!$B4,PL_UAE!$C:$C,PL_UAE!J:J)),0) -> 2.2093482e+08 | J4: =IF(J$3<=Summary!$C$2,(_xlfn.XLOOKUP(Group!$B4,PL_NG!$C:$C,PL_NG!K:K)+_xlfn.XLOOKUP(Group!$B4,PL_UK!$C:$C,PL_UK!K:K)+_xlfn.XLOOKUP(Group!$B4,PL_UAE!$C:$C,PL_UAE!K:K)),0) -> 3.6012899e+08 | K4: =IF(K$3<=Summary!$C$2,(_xlfn.XLOOKUP(Group!$B4,PL_NG!$C:$C,PL_NG!L:L)+_xlfn.XLOOKUP(Group!$B4,PL_UK!$C:$C,PL_UK!L:L)+_xlfn.XLOOKUP(Group!$B4,PL_UAE!$C:$C,PL_UAE!L:L)),0) -> 1.5127642e+08 | L4: =IF(L$3<=Summary!$C$2,(_xlfn.XLOOKUP(Group!$B4,PL_NG!$C:$C,PL_NG!M:M)+_xlfn.XLOOKUP(Group!$B4,PL_UK!$C:$C,PL_UK!M:M)+_xlfn.XLOOKUP(Group!$B4,PL_UAE!$C:$C,PL_UAE!M:M)),0) -> 1.9536778e+08 | M4: =IF(M$3<=Summary!$C$2,(_xlfn.XLOOKUP(Group!$B4,PL_NG!$C:$C,PL_NG!N:N)+_xlfn.XLOOKUP(Group!$B4,PL_UK!$C:$C,PL_UK!N:N)+_xlfn.XLOOKUP(Group!$B4,PL_UAE!$C:$C,PL_UAE!N:N)),0) -> 2.4651485e+08 | N4: =IF(N$3<=Summary!$C$2,(_xlfn.XLOOKUP(Group!$B4,PL_NG!$C:$C,PL_NG!O:O)+_xlfn.XLOOKUP(Group!$B4,PL_UK!$C:$C,PL_UK!O:O)+_xlfn.XLOOKUP(Group!$B4,PL_UAE!$C:$C,PL_UAE!O:O)),0) -> 6.0277632e+08 | O4: =IF(O$3<=Summary!$C$2,(_xlfn.XLOOKUP(Group!$B4,PL_NG!$C:$C,PL_NG!P:P)+_xlfn.XLOOKUP(Group!$B4,PL_UK!$C:$C,PL_UK!P:P)+_xlfn.XLOOKUP(Group!$B4,PL_UAE!$C:$C,PL_UAE!P:P)),0) -> 2.3652683e+08 | P4: =IF(P$3<=Summary!$C$2,(_xlfn.XLOOKUP(Group!$B4,PL_NG!$C:$C,PL_NG!Q:Q)+_xlfn.XLOOKUP(Group!$B4,PL_UK!$C:$C,PL_UK!Q:Q)+_xlfn.XLOOKUP(Group!$B4,PL_UAE!$C:$C,PL_UAE!Q:Q)),0) -> 2.1640024e+08 | Q4: =IF(Q$3<=Summary!$C$2,(_xlfn.XLOOKUP(Group!$B4,PL_NG!$C:$C,PL_NG!R:R)+_xlfn.XLOOKUP(Group!$B4,PL_UK!$C:$C,PL_UK!R:R)+_xlfn.XLOOKUP(Group!$B4,PL_UAE!$C:$C,PL_UAE!R:R)),0) -> 2.3413942e+08 | R4: =IF(R$3<=Summary!$C$2,(_xlfn.XLOOKUP(Group!$B4,PL_NG!$C:$C,PL_NG!S:S)+_xlfn.XLOOKUP(Group!$B4,PL_UK!$C:$C,PL_UK!S:S)+_xlfn.XLOOKUP(Group!$B4,PL_UAE!$C:$C,PL_UAE!S:S)),0) -> 2.4454141e+08 | S4: =IF(S$3<=Summary!$C$2,(_xlfn.XLOOKUP(Group!$B4,PL_NG!$C:$C,PL_NG!T:T)+_xlfn.XLOOKUP(Group!$B4,PL_UK!$C:$C,PL_UK!T:T)+_xlfn.XLOOKUP(Group!$B4,PL_UAE!$C:$C,PL_UAE!T:T)),0) -> 1.7682674e+08 | T4: =IF(T$3<=Summary!$C$2,(_xlfn.XLOOKUP(Group!$B4,PL_NG!$C:$C,PL_NG!U:U)+_xlfn.XLOOKUP(Group!$B4,PL_UK!$C:$C,PL_UK!U:U)+_xlfn.XLOOKUP(Group!$B4,PL_UAE!$C:$C,PL_UAE!U:U)),0) -> 1.2019372e+08 | U4: =IF(U$3<=Summary!$C$2,(_xlfn.XLOOKUP(Group!$B4,PL_NG!$C:$C,PL_NG!V:V)+_xlfn.XLOOKUP(Group!$B4,PL_UK!$C:$C,PL_UK!V:V)+_xlfn.XLOOKUP(Group!$B4,PL_UAE!$C:$C,PL_UAE!V:V)),0) -> 2.1214077e+08 | V4: =IF(V$3<=Summary!$C$2,(_xlfn.XLOOKUP(Group!$B4,PL_NG!$C:$C,PL_NG!W:W)+_xlfn.XLOOKUP(Group!$B4,PL_UK!$C:$C,PL_UK!W:W)+_xlfn.XLOOKUP(Group!$B4,PL_UAE!$C:$C,PL_UAE!W:W)),0) -> 1.945011e+08 | W4: =IF(W$3<=Summary!$C$2,(_xlfn.XLOOKUP(Group!$B4,PL_NG!$C:$C,PL_NG!X:X)+_xlfn.XLOOKUP(Group!$B4,PL_UK!$C:$C,PL_UK!X:X)+_xlfn.XLOOKUP(Group!$B4,PL_UAE!$C:$C,PL_UAE!X:X)),0) -> 4.072536e+08 | X4: =IF(X$3<=Summary!$C$2,(_xlfn.XLOOKUP(Group!$B4,PL_NG!$C:$C,PL_NG!Y:Y)+_xlfn.XLOOKUP(Group!$B4,PL_UK!$C:$C,PL_UK!Y:Y)+_xlfn.XLOOKUP(Group!$B4,PL_UAE!$C:$C,PL_UAE!Y:Y)),0) -> 7.443618e+08 | Y4: =IF(Y$3<=Summary!$C$2,(_xlfn.XLOOKUP(Group!$B4,PL_NG!$C:$C,PL_NG!Z:Z)+_xlfn.XLOOKUP(Group!$B4,PL_UK!$C:$C,PL_UK!Z:Z)+_xlfn.XLOOKUP(Group!$B4,PL_UAE!$C:$C,PL_UAE!Z:Z)),0) -> 3.247382e+08 | Z4: =IF(Z$3<=Summary!$C$2,(_xlfn.XLOOKUP(Group!$B4,PL_NG!$C:$C,PL_NG!AA:AA)+_xlfn.XLOOKUP(Group!$B4,PL_UK!$C:$C,PL_UK!AA:AA)+_xlfn.XLOOKUP(Group!$B4,PL_UAE!$C:$C,PL_UAE!AA:AA)),0) -> 3.1322847e+08 | AA4: =IF(AA$3<=Summary!$C$2,(_xlfn.XLOOKUP(Group!$B4,PL_NG!$C:$C,PL_NG!AB:AB)+_xlfn.XLOOKUP(Group!$B4,PL_UK!$C:$C,PL_UK!AB:AB)+_xlfn.XLOOKUP(Group!$B4,PL_UAE!$C:$C,PL_UAE!AB:AB)),0) -> 7.1398264e+08 | AB4: =IF(AB$3<=Summary!$C$2,(_xlfn.XLOOKUP(Group!$B4,PL_NG!$C:$C,PL_NG!AC:AC)+_xlfn.XLOOKUP(Group!$B4,PL_UK!$C:$C,PL_UK!AC:AC)+_xlfn.XLOOKUP(Group!$B4,PL_UAE!$C:$C,PL_UAE!AC:AC)),0) -> 7.5942982e+08 | AC4: =IF(AC$3<=Summary!$C$2,(_xlfn.XLOOKUP(Group!$B4,PL_NG!$C:$C,PL_NG!AD:AD)+_xlfn.XLOOKUP(Group!$B4,PL_UK!$C:$C,PL_UK!AD:AD)+_xlfn.XLOOKUP(Group!$B4,PL_UAE!$C:$C,PL_UAE!AD:AD)),0) -> 5.5103186e+08 | AD4: =IF(AD$3<=Summary!$C$2,(_xlfn.XLOOKUP(Group!$B4,PL_NG!$C:$C,PL_NG!AE:AE)+_xlfn.XLOOKUP(Group!$B4,PL_UK!$C:$C,PL_UK!AE:AE)+_xlfn.XLOOKUP(Group!$B4,PL_UAE!$C:$C,PL_UAE!AE:AE)),0) -> 3.460454e+08 | AE4: =IF(AE$3<=Summary!$C$2,(_xlfn.XLOOKUP(Group!$B4,PL_NG!$C:$C,PL_NG!AF:AF)+_xlfn.XLOOKUP(Group!$B4,PL_UK!$C:$C,PL_UK!AF:AF)+_xlfn.XLOOKUP(Group!$B4,PL_UAE!$C:$C,PL_UAE!AF:AF)),0) -> 0 | AF4: =IF(AF$3<=Summary!$C$2,(_xlfn.XLOOKUP(Group!$B4,PL_NG!$C:$C,PL_NG!AG:AG)+_xlfn.XLOOKUP(Group!$B4,PL_UK!$C:$C,PL_UK!AG:AG)+_xlfn.XLOOKUP(Group!$B4,PL_UAE!$C:$C,PL_UAE!AG:AG)),0) -> 0 | AG4: =IF(AG$3<=Summary!$C$2,(_xlfn.XLOOKUP(Group!$B4,PL_NG!$C:$C,PL_NG!AH:AH)+_xlfn.XLOOKUP(Group!$B4,PL_UK!$C:$C,PL_UK!AH:AH)+_xlfn.XLOOKUP(Group!$B4,PL_UAE!$C:$C,PL_UAE!AH:AH)),0) -> 0 | AH4: =IF(AH$3<=Summary!$C$2,(_xlfn.XLOOKUP(Group!$B4,PL_NG!$C:$C,PL_NG!AI:AI)+_xlfn.XLOOKUP(Group!$B4,PL_UK!$C:$C,PL_UK!AI:AI)+_xlfn.XLOOKUP(Group!$B4,PL_UAE!$C:$C,PL_UAE!AI:AI)),0) -> 0 | AI4: =IF(AI$3<=Summary!$C$2,(_xlfn.XLOOKUP(Group!$B4,PL_NG!$C:$C,PL_NG!AJ:AJ)+_xlfn.XLOOKUP(Group!$B4,PL_UK!$C:$C,PL_UK!AJ:AJ)+_xlfn.XLOOKUP(Group!$B4,PL_UAE!$C:$C,PL_UAE!AJ:AJ)),0) -> 0 | AJ4: =IF(AJ$3<=Summary!$C$2,(_xlfn.XLOOKUP(Group!$B4,PL_NG!$C:$C,PL_NG!AK:AK)+_xlfn.XLOOKUP(Group!$B4,PL_UK!$C:$C,PL_UK!AK:AK)+_xlfn.XLOOKUP(Group!$B4,PL_UAE!$C:$C,PL_UAE!AK:AK)),0) -> 0 | AK4: =IF(AK$3<=Summary!$C$2,(_xlfn.XLOOKUP(Group!$B4,PL_NG!$C:$C,PL_NG!AL:AL)+_xlfn.XLOOKUP(Group!$B4,PL_UK!$C:$C,PL_UK!AL:AL)+_xlfn.XLOOKUP(Group!$B4,PL_UAE!$C:$C,PL_UAE!AL:AL)),0) -> 0 | AL4: =IF(AL$3<=Summary!$C$2,(_xlfn.XLOOKUP(Group!$B4,PL_NG!$C:$C,PL_NG!AM:AM)+_xlfn.XLOOKUP(Group!$B4,PL_UK!$C:$C,PL_UK!AM:AM)+_xlfn.XLOOKUP(Group!$B4,PL_UAE!$C:$C,PL_UAE!AM:AM)),0) -> 0
B5: TOTAL COST OF SALES | C5: =IF(C$3<=Summary!$C$2,(_xlfn.XLOOKUP(Group!$B5,PL_NG!$C:$C,PL_NG!D:D)+_xlfn.XLOOKUP(Group!$B5,PL_UK!$C:$C,PL_UK!D:D)+_xlfn.XLOOKUP(Group!$B5,PL_UAE!$C:$C,PL_UAE!D:D)),0) -> -87464215 | D5: =IF(D$3<=Summary!$C$2,(_xlfn.XLOOKUP(Group!$B5,PL_NG!$C:$C,PL_NG!E:E)+_xlfn.XLOOKUP(Group!$B5,PL_UK!$C:$C,PL_UK!E:E)+_xlfn.XLOOKUP(Group!$B5,PL_UAE!$C:$C,PL_UAE!E:E)),0) -> -1.1008525e+08 | E5: =IF(E$3<=Summary!$C$2,(_xlfn.XLOOKUP(Group!$B5,PL_NG!$C:$C,PL_NG!F:F)+_xlfn.XLOOKUP(Group!$B5,PL_UK!$C:$C,PL_UK!F:F)+_xlfn.XLOOKUP(Group!$B5,PL_UAE!$C:$C,PL_UAE!F:F)),0) -> -1.3858746e+08 | F5: =IF(F$3<=Summary!$C$2,(_xlfn.XLOOKUP(Group!$B5,PL_NG!$C:$C,PL_NG!G:G)+_xlfn.XLOOKUP(Group!$B5,PL_UK!$C:$C,PL_UK!G:G)+_xlfn.XLOOKUP(Group!$B5,PL_UAE!$C:$C,PL_UAE!G:G)),0) -> -1.6223054e+08 | G5: =IF(G$3<=Summary!$C$2,(_xlfn.XLOOKUP(Group!$B5,PL_NG!$C:$C,PL_NG!H:H)+_xlfn.XLOOKUP(Group!$B5,PL_UK!$C:$C,PL_UK!H:H)+_xlfn.XLOOKUP(Group!$B5,PL_UAE!$C:$C,PL_UAE!H:H)),0) -> -1.6474228e+08 | H5: =IF(H$3<=Summary!$C$2,(_xlfn.XLOOKUP(Group!$B5,PL_NG!$C:$C,PL_NG!I:I)+_xlfn.XLOOKUP(Group!$B5,PL_UK!$C:$C,PL_UK!I:I)+_xlfn.XLOOKUP(Group!$B5,PL_UAE!$C:$C,PL_UAE!I:I)),0) -> -78094783 | I5: =IF(I$3<=Summary!$C$2,(_xlfn.XLOOKUP(Group!$B5,PL_NG!$C:$C,PL_NG!J:J)+_xlfn.XLOOKUP(Group!$B5,PL_UK!$C:$C,PL_UK!J:J)+_xlfn.XLOOKUP(Group!$B5,PL_UAE!$C:$C,PL_UAE!J:J)),0) -> -68806938 | J5: =IF(J$3<=Summary!$C$2,(_xlfn.XLOOKUP(Group!$B5,PL_NG!$C:$C,PL_NG!K:K)+_xlfn.XLOOKUP(Group!$B5,PL_UK!$C:$C,PL_UK!K:K)+_xlfn.XLOOKUP(Group!$B5,PL_UAE!$C:$C,PL_UAE!K:K)),0) -> -1.6114817e+08 | K5: =IF(K$3<=Summary!$C$2,(_xlfn.XLOOKUP(Group!$B5,PL_NG!$C:$C,PL_NG!L:L)+_xlfn.XLOOKUP(Group!$B5,PL_UK!$C:$C,PL_UK!L:L)+_xlfn.XLOOKUP(Group!$B5,PL_UAE!$C:$C,PL_UAE!L:L)),0) -> -83003086 | L5: =IF(L$3<=Summary!$C$2,(_xlfn.XLOOKUP(Group!$B5,PL_NG!$C:$C,PL_NG!M:M)+_xlfn.XLOOKUP(Group!$B5,PL_UK!$C:$C,PL_UK!M:M)+_xlfn.XLOOKUP(Group!$B5,PL_UAE!$C:$C,PL_UAE!M:M)),0) -> -82725526 | M5: =IF(M$3<=Summary!$C$2,(_xlfn.XLOOKUP(Group!$B5,PL_NG!$C:$C,PL_NG!N:N)+_xlfn.XLOOKUP(Group!$B5,PL_UK!$C:$C,PL_UK!N:N)+_xlfn.XLOOKUP(Group!$B5,PL_UAE!$C:$C,PL_UAE!N:N)),0) -> -91989297 | N5: =IF(N$3<=Summary!$C$2,(_xlfn.XLOOKUP(Group!$B5,PL_NG!$C:$C,PL_NG!O:O)+_xlfn.XLOOKUP(Group!$B5,PL_UK!$C:$C,PL_UK!O:O)+_xlfn.XLOOKUP(Group!$B5,PL_UAE!$C:$C,PL_UAE!O:O)),0) -> -1.075832e+08 | O5: =IF(O$3<=Summary!$C$2,(_xlfn.XLOOKUP(Group!$B5,PL_NG!$C:$C,PL_NG!P:P)+_xlfn.XLOOKUP(Group!$B5,PL_UK!$C:$C,PL_UK!P:P)+_xlfn.XLOOKUP(Group!$B5,PL_UAE!$C:$C,PL_UAE!P:P)),0) -> -78920967 | P5: =IF(P$3<=Summary!$C$2,(_xlfn.XLOOKUP(Group!$B5,PL_NG!$C:$C,PL_NG!Q:Q)+_xlfn.XLOOKUP(Group!$B5,PL_UK!$C:$C,PL_UK!Q:Q)+_xlfn.XLOOKUP(Group!$B5,PL_UAE!$C:$C,PL_UAE!Q:Q)),0) -> -59583746 | Q5: =IF(Q$3<=Summary!$C$2,(_xlfn.XLOOKUP(Group!$B5,PL_NG!$C:$C,PL_NG!R:R)+_xlfn.XLOOKUP(Group!$B5,PL_UK!$C:$C,PL_UK!R:R)+_xlfn.XLOOKUP(Group!$B5,PL_UAE!$C:$C,PL_UAE!R:R)),0) -> -60763027 | R5: =IF(R$3<=Summary!$C$2,(_xlfn.XLOOKUP(Group!$B5,PL_NG!$C:$C,PL_NG!S:S)+_xlfn.XLOOKUP(Group!$B5,PL_UK!$C:$C,PL_UK!S:S)+_xlfn.XLOOKUP(Group!$B5,PL_UAE!$C:$C,PL_UAE!S:S)),0) -> -59132875 | S5: =IF(S$3<=Summary!$C$2,(_xlfn.XLOOKUP(Group!$B5,PL_NG!$C:$C,PL_NG!T:T)+_xlfn.XLOOKUP(Group!$B5,PL_UK!$C:$C,PL_UK!T:T)+_xlfn.XLOOKUP(Group!$B5,PL_UAE!$C:$C,PL_UAE!T:T)),0) -> -70273010 | T5: =IF(T$3<=Summary!$C$2,(_xlfn.XLOOKUP(Group!$B5,PL_NG!$C:$C,PL_NG!U:U)+_xlfn.XLOOKUP(Group!$B5,PL_UK!$C:$C,PL_UK!U:U)+_xlfn.XLOOKUP(Group!$B5,PL_UAE!$C:$C,PL_UAE!U:U)),0) -> -64141909 | U5: =IF(U$3<=Summary!$C$2,(_xlfn.XLOOKUP(Group!$B5,PL_NG!$C:$C,PL_NG!V:V)+_xlfn.XLOOKUP(Group!$B5,PL_UK!$C:$C,PL_UK!V:V)+_xlfn.XLOOKUP(Group!$B5,PL_UAE!$C:$C,PL_UAE!V:V)),0) -> -1.0630877e+08 | V5: =IF(V$3<=Summary!$C$2,(_xlfn.XLOOKUP(Group!$B5,PL_NG!$C:$C,PL_NG!W:W)+_xlfn.XLOOKUP(Group!$B5,PL_UK!$C:$C,PL_UK!W:W)+_xlfn.XLOOKUP(Group!$B5,PL_UAE!$C:$C,PL_UAE!W:W)),0) -> 8014316.8 | W5: =IF(W$3<=Summary!$C$2,(_xlfn.XLOOKUP(Group!$B5,PL_NG!$C:$C,PL_NG!X:X)+_xlfn.XLOOKUP(Group!$B5,PL_UK!$C:$C,PL_UK!X:X)+_xlfn.XLOOKUP(Group!$B5,PL_UAE!$C:$C,PL_UAE!X:X)),0) -> -1.1081229e+08 | X5: =IF(X$3<=Summary!$C$2,(_xlfn.XLOOKUP(Group!$B5,PL_NG!$C:$C,PL_NG!Y:Y)+_xlfn.XLOOKUP(Group!$B5,PL_UK!$C:$C,PL_UK!Y:Y)+_xlfn.XLOOKUP(Group!$B5,PL_UAE!$C:$C,PL_UAE!Y:Y)),0) -> -80546947 | Y5: =IF(Y$3<=Summary!$C$2,(_xlfn.XLOOKUP(Group!$B5,PL_NG!$C:$C,PL_NG!Z:Z)+_xlfn.XLOOKUP(Group!$B5,PL_UK!$C:$C,PL_UK!Z:Z)+_xlfn.XLOOKUP(Group!$B5,PL_UAE!$C:$C,PL_UAE!Z:Z)),0) -> -64452933 | Z5: =IF(Z$3<=Summary!$C$2,(_xlfn.XLOOKUP(Group!$B5,PL_NG!$C:$C,PL_NG!AA:AA)+_xlfn.XLOOKUP(Group!$B5,PL_UK!$C:$C,PL_UK!AA:AA)+_xlfn.XLOOKUP(Group!$B5,PL_UAE!$C:$C,PL_UAE!AA:AA)),0) -> -1.4999289e+08 | AA5: =IF(AA$3<=Summary!$C$2,(_xlfn.XLOOKUP(Group!$B5,PL_NG!$C:$C,PL_NG!AB:AB)+_xlfn.XLOOKUP(Group!$B5,PL_UK!$C:$C,PL_UK!AB:AB)+_xlfn.XLOOKUP(Group!$B5,PL_UAE!$C:$C,PL_UAE!AB:AB)),0) -> -1.5518618e+08 | AB5: =IF(AB$3<=Summary!$C$2,(_xlfn.XLOOKUP(Group!$B5,PL_NG!$C:$C,PL_NG!AC:AC)+_xlfn.XLOOKUP(Group!$B5,PL_UK!$C:$C,PL_UK!AC:AC)+_xlfn.XLOOKUP(Group!$B5,PL_UAE!$C:$C,PL_UAE!AC:AC)),0) -> -1.4194322e+08 | AC5: =IF(AC$3<=Summary!$C$2,(_xlfn.XLOOKUP(Group!$B5,PL_NG!$C:$C,PL_NG!AD:AD)+_xlfn.XLOOKUP(Group!$B5,PL_UK!$C:$C,PL_UK!AD:AD)+_xlfn.XLOOKUP(Group!$B5,PL_UAE!$C:$C,PL_UAE!AD:AD)),0) -> -1.4389944e+08 | AD5: =IF(AD$3<=Summary!$C$2,(_xlfn.XLOOKUP(Group!$B5,PL_NG!$C:$C,PL_NG!AE:AE)+_xlfn.XLOOKUP(Group!$B5,PL_UK!$C:$C,PL_UK!AE:AE)+_xlfn.XLOOKUP(Group!$B5,PL_UAE!$C:$C,PL_UAE!AE:AE)),0) -> -74747890 | AE5: =IF(AE$3<=Summary!$C$2,(_xlfn.XLOOKUP(Group!$B5,PL_NG!$C:$C,PL_NG!AF:AF)+_xlfn.XLOOKUP(Group!$B5,PL_UK!$C:$C,PL_UK!AF:AF)+_xlfn.XLOOKUP(Group!$B5,PL_UAE!$C:$C,PL_UAE!AF:AF)),0) -> 0 | AF5: =IF(AF$3<=Summary!$C$2,(_xlfn.XLOOKUP(Group!$B5,PL_NG!$C:$C,PL_NG!AG:AG)+_xlfn.XLOOKUP(Group!$B5,PL_UK!$C:$C,PL_UK!AG:AG)+_xlfn.XLOOKUP(Group!$B5,PL_UAE!$C:$C,PL_UAE!AG:AG)),0) -> 0 | AG5: =IF(AG$3<=Summary!$C$2,(_xlfn.XLOOKUP(Group!$B5,PL_NG!$C:$C,PL_NG!AH:AH)+_xlfn.XLOOKUP(Group!$B5,PL_UK!$C:$C,PL_UK!AH:AH)+_xlfn.XLOOKUP(Group!$B5,PL_UAE!$C:$C,PL_UAE!AH:AH)),0) -> 0 | AH5: =IF(AH$3<=Summary!$C$2,(_xlfn.XLOOKUP(Group!$B5,PL_NG!$C:$C,PL_NG!AI:AI)+_xlfn.XLOOKUP(Group!$B5,PL_UK!$C:$C,PL_UK!AI:AI)+_xlfn.XLOOKUP(Group!$B5,PL_UAE!$C:$C,PL_UAE!AI:AI)),0) -> 0 | AI5: =IF(AI$3<=Summary!$C$2,(_xlfn.XLOOKUP(Group!$B5,PL_NG!$C:$C,PL_NG!AJ:AJ)+_xlfn.XLOOKUP(Group!$B5,PL_UK!$C:$C,PL_UK!AJ:AJ)+_xlfn.XLOOKUP(Group!$B5,PL_UAE!$C:$C,PL_UAE!AJ:AJ)),0) -> 0 | AJ5: =IF(AJ$3<=Summary!$C$2,(_xlfn.XLOOKUP(Group!$B5,PL_NG!$C:$C,PL_NG!AK:AK)+_xlfn.XLOOKUP(Group!$B5,PL_UK!$C:$C,PL_UK!AK:AK)+_xlfn.XLOOKUP(Group!$B5,PL_UAE!$C:$C,PL_UAE!AK:AK)),0) -> 0 | AK5: =IF(AK$3<=Summary!$C$2,(_xlfn.XLOOKUP(Group!$B5,PL_NG!$C:$C,PL_NG!AL:AL)+_xlfn.XLOOKUP(Group!$B5,PL_UK!$C:$C,PL_UK!AL:AL)+_xlfn.XLOOKUP(Group!$B5,PL_UAE!$C:$C,PL_UAE!AL:AL)),0) -> 0 | AL5: =IF(AL$3<=Summary!$C$2,(_xlfn.XLOOKUP(Group!$B5,PL_NG!$C:$C,PL_NG!AM:AM)+_xlfn.XLOOKUP(Group!$B5,PL_UK!$C:$C,PL_UK!AM:AM)+_xlfn.XLOOKUP(Group!$B5,PL_UAE!$C:$C,PL_UAE!AM:AM)),0) -> 0
B6: TOTAL OTHER REVENUE | C6: =IF(C$3<=Summary!$C$2,(_xlfn.XLOOKUP(Group!$B6,PL_NG!$C:$C,PL_NG!D:D)+_xlfn.XLOOKUP(Group!$B6,PL_UK!$C:$C,PL_UK!D:D)+_xlfn.XLOOKUP(Group!$B6,PL_UAE!$C:$C,PL_UAE!D:D)),0) -> 54873.98 | D6: =IF(D$3<=Summary!$C$2,(_xlfn.XLOOKUP(Group!$B6,PL_NG!$C:$C,PL_NG!E:E)+_xlfn.XLOOKUP(Group!$B6,PL_UK!$C:$C,PL_UK!E:E)+_xlfn.XLOOKUP(Group!$B6,PL_UAE!$C:$C,PL_UAE!E:E)),0) -> 28793.59 | E6: =IF(E$3<=Summary!$C$2,(_xlfn.XLOOKUP(Group!$B6,PL_NG!$C:$C,PL_NG!F:F)+_xlfn.XLOOKUP(Group!$B6,PL_UK!$C:$C,PL_UK!F:F)+_xlfn.XLOOKUP(Group!$B6,PL_UAE!$C:$C,PL_UAE!F:F)),0) -> 36275.65 | F6: =IF(F$3<=Summary!$C$2,(_xlfn.XLOOKUP(Group!$B6,PL_NG!$C:$C,PL_NG!G:G)+_xlfn.XLOOKUP(Group!$B6,PL_UK!$C:$C,PL_UK!G:G)+_xlfn.XLOOKUP(Group!$B6,PL_UAE!$C:$C,PL_UAE!G:G)),0) -> 308917.02 | G6: =IF(G$3<=Summary!$C$2,(_xlfn.XLOOKUP(Group!$B6,PL_NG!$C:$C,PL_NG!H:H)+_xlfn.XLOOKUP(Group!$B6,PL_UK!$C:$C,PL_UK!H:H)+_xlfn.XLOOKUP(Group!$B6,PL_UAE!$C:$C,PL_UAE!H:H)),0) -> 9570381.1 | H6: =IF(H$3<=Summary!$C$2,(_xlfn.XLOOKUP(Group!$B6,PL_NG!$C:$C,PL_NG!I:I)+_xlfn.XLOOKUP(Group!$B6,PL_UK!$C:$C,PL_UK!I:I)+_xlfn.XLOOKUP(Group!$B6,PL_UAE!$C:$C,PL_UAE!I:I)),0) -> 33173690 | I6: =IF(I$3<=Summary!$C$2,(_xlfn.XLOOKUP(Group!$B6,PL_NG!$C:$C,PL_NG!J:J)+_xlfn.XLOOKUP(Group!$B6,PL_UK!$C:$C,PL_UK!J:J)+_xlfn.XLOOKUP(Group!$B6,PL_UAE!$C:$C,PL_UAE!J:J)),0) -> 31628524 | J6: =IF(J$3<=Summary!$C$2,(_xlfn.XLOOKUP(Group!$B6,PL_NG!$C:$C,PL_NG!K:K)+_xlfn.XLOOKUP(Group!$B6,PL_UK!$C:$C,PL_UK!K:K)+_xlfn.XLOOKUP(Group!$B6,PL_UAE!$C:$C,PL_UAE!K:K)),0) -> 33151885 | K6: =IF(K$3<=Summary!$C$2,(_xlfn.XLOOKUP(Group!$B6,PL_NG!$C:$C,PL_NG!L:L)+_xlfn.XLOOKUP(Group!$B6,PL_UK!$C:$C,PL_UK!L:L)+_xlfn.XLOOKUP(Group!$B6,PL_UAE!$C:$C,PL_UAE!L:L)),0) -> 2841293 | L6: =IF(L$3<=Summary!$C$2,(_xlfn.XLOOKUP(Group!$B6,PL_NG!$C:$C,PL_NG!M:M)+_xlfn.XLOOKUP(Group!$B6,PL_UK!$C:$C,PL_UK!M:M)+_xlfn.XLOOKUP(Group!$B6,PL_UAE!$C:$C,PL_UAE!M:M)),0) -> 77487952 | M6: =IF(M$3<=Summary!$C$2,(_xlfn.XLOOKUP(Group!$B6,PL_NG!$C:$C,PL_NG!N:N)+_xlfn.XLOOKUP(Group!$B6,PL_UK!$C:$C,PL_UK!N:N)+_xlfn.XLOOKUP(Group!$B6,PL_UAE!$C:$C,PL_UAE!N:N)),0) -> 41107532 | N6: =IF(N$3<=Summary!$C$2,(_xlfn.XLOOKUP(Group!$B6,PL_NG!$C:$C,PL_NG!O:O)+_xlfn.XLOOKUP(Group!$B6,PL_UK!$C:$C,PL_UK!O:O)+_xlfn.XLOOKUP(Group!$B6,PL_UAE!$C:$C,PL_UAE!O:O)),0) -> 43432413 | O6: =IF(O$3<=Summary!$C$2,(_xlfn.XLOOKUP(Group!$B6,PL_NG!$C:$C,PL_NG!P:P)+_xlfn.XLOOKUP(Group!$B6,PL_UK!$C:$C,PL_UK!P:P)+_xlfn.XLOOKUP(Group!$B6,PL_UAE!$C:$C,PL_UAE!P:P)),0) -> 39010459 | P6: =IF(P$3<=Summary!$C$2,(_xlfn.XLOOKUP(Group!$B6,PL_NG!$C:$C,PL_NG!Q:Q)+_xlfn.XLOOKUP(Group!$B6,PL_UK!$C:$C,PL_UK!Q:Q)+_xlfn.XLOOKUP(Group!$B6,PL_UAE!$C:$C,PL_UAE!Q:Q)),0) -> 31301634 | Q6: =IF(Q$3<=Summary!$C$2,(_xlfn.XLOOKUP(Group!$B6,PL_NG!$C:$C,PL_NG!R:R)+_xlfn.XLOOKUP(Group!$B6,PL_UK!$C:$C,PL_UK!R:R)+_xlfn.XLOOKUP(Group!$B6,PL_UAE!$C:$C,PL_UAE!R:R)),0) -> 28246672 | R6: =IF(R$3<=Summary!$C$2,(_xlfn.XLOOKUP(Group!$B6,PL_NG!$C:$C,PL_NG!S:S)+_xlfn.XLOOKUP(Group!$B6,PL_UK!$C:$C,PL_UK!S:S)+_xlfn.XLOOKUP(Group!$B6,PL_UAE!$C:$C,PL_UAE!S:S)),0) -> 29699520 | S6: =IF(S$3<=Summary!$C$2,(_xlfn.XLOOKUP(Group!$B6,PL_NG!$C:$C,PL_NG!T:T)+_xlfn.XLOOKUP(Group!$B6,PL_UK!$C:$C,PL_UK!T:T)+_xlfn.XLOOKUP(Group!$B6,PL_UAE!$C:$C,PL_UAE!T:T)),0) -> 23109999 | T6: =IF(T$3<=Summary!$C$2,(_xlfn.XLOOKUP(Group!$B6,PL_NG!$C:$C,PL_NG!U:U)+_xlfn.XLOOKUP(Group!$B6,PL_UK!$C:$C,PL_UK!U:U)+_xlfn.XLOOKUP(Group!$B6,PL_UAE!$C:$C,PL_UAE!U:U)),0) -> 21501586 | U6: =IF(U$3<=Summary!$C$2,(_xlfn.XLOOKUP(Group!$B6,PL_NG!$C:$C,PL_NG!V:V)+_xlfn.XLOOKUP(Group!$B6,PL_UK!$C:$C,PL_UK!V:V)+_xlfn.XLOOKUP(Group!$B6,PL_UAE!$C:$C,PL_UAE!V:V)),0) -> 21339894 | V6: =IF(V$3<=Summary!$C$2,(_xlfn.XLOOKUP(Group!$B6,PL_NG!$C:$C,PL_NG!W:W)+_xlfn.XLOOKUP(Group!$B6,PL_UK!$C:$C,PL_UK!W:W)+_xlfn.XLOOKUP(Group!$B6,PL_UAE!$C:$C,PL_UAE!W:W)),0) -> 32103767 | W6: =IF(W$3<=Summary!$C$2,(_xlfn.XLOOKUP(Group!$B6,PL_NG!$C:$C,PL_NG!X:X)+_xlfn.XLOOKUP(Group!$B6,PL_UK!$C:$C,PL_UK!X:X)+_xlfn.XLOOKUP(Group!$B6,PL_UAE!$C:$C,PL_UAE!X:X)),0) -> 15620184 | X6: =IF(X$3<=Summary!$C$2,(_xlfn.XLOOKUP(Group!$B6,PL_NG!$C:$C,PL_NG!Y:Y)+_xlfn.XLOOKUP(Group!$B6,PL_UK!$C:$C,PL_UK!Y:Y)+_xlfn.XLOOKUP(Group!$B6,PL_UAE!$C:$C,PL_UAE!Y:Y)),0) -> 16531444 | Y6: =IF(Y$3<=Summary!$C$2,(_xlfn.XLOOKUP(Group!$B6,PL_NG!$C:$C,PL_NG!Z:Z)+_xlfn.XLOOKUP(Group!$B6,PL_UK!$C:$C,PL_UK!Z:Z)+_xlfn.XLOOKUP(Group!$B6,PL_UAE!$C:$C,PL_UAE!Z:Z)),0) -> 16189960 | Z6: =IF(Z$3<=Summary!$C$2,(_xlfn.XLOOKUP(Group!$B6,PL_NG!$C:$C,PL_NG!AA:AA)+_xlfn.XLOOKUP(Group!$B6,PL_UK!$C:$C,PL_UK!AA:AA)+_xlfn.XLOOKUP(Group!$B6,PL_UAE!$C:$C,PL_UAE!AA:AA)),0) -> 1.729648e+08 | AA6: =IF(AA$3<=Summary!$C$2,(_xlfn.XLOOKUP(Group!$B6,PL_NG!$C:$C,PL_NG!AB:AB)+_xlfn.XLOOKUP(Group!$B6,PL_UK!$C:$C,PL_UK!AB:AB)+_xlfn.XLOOKUP(Group!$B6,PL_UAE!$C:$C,PL_UAE!AB:AB)),0) -> 5399535.4 | AB6: =IF(AB$3<=Summary!$C$2,(_xlfn.XLOOKUP(Group!$B6,PL_NG!$C:$C,PL_NG!AC:AC)+_xlfn.XLOOKUP(Group!$B6,PL_UK!$C:$C,PL_UK!AC:AC)+_xlfn.XLOOKUP(Group!$B6,PL_UAE!$C:$C,PL_UAE!AC:AC)),0) -> 22316487 | AC6: =IF(AC$3<=Summary!$C$2,(_xlfn.XLOOKUP(Group!$B6,PL_NG!$C:$C,PL_NG!AD:AD)+_xlfn.XLOOKUP(Group!$B6,PL_UK!$C:$C,PL_UK!AD:AD)+_xlfn.XLOOKUP(Group!$B6,PL_UAE!$C:$C,PL_UAE!AD:AD)),0) -> -18478033 | AD6: =IF(AD$3<=Summary!$C$2,(_xlfn.XLOOKUP(Group!$B6,PL_NG!$C:$C,PL_NG!AE:AE)+_xlfn.XLOOKUP(Group!$B6,PL_UK!$C:$C,PL_UK!AE:AE)+_xlfn.XLOOKUP(Group!$B6,PL_UAE!$C:$C,PL_UAE!AE:AE)),0) -> 63198520 | AE6: =IF(AE$3<=Summary!$C$2,(_xlfn.XLOOKUP(Group!$B6,PL_NG!$C:$C,PL_NG!AF:AF)+_xlfn.XLOOKUP(Group!$B6,PL_UK!$C:$C,PL_UK!AF:AF)+_xlfn.XLOOKUP(Group!$B6,PL_UAE!$C:$C,PL_UAE!AF:AF)),0) -> 0 | AF6: =IF(AF$3<=Summary!$C$2,(_xlfn.XLOOKUP(Group!$B6,PL_NG!$C:$C,PL_NG!AG:AG)+_xlfn.XLOOKUP(Group!$B6,PL_UK!$C:$C,PL_UK!AG:AG)+_xlfn.XLOOKUP(Group!$B6,PL_UAE!$C:$C,PL_UAE!AG:AG)),0) -> 0 | AG6: =IF(AG$3<=Summary!$C$2,(_xlfn.XLOOKUP(Group!$B6,PL_NG!$C:$C,PL_NG!AH:AH)+_xlfn.XLOOKUP(Group!$B6,PL_UK!$C:$C,PL_UK!AH:AH)+_xlfn.XLOOKUP(Group!$B6,PL_UAE!$C:$C,PL_UAE!AH:AH)),0) -> 0 | AH6: =IF(AH$3<=Summary!$C$2,(_xlfn.XLOOKUP(Group!$B6,PL_NG!$C:$C,PL_NG!AI:AI)+_xlfn.XLOOKUP(Group!$B6,PL_UK!$C:$C,PL_UK!AI:AI)+_xlfn.XLOOKUP(Group!$B6,PL_UAE!$C:$C,PL_UAE!AI:AI)),0) -> 0 | AI6: =IF(AI$3<=Summary!$C$2,(_xlfn.XLOOKUP(Group!$B6,PL_NG!$C:$C,PL_NG!AJ:AJ)+_xlfn.XLOOKUP(Group!$B6,PL_UK!$C:$C,PL_UK!AJ:AJ)+_xlfn.XLOOKUP(Group!$B6,PL_UAE!$C:$C,PL_UAE!AJ:AJ)),0) -> 0 | AJ6: =IF(AJ$3<=Summary!$C$2,(_xlfn.XLOOKUP(Group!$B6,PL_NG!$C:$C,PL_NG!AK:AK)+_xlfn.XLOOKUP(Group!$B6,PL_UK!$C:$C,PL_UK!AK:AK)+_xlfn.XLOOKUP(Group!$B6,PL_UAE!$C:$C,PL_UAE!AK:AK)),0) -> 0 | AK6: =IF(AK$3<=Summary!$C$2,(_xlfn.XLOOKUP(Group!$B6,PL_NG!$C:$C,PL_NG!AL:AL)+_xlfn.XLOOKUP(Group!$B6,PL_UK!$C:$C,PL_UK!AL:AL)+_xlfn.XLOOKUP(Group!$B6,PL_UAE!$C:$C,PL_UAE!AL:AL)),0) -> 0 | AL6: =IF(AL$3<=Summary!$C$2,(_xlfn.XLOOKUP(Group!$B6,PL_NG!$C:$C,PL_NG!AM:AM)+_xlfn.XLOOKUP(Group!$B6,PL_UK!$C:$C,PL_UK!AM:AM)+_xlfn.XLOOKUP(Group!$B6,PL_UAE!$C:$C,PL_UAE!AM:AM)),0) -> 0
B7: TOTAL OPERATING EXPENSES | C7: =IF(C$3<=Summary!$C$2,(_xlfn.XLOOKUP(Group!$B7,PL_NG!$C:$C,PL_NG!D:D)+_xlfn.XLOOKUP(Group!$B7,PL_UK!$C:$C,PL_UK!D:D)+_xlfn.XLOOKUP(Group!$B7,PL_UAE!$C:$C,PL_UAE!D:D)),0) -> -1.396446e+08 | D7: =IF(D$3<=Summary!$C$2,(_xlfn.XLOOKUP(Group!$B7,PL_NG!$C:$C,PL_NG!E:E)+_xlfn.XLOOKUP(Group!$B7,PL_UK!$C:$C,PL_UK!E:E)+_xlfn.XLOOKUP(Group!$B7,PL_UAE!$C:$C,PL_UAE!E:E)),0) -> -1.6072419e+08 | E7: =IF(E$3<=Summary!$C$2,(_xlfn.XLOOKUP(Group!$B7,PL_NG!$C:$C,PL_NG!F:F)+_xlfn.XLOOKUP(Group!$B7,PL_UK!$C:$C,PL_UK!F:F)+_xlfn.XLOOKUP(Group!$B7,PL_UAE!$C:$C,PL_UAE!F:F)),0) -> -5.0489838e+08 | F7: =IF(F$3<=Summary!$C$2,(_xlfn.XLOOKUP(Group!$B7,PL_NG!$C:$C,PL_NG!G:G)+_xlfn.XLOOKUP(Group!$B7,PL_UK!$C:$C,PL_UK!G:G)+_xlfn.XLOOKUP(Group!$B7,PL_UAE!$C:$C,PL_UAE!G:G)),0) -> -1.8891924e+08 | G7: =IF(G$3<=Summary!$C$2,(_xlfn.XLOOKUP(Group!$B7,PL_NG!$C:$C,PL_NG!H:H)+_xlfn.XLOOKUP(Group!$B7,PL_UK!$C:$C,PL_UK!H:H)+_xlfn.XLOOKUP(Group!$B7,PL_UAE!$C:$C,PL_UAE!H:H)),0) -> -3.5064369e+08 | H7: =IF(H$3<=Summary!$C$2,(_xlfn.XLOOKUP(Group!$B7,PL_NG!$C:$C,PL_NG!I:I)+_xlfn.XLOOKUP(Group!$B7,PL_UK!$C:$C,PL_UK!I:I)+_xlfn.XLOOKUP(Group!$B7,PL_UAE!$C:$C,PL_UAE!I:I)),0) -> -3.3039165e+08 | I7: =IF(I$3<=Summary!$C$2,(_xlfn.XLOOKUP(Group!$B7,PL_NG!$C:$C,PL_NG!J:J)+_xlfn.XLOOKUP(Group!$B7,PL_UK!$C:$C,PL_UK!J:J)+_xlfn.XLOOKUP(Group!$B7,PL_UAE!$C:$C,PL_UAE!J:J)),0) -> -3.7832608e+08 | J7: =IF(J$3<=Summary!$C$2,(_xlfn.XLOOKUP(Group!$B7,PL_NG!$C:$C,PL_NG!K:K)+_xlfn.XLOOKUP(Group!$B7,PL_UK!$C:$C,PL_UK!K:K)+_xlfn.XLOOKUP(Group!$B7,PL_UAE!$C:$C,PL_UAE!K:K)),0) -> -2.2045908e+08 | K7: =IF(K$3<=Summary!$C$2,(_xlfn.XLOOKUP(Group!$B7,PL_NG!$C:$C,PL_NG!L:L)+_xlfn.XLOOKUP(Group!$B7,PL_UK!$C:$C,PL_UK!L:L)+_xlfn.XLOOKUP(Group!$B7,PL_UAE!$C:$C,PL_UAE!L:L)),0) -> -1.6456841e+08 | L7: =IF(L$3<=Summary!$C$2,(_xlfn.XLOOKUP(Group!$B7,PL_NG!$C:$C,PL_NG!M:M)+_xlfn.XLOOKUP(Group!$B7,PL_UK!$C:$C,PL_UK!M:M)+_xlfn.XLOOKUP(Group!$B7,PL_UAE!$C:$C,PL_UAE!M:M)),0) -> -5.4327245e+08 | M7: =IF(M$3<=Summary!$C$2,(_xlfn.XLOOKUP(Group!$B7,PL_NG!$C:$C,PL_NG!N:N)+_xlfn.XLOOKUP(Group!$B7,PL_UK!$C:$C,PL_UK!N:N)+_xlfn.XLOOKUP(Group!$B7,PL_UAE!$C:$C,PL_UAE!N:N)),0) -> -4.9102521e+08 | N7: =IF(N$3<=Summary!$C$2,(_xlfn.XLOOKUP(Group!$B7,PL_NG!$C:$C,PL_NG!O:O)+_xlfn.XLOOKUP(Group!$B7,PL_UK!$C:$C,PL_UK!O:O)+_xlfn.XLOOKUP(Group!$B7,PL_UAE!$C:$C,PL_UAE!O:O)),0) -> -1.6807679e+08 | O7: =IF(O$3<=Summary!$C$2,(_xlfn.XLOOKUP(Group!$B7,PL_NG!$C:$C,PL_NG!P:P)+_xlfn.XLOOKUP(Group!$B7,PL_UK!$C:$C,PL_UK!P:P)+_xlfn.XLOOKUP(Group!$B7,PL_UAE!$C:$C,PL_UAE!P:P)),0) -> -2.8034486e+08 | P7: =IF(P$3<=Summary!$C$2,(_xlfn.XLOOKUP(Group!$B7,PL_NG!$C:$C,PL_NG!Q:Q)+_xlfn.XLOOKUP(Group!$B7,PL_UK!$C:$C,PL_UK!Q:Q)+_xlfn.XLOOKUP(Group!$B7,PL_UAE!$C:$C,PL_UAE!Q:Q)),0) -> -2.9097878e+08 | Q7: =IF(Q$3<=Summary!$C$2,(_xlfn.XLOOKUP(Group!$B7,PL_NG!$C:$C,PL_NG!R:R)+_xlfn.XLOOKUP(Group!$B7,PL_UK!$C:$C,PL_UK!R:R)+_xlfn.XLOOKUP(Group!$B7,PL_UAE!$C:$C,PL_UAE!R:R)),0) -> -2.9089761e+08 | R7: =IF(R$3<=Summary!$C$2,(_xlfn.XLOOKUP(Group!$B7,PL_NG!$C:$C,PL_NG!S:S)+_xlfn.XLOOKUP(Group!$B7,PL_UK!$C:$C,PL_UK!S:S)+_xlfn.XLOOKUP(Group!$B7,PL_UAE!$C:$C,PL_UAE!S:S)),0) -> -1.8319331e+08 | S7: =IF(S$3<=Summary!$C$2,(_xlfn.XLOOKUP(Group!$B7,PL_NG!$C:$C,PL_NG!T:T)+_xlfn.XLOOKUP(Group!$B7,PL_UK!$C:$C,PL_UK!T:T)+_xlfn.XLOOKUP(Group!$B7,PL_UAE!$C:$C,PL_UAE!T:T)),0) -> -4.9407195e+08 | T7: =IF(T$3<=Summary!$C$2,(_xlfn.XLOOKUP(Group!$B7,PL_NG!$C:$C,PL_NG!U:U)+_xlfn.XLOOKUP(Group!$B7,PL_UK!$C:$C,PL_UK!U:U)+_xlfn.XLOOKUP(Group!$B7,PL_UAE!$C:$C,PL_UAE!U:U)),0) -> -4.2519913e+08 | U7: =IF(U$3<=Summary!$C$2,(_xlfn.XLOOKUP(Group!$B7,PL_NG!$C:$C,PL_NG!V:V)+_xlfn.XLOOKUP(Group!$B7,PL_UK!$C:$C,PL_UK!V:V)+_xlfn.XLOOKUP(Group!$B7,PL_UAE!$C:$C,PL_UAE!V:V)),0) -> -3.7276407e+08 | V7: =IF(V$3<=Summary!$C$2,(_xlfn.XLOOKUP(Group!$B7,PL_NG!$C:$C,PL_NG!W:W)+_xlfn.XLOOKUP(Group!$B7,PL_UK!$C:$C,PL_UK!W:W)+_xlfn.XLOOKUP(Group!$B7,PL_UAE!$C:$C,PL_UAE!W:W)),0) -> -3.3948152e+08 | W7: =IF(W$3<=Summary!$C$2,(_xlfn.XLOOKUP(Group!$B7,PL_NG!$C:$C,PL_NG!X:X)+_xlfn.XLOOKUP(Group!$B7,PL_UK!$C:$C,PL_UK!X:X)+_xlfn.XLOOKUP(Group!$B7,PL_UAE!$C:$C,PL_UAE!X:X)),0) -> -5.2949147e+08 | X7: =IF(X$3<=Summary!$C$2,(_xlfn.XLOOKUP(Group!$B7,PL_NG!$C:$C,PL_NG!Y:Y)+_xlfn.XLOOKUP(Group!$B7,PL_UK!$C:$C,PL_UK!Y:Y)+_xlfn.XLOOKUP(Group!$B7,PL_UAE!$C:$C,PL_UAE!Y:Y)),0) -> -4.2643524e+08 | Y7: =IF(Y$3<=Summary!$C$2,(_xlfn.XLOOKUP(Group!$B7,PL_NG!$C:$C,PL_NG!Z:Z)+_xlfn.XLOOKUP(Group!$B7,PL_UK!$C:$C,PL_UK!Z:Z)+_xlfn.XLOOKUP(Group!$B7,PL_UAE!$C:$C,PL_UAE!Z:Z)),0) -> -3.7939108e+08 | Z7: =IF(Z$3<=Summary!$C$2,(_xlfn.XLOOKUP(Group!$B7,PL_NG!$C:$C,PL_NG!AA:AA)+_xlfn.XLOOKUP(Group!$B7,PL_UK!$C:$C,PL_UK!AA:AA)+_xlfn.XLOOKUP(Group!$B7,PL_UAE!$C:$C,PL_UAE!AA:AA)),0) -> -5.9356346e+08 | AA7: =IF(AA$3<=Summary!$C$2,(_xlfn.XLOOKUP(Group!$B7,PL_NG!$C:$C,PL_NG!AB:AB)+_xlfn.XLOOKUP(Group!$B7,PL_UK!$C:$C,PL_UK!AB:AB)+_xlfn.XLOOKUP(Group!$B7,PL_UAE!$C:$C,PL_UAE!AB:AB)),0) -> -3.689248e+08 | AB7: =IF(AB$3<=Summary!$C$2,(_xlfn.XLOOKUP(Group!$B7,PL_NG!$C:$C,PL_NG!AC:AC)+_xlfn.XLOOKUP(Group!$B7,PL_UK!$C:$C,PL_UK!AC:AC)+_xlfn.XLOOKUP(Group!$B7,PL_UAE!$C:$C,PL_UAE!AC:AC)),0) -> -3.3809356e+08 | AC7: =IF(AC$3<=Summary!$C$2,(_xlfn.XLOOKUP(Group!$B7,PL_NG!$C:$C,PL_NG!AD:AD)+_xlfn.XLOOKUP(Group!$B7,PL_UK!$C:$C,PL_UK!AD:AD)+_xlfn.XLOOKUP(Group!$B7,PL_UAE!$C:$C,PL_UAE!AD:AD)),0) -> -3.0400252e+08 | AD7: =IF(AD$3<=Summary!$C$2,(_xlfn.XLOOKUP(Group!$B7,PL_NG!$C:$C,PL_NG!AE:AE)+_xlfn.XLOOKUP(Group!$B7,PL_UK!$C:$C,PL_UK!AE:AE)+_xlfn.XLOOKUP(Group!$B7,PL_UAE!$C:$C,PL_UAE!AE:AE)),0) -> -2.9878433e+08 | AE7: =IF(AE$3<=Summary!$C$2,(_xlfn.XLOOKUP(Group!$B7,PL_NG!$C:$C,PL_NG!AF:AF)+_xlfn.XLOOKUP(Group!$B7,PL_UK!$C:$C,PL_UK!AF:AF)+_xlfn.XLOOKUP(Group!$B7,PL_UAE!$C:$C,PL_UAE!AF:AF)),0) -> 0 | AF7: =IF(AF$3<=Summary!$C$2,(_xlfn.XLOOKUP(Group!$B7,PL_NG!$C:$C,PL_NG!AG:AG)+_xlfn.XLOOKUP(Group!$B7,PL_UK!$C:$C,PL_UK!AG:AG)+_xlfn.XLOOKUP(Group!$B7,PL_UAE!$C:$C,PL_UAE!AG:AG)),0) -> 0 | AG7: =IF(AG$3<=Summary!$C$2,(_xlfn.XLOOKUP(Group!$B7,PL_NG!$C:$C,PL_NG!AH:AH)+_xlfn.XLOOKUP(Group!$B7,PL_UK!$C:$C,PL_UK!AH:AH)+_xlfn.XLOOKUP(Group!$B7,PL_UAE!$C:$C,PL_UAE!AH:AH)),0) -> 0 | AH7: =IF(AH$3<=Summary!$C$2,(_xlfn.XLOOKUP(Group!$B7,PL_NG!$C:$C,PL_NG!AI:AI)+_xlfn.XLOOKUP(Group!$B7,PL_UK!$C:$C,PL_UK!AI:AI)+_xlfn.XLOOKUP(Group!$B7,PL_UAE!$C:$C,PL_UAE!AI:AI)),0) -> 0 | AI7: =IF(AI$3<=Summary!$C$2,(_xlfn.XLOOKUP(Group!$B7,PL_NG!$C:$C,PL_NG!AJ:AJ)+_xlfn.XLOOKUP(Group!$B7,PL_UK!$C:$C,PL_UK!AJ:AJ)+_xlfn.XLOOKUP(Group!$B7,PL_UAE!$C:$C,PL_UAE!AJ:AJ)),0) -> 0 | AJ7: =IF(AJ$3<=Summary!$C$2,(_xlfn.XLOOKUP(Group!$B7,PL_NG!$C:$C,PL_NG!AK:AK)+_xlfn.XLOOKUP(Group!$B7,PL_UK!$C:$C,PL_UK!AK:AK)+_xlfn.XLOOKUP(Group!$B7,PL_UAE!$C:$C,PL_UAE!AK:AK)),0) -> 0 | AK7: =IF(AK$3<=Summary!$C$2,(_xlfn.XLOOKUP(Group!$B7,PL_NG!$C:$C,PL_NG!AL:AL)+_xlfn.XLOOKUP(Group!$B7,PL_UK!$C:$C,PL_UK!AL:AL)+_xlfn.XLOOKUP(Group!$B7,PL_UAE!$C:$C,PL_UAE!AL:AL)),0) -> 0 | AL7: =IF(AL$3<=Summary!$C$2,(_xlfn.XLOOKUP(Group!$B7,PL_NG!$C:$C,PL_NG!AM:AM)+_xlfn.XLOOKUP(Group!$B7,PL_UK!$C:$C,PL_UK!AM:AM)+_xlfn.XLOOKUP(Group!$B7,PL_UAE!$C:$C,PL_UAE!AM:AM)),0) -> 0
B8: TOTAL DEPRECIATION & AMORTISATION | C8: =IF(C$3<=Summary!$C$2,(_xlfn.XLOOKUP(Group!$B8,PL_NG!$C:$C,PL_NG!D:D)+_xlfn.XLOOKUP(Group!$B8,PL_UK!$C:$C,PL_UK!D:D)+_xlfn.XLOOKUP(Group!$B8,PL_UAE!$C:$C,PL_UAE!D:D)),0) -> -2995833.9 | D8: =IF(D$3<=Summary!$C$2,(_xlfn.XLOOKUP(Group!$B8,PL_NG!$C:$C,PL_NG!E:E)+_xlfn.XLOOKUP(Group!$B8,PL_UK!$C:$C,PL_UK!E:E)+_xlfn.XLOOKUP(Group!$B8,PL_UAE!$C:$C,PL_UAE!E:E)),0) -> -3291706.3 | E8: =IF(E$3<=Summary!$C$2,(_xlfn.XLOOKUP(Group!$B8,PL_NG!$C:$C,PL_NG!F:F)+_xlfn.XLOOKUP(Group!$B8,PL_UK!$C:$C,PL_UK!F:F)+_xlfn.XLOOKUP(Group!$B8,PL_UAE!$C:$C,PL_UAE!F:F)),0) -> -2965718.8 | F8: =IF(F$3<=Summary!$C$2,(_xlfn.XLOOKUP(Group!$B8,PL_NG!$C:$C,PL_NG!G:G)+_xlfn.XLOOKUP(Group!$B8,PL_UK!$C:$C,PL_UK!G:G)+_xlfn.XLOOKUP(Group!$B8,PL_UAE!$C:$C,PL_UAE!G:G)),0) -> -2633116.7 | G8: =IF(G$3<=Summary!$C$2,(_xlfn.XLOOKUP(Group!$B8,PL_NG!$C:$C,PL_NG!H:H)+_xlfn.XLOOKUP(Group!$B8,PL_UK!$C:$C,PL_UK!H:H)+_xlfn.XLOOKUP(Group!$B8,PL_UAE!$C:$C,PL_UAE!H:H)),0) -> -3068876.8 | H8: =IF(H$3<=Summary!$C$2,(_xlfn.XLOOKUP(Group!$B8,PL_NG!$C:$C,PL_NG!I:I)+_xlfn.XLOOKUP(Group!$B8,PL_UK!$C:$C,PL_UK!I:I)+_xlfn.XLOOKUP(Group!$B8,PL_UAE!$C:$C,PL_UAE!I:I)),0) -> -3487754.1 | I8: =IF(I$3<=Summary!$C$2,(_xlfn.XLOOKUP(Group!$B8,PL_NG!$C:$C,PL_NG!J:J)+_xlfn.XLOOKUP(Group!$B8,PL_UK!$C:$C,PL_UK!J:J)+_xlfn.XLOOKUP(Group!$B8,PL_UAE!$C:$C,PL_UAE!J:J)),0) -> -3320451.2 | J8: =IF(J$3<=Summary!$C$2,(_xlfn.XLOOKUP(Group!$B8,PL_NG!$C:$C,PL_NG!K:K)+_xlfn.XLOOKUP(Group!$B8,PL_UK!$C:$C,PL_UK!K:K)+_xlfn.XLOOKUP(Group!$B8,PL_UAE!$C:$C,PL_UAE!K:K)),0) -> -4516696.9 | K8: =IF(K$3<=Summary!$C$2,(_xlfn.XLOOKUP(Group!$B8,PL_NG!$C:$C,PL_NG!L:L)+_xlfn.XLOOKUP(Group!$B8,PL_UK!$C:$C,PL_UK!L:L)+_xlfn.XLOOKUP(Group!$B8,PL_UAE!$C:$C,PL_UAE!L:L)),0) -> -4489991.1 | L8: =IF(L$3<=Summary!$C$2,(_xlfn.XLOOKUP(Group!$B8,PL_NG!$C:$C,PL_NG!M:M)+_xlfn.XLOOKUP(Group!$B8,PL_UK!$C:$C,PL_UK!M:M)+_xlfn.XLOOKUP(Group!$B8,PL_UAE!$C:$C,PL_UAE!M:M)),0) -> -4643826.4 | M8: =IF(M$3<=Summary!$C$2,(_xlfn.XLOOKUP(Group!$B8,PL_NG!$C:$C,PL_NG!N:N)+_xlfn.XLOOKUP(Group!$B8,PL_UK!$C:$C,PL_UK!N:N)+_xlfn.XLOOKUP(Group!$B8,PL_UAE!$C:$C,PL_UAE!N:N)),0) -> -4769940.9 | N8: =IF(N$3<=Summary!$C$2,(_xlfn.XLOOKUP(Group!$B8,PL_NG!$C:$C,PL_NG!O:O)+_xlfn.XLOOKUP(Group!$B8,PL_UK!$C:$C,PL_UK!O:O)+_xlfn.XLOOKUP(Group!$B8,PL_UAE!$C:$C,PL_UAE!O:O)),0) -> -4734679.3 | O8: =IF(O$3<=Summary!$C$2,(_xlfn.XLOOKUP(Group!$B8,PL_NG!$C:$C,PL_NG!P:P)+_xlfn.XLOOKUP(Group!$B8,PL_UK!$C:$C,PL_UK!P:P)+_xlfn.XLOOKUP(Group!$B8,PL_UAE!$C:$C,PL_UAE!P:P)),0) -> -4796595.2 | P8: =IF(P$3<=Summary!$C$2,(_xlfn.XLOOKUP(Group!$B8,PL_NG!$C:$C,PL_NG!Q:Q)+_xlfn.XLOOKUP(Group!$B8,PL_UK!$C:$C,PL_UK!Q:Q)+_xlfn.XLOOKUP(Group!$B8,PL_UAE!$C:$C,PL_UAE!Q:Q)),0) -> -5059380.6 | Q8: =IF(Q$3<=Summary!$C$2,(_xlfn.XLOOKUP(Group!$B8,PL_NG!$C:$C,PL_NG!R:R)+_xlfn.XLOOKUP(Group!$B8,PL_UK!$C:$C,PL_UK!R:R)+_xlfn.XLOOKUP(Group!$B8,PL_UAE!$C:$C,PL_UAE!R:R)),0) -> -5098755.7 | R8: =IF(R$3<=Summary!$C$2,(_xlfn.XLOOKUP(Group!$B8,PL_NG!$C:$C,PL_NG!S:S)+_xlfn.XLOOKUP(Group!$B8,PL_UK!$C:$C,PL_UK!S:S)+_xlfn.XLOOKUP(Group!$B8,PL_UAE!$C:$C,PL_UAE!S:S)),0) -> -5113187.3 | S8: =IF(S$3<=Summary!$C$2,(_xlfn.XLOOKUP(Group!$B8,PL_NG!$C:$C,PL_NG!T:T)+_xlfn.XLOOKUP(Group!$B8,PL_UK!$C:$C,PL_UK!T:T)+_xlfn.XLOOKUP(Group!$B8,PL_UAE!$C:$C,PL_UAE!T:T)),0) -> -5119640.4 | T8: =IF(T$3<=Summary!$C$2,(_xlfn.XLOOKUP(Group!$B8,PL_NG!$C:$C,PL_NG!U:U)+_xlfn.XLOOKUP(Group!$B8,PL_UK!$C:$C,PL_UK!U:U)+_xlfn.XLOOKUP(Group!$B8,PL_UAE!$C:$C,PL_UAE!U:U)),0) -> -5116140 | U8: =IF(U$3<=Summary!$C$2,(_xlfn.XLOOKUP(Group!$B8,PL_NG!$C:$C,PL_NG!V:V)+_xlfn.XLOOKUP(Group!$B8,PL_UK!$C:$C,PL_UK!V:V)+_xlfn.XLOOKUP(Group!$B8,PL_UAE!$C:$C,PL_UAE!V:V)),0) -> -7739986.9 | V8: =IF(V$3<=Summary!$C$2,(_xlfn.XLOOKUP(Group!$B8,PL_NG!$C:$C,PL_NG!W:W)+_xlfn.XLOOKUP(Group!$B8,PL_UK!$C:$C,PL_UK!W:W)+_xlfn.XLOOKUP(Group!$B8,PL_UAE!$C:$C,PL_UAE!W:W)),0) -> -6663455.8 | W8: =IF(W$3<=Summary!$C$2,(_xlfn.XLOOKUP(Group!$B8,PL_NG!$C:$C,PL_NG!X:X)+_xlfn.XLOOKUP(Group!$B8,PL_UK!$C:$C,PL_UK!X:X)+_xlfn.XLOOKUP(Group!$B8,PL_UAE!$C:$C,PL_UAE!X:X)),0) -> -6619303.6 | X8: =IF(X$3<=Summary!$C$2,(_xlfn.XLOOKUP(Group!$B8,PL_NG!$C:$C,PL_NG!Y:Y)+_xlfn.XLOOKUP(Group!$B8,PL_UK!$C:$C,PL_UK!Y:Y)+_xlfn.XLOOKUP(Group!$B8,PL_UAE!$C:$C,PL_UAE!Y:Y)),0) -> -6602168.5 | Y8: =IF(Y$3<=Summary!$C$2,(_xlfn.XLOOKUP(Group!$B8,PL_NG!$C:$C,PL_NG!Z:Z)+_xlfn.XLOOKUP(Group!$B8,PL_UK!$C:$C,PL_UK!Z:Z)+_xlfn.XLOOKUP(Group!$B8,PL_UAE!$C:$C,PL_UAE!Z:Z)),0) -> -6817841.1 | Z8: =IF(Z$3<=Summary!$C$2,(_xlfn.XLOOKUP(Group!$B8,PL_NG!$C:$C,PL_NG!AA:AA)+_xlfn.XLOOKUP(Group!$B8,PL_UK!$C:$C,PL_UK!AA:AA)+_xlfn.XLOOKUP(Group!$B8,PL_UAE!$C:$C,PL_UAE!AA:AA)),0) -> -6866043 | AA8: =IF(AA$3<=Summary!$C$2,(_xlfn.XLOOKUP(Group!$B8,PL_NG!$C:$C,PL_NG!AB:AB)+_xlfn.XLOOKUP(Group!$B8,PL_UK!$C:$C,PL_UK!AB:AB)+_xlfn.XLOOKUP(Group!$B8,PL_UAE!$C:$C,PL_UAE!AB:AB)),0) -> -12427212 | AB8: =IF(AB$3<=Summary!$C$2,(_xlfn.XLOOKUP(Group!$B8,PL_NG!$C:$C,PL_NG!AC:AC)+_xlfn.XLOOKUP(Group!$B8,PL_UK!$C:$C,PL_UK!AC:AC)+_xlfn.XLOOKUP(Group!$B8,PL_UAE!$C:$C,PL_UAE!AC:AC)),0) -> -12540619 | AC8: =IF(AC$3<=Summary!$C$2,(_xlfn.XLOOKUP(Group!$B8,PL_NG!$C:$C,PL_NG!AD:AD)+_xlfn.XLOOKUP(Group!$B8,PL_UK!$C:$C,PL_UK!AD:AD)+_xlfn.XLOOKUP(Group!$B8,PL_UAE!$C:$C,PL_UAE!AD:AD)),0) -> -12323423 | AD8: =IF(AD$3<=Summary!$C$2,(_xlfn.XLOOKUP(Group!$B8,PL_NG!$C:$C,PL_NG!AE:AE)+_xlfn.XLOOKUP(Group!$B8,PL_UK!$C:$C,PL_UK!AE:AE)+_xlfn.XLOOKUP(Group!$B8,PL_UAE!$C:$C,PL_UAE!AE:AE)),0) -> -12547814 | AE8: =IF(AE$3<=Summary!$C$2,(_xlfn.XLOOKUP(Group!$B8,PL_NG!$C:$C,PL_NG!AF:AF)+_xlfn.XLOOKUP(Group!$B8,PL_UK!$C:$C,PL_UK!AF:AF)+_xlfn.XLOOKUP(Group!$B8,PL_UAE!$C:$C,PL_UAE!AF:AF)),0) -> 0 | AF8: =IF(AF$3<=Summary!$C$2,(_xlfn.XLOOKUP(Group!$B8,PL_NG!$C:$C,PL_NG!AG:AG)+_xlfn.XLOOKUP(Group!$B8,PL_UK!$C:$C,PL_UK!AG:AG)+_xlfn.XLOOKUP(Group!$B8,PL_UAE!$C:$C,PL_UAE!AG:AG)),0) -> 0 | AG8: =IF(AG$3<=Summary!$C$2,(_xlfn.XLOOKUP(Group!$B8,PL_NG!$C:$C,PL_NG!AH:AH)+_xlfn.XLOOKUP(Group!$B8,PL_UK!$C:$C,PL_UK!AH:AH)+_xlfn.XLOOKUP(Group!$B8,PL_UAE!$C:$C,PL_UAE!AH:AH)),0) -> 0 | AH8: =IF(AH$3<=Summary!$C$2,(_xlfn.XLOOKUP(Group!$B8,PL_NG!$C:$C,PL_NG!AI:AI)+_xlfn.XLOOKUP(Group!$B8,PL_UK!$C:$C,PL_UK!AI:AI)+_xlfn.XLOOKUP(Group!$B8,PL_UAE!$C:$C,PL_UAE!AI:AI)),0) -> 0 | AI8: =IF(AI$3<=Summary!$C$2,(_xlfn.XLOOKUP(Group!$B8,PL_NG!$C:$C,PL_NG!AJ:AJ)+_xlfn.XLOOKUP(Group!$B8,PL_UK!$C:$C,PL_UK!AJ:AJ)+_xlfn.XLOOKUP(Group!$B8,PL_UAE!$C:$C,PL_UAE!AJ:AJ)),0) -> 0 | AJ8: =IF(AJ$3<=Summary!$C$2,(_xlfn.XLOOKUP(Group!$B8,PL_NG!$C:$C,PL_NG!AK:AK)+_xlfn.XLOOKUP(Group!$B8,PL_UK!$C:$C,PL_UK!AK:AK)+_xlfn.XLOOKUP(Group!$B8,PL_UAE!$C:$C,PL_UAE!AK:AK)),0) -> 0 | AK8: =IF(AK$3<=Summary!$C$2,(_xlfn.XLOOKUP(Group!$B8,PL_NG!$C:$C,PL_NG!AL:AL)+_xlfn.XLOOKUP(Group!$B8,PL_UK!$C:$C,PL_UK!AL:AL)+_xlfn.XLOOKUP(Group!$B8,PL_UAE!$C:$C,PL_UAE!AL:AL)),0) -> 0 | AL8: =IF(AL$3<=Summary!$C$2,(_xlfn.XLOOKUP(Group!$B8,PL_NG!$C:$C,PL_NG!AM:AM)+_xlfn.XLOOKUP(Group!$B8,PL_UK!$C:$C,PL_UK!AM:AM)+_xlfn.XLOOKUP(Group!$B8,PL_UAE!$C:$C,PL_UAE!AM:AM)),0) -> 0
B9: TOTAL INTEREST EXPENSES | C9: =IF(C$3<=Summary!$C$2,(_xlfn.XLOOKUP(Group!$B9,PL_NG!$C:$C,PL_NG!D:D)+_xlfn.XLOOKUP(Group!$B9,PL_UK!$C:$C,PL_UK!D:D)+_xlfn.XLOOKUP(Group!$B9,PL_UAE!$C:$C,PL_UAE!D:D)),0) -> 0 | D9: =IF(D$3<=Summary!$C$2,(_xlfn.XLOOKUP(Group!$B9,PL_NG!$C:$C,PL_NG!E:E)+_xlfn.XLOOKUP(Group!$B9,PL_UK!$C:$C,PL_UK!E:E)+_xlfn.XLOOKUP(Group!$B9,PL_UAE!$C:$C,PL_UAE!E:E)),0) -> -321442.6 | E9: =IF(E$3<=Summary!$C$2,(_xlfn.XLOOKUP(Group!$B9,PL_NG!$C:$C,PL_NG!F:F)+_xlfn.XLOOKUP(Group!$B9,PL_UK!$C:$C,PL_UK!F:F)+_xlfn.XLOOKUP(Group!$B9,PL_UAE!$C:$C,PL_UAE!F:F)),0) -> -1014508.5 | F9: =IF(F$3<=Summary!$C$2,(_xlfn.XLOOKUP(Group!$B9,PL_NG!$C:$C,PL_NG!G:G)+_xlfn.XLOOKUP(Group!$B9,PL_UK!$C:$C,PL_UK!G:G)+_xlfn.XLOOKUP(Group!$B9,PL_UAE!$C:$C,PL_UAE!G:G)),0) -> 0 | G9: =IF(G$3<=Summary!$C$2,(_xlfn.XLOOKUP(Group!$B9,PL_NG!$C:$C,PL_NG!H:H)+_xlfn.XLOOKUP(Group!$B9,PL_UK!$C:$C,PL_UK!H:H)+_xlfn.XLOOKUP(Group!$B9,PL_UAE!$C:$C,PL_UAE!H:H)),0) -> 0 | H9: =IF(H$3<=Summary!$C$2,(_xlfn.XLOOKUP(Group!$B9,PL_NG!$C:$C,PL_NG!I:I)+_xlfn.XLOOKUP(Group!$B9,PL_UK!$C:$C,PL_UK!I:I)+_xlfn.XLOOKUP(Group!$B9,PL_UAE!$C:$C,PL_UAE!I:I)),0) -> 0 | I9: =IF(I$3<=Summary!$C$2,(_xlfn.XLOOKUP(Group!$B9,PL_NG!$C:$C,PL_NG!J:J)+_xlfn.XLOOKUP(Group!$B9,PL_UK!$C:$C,PL_UK!J:J)+_xlfn.XLOOKUP(Group!$B9,PL_UAE!$C:$C,PL_UAE!J:J)),0) -> 0 | J9: =IF(J$3<=Summary!$C$2,(_xlfn.XLOOKUP(Group!$B9,PL_NG!$C:$C,PL_NG!K:K)+_xlfn.XLOOKUP(Group!$B9,PL_UK!$C:$C,PL_UK!K:K)+_xlfn.XLOOKUP(Group!$B9,PL_UAE!$C:$C,PL_UAE!K:K)),0) -> 0 | K9: =IF(K$3<=Summary!$C$2,(_xlfn.XLOOKUP(Group!$B9,PL_NG!$C:$C,PL_NG!L:L)+_xlfn.XLOOKUP(Group!$B9,PL_UK!$C:$C,PL_UK!L:L)+_xlfn.XLOOKUP(Group!$B9,PL_UAE!$C:$C,PL_UAE!L:L)),0) -> 0 | L9: =IF(L$3<=Summary!$C$2,(_xlfn.XLOOKUP(Group!$B9,PL_NG!$C:$C,PL_NG!M:M)+_xlfn.XLOOKUP(Group!$B9,PL_UK!$C:$C,PL_UK!M:M)+_xlfn.XLOOKUP(Group!$B9,PL_UAE!$C:$C,PL_UAE!M:M)),0) -> 0 | M9: =IF(M$3<=Summary!$C$2,(_xlfn.XLOOKUP(Group!$B9,PL_NG!$C:$C,PL_NG!N:N)+_xlfn.XLOOKUP(Group!$B9,PL_UK!$C:$C,PL_UK!N:N)+_xlfn.XLOOKUP(Group!$B9,PL_UAE!$C:$C,PL_UAE!N:N)),0) -> 0 | N9: =IF(N$3<=Summary!$C$2,(_xlfn.XLOOKUP(Group!$B9,PL_NG!$C:$C,PL_NG!O:O)+_xlfn.XLOOKUP(Group!$B9,PL_UK!$C:$C,PL_UK!O:O)+_xlfn.XLOOKUP(Group!$B9,PL_UAE!$C:$C,PL_UAE!O:O)),0) -> 0 | O9: =IF(O$3<=Summary!$C$2,(_xlfn.XLOOKUP(Group!$B9,PL_NG!$C:$C,PL_NG!P:P)+_xlfn.XLOOKUP(Group!$B9,PL_UK!$C:$C,PL_UK!P:P)+_xlfn.XLOOKUP(Group!$B9,PL_UAE!$C:$C,PL_UAE!P:P)),0) -> 0 | P9: =IF(P$3<=Summary!$C$2,(_xlfn.XLOOKUP(Group!$B9,PL_NG!$C:$C,PL_NG!Q:Q)+_xlfn.XLOOKUP(Group!$B9,PL_UK!$C:$C,PL_UK!Q:Q)+_xlfn.XLOOKUP(Group!$B9,PL_UAE!$C:$C,PL_UAE!Q:Q)),0) -> 0 | Q9: =IF(Q$3<=Summary!$C$2,(_xlfn.XLOOKUP(Group!$B9,PL_NG!$C:$C,PL_NG!R:R)+_xlfn.XLOOKUP(Group!$B9,PL_UK!$C:$C,PL_UK!R:R)+_xlfn.XLOOKUP(Group!$B9,PL_UAE!$C:$C,PL_UAE!R:R)),0) -> 0 | R9: =IF(R$3<=Summary!$C$2,(_xlfn.XLOOKUP(Group!$B9,PL_NG!$C:$C,PL_NG!S:S)+_xlfn.XLOOKUP(Group!$B9,PL_UK!$C:$C,PL_UK!S:S)+_xlfn.XLOOKUP(Group!$B9,PL_UAE!$C:$C,PL_UAE!S:S)),0) -> 0 | S9: =IF(S$3<=Summary!$C$2,(_xlfn.XLOOKUP(Group!$B9,PL_NG!$C:$C,PL_NG!T:T)+_xlfn.XLOOKUP(Group!$B9,PL_UK!$C:$C,PL_UK!T:T)+_xlfn.XLOOKUP(Group!$B9,PL_UAE!$C:$C,PL_UAE!T:T)),0) -> -144180000 | T9: =IF(T$3<=Summary!$C$2,(_xlfn.XLOOKUP(Group!$B9,PL_NG!$C:$C,PL_NG!U:U)+_xlfn.XLOOKUP(Group!$B9,PL_UK!$C:$C,PL_UK!U:U)+_xlfn.XLOOKUP(Group!$B9,PL_UAE!$C:$C,PL_UAE!U:U)),0) -> 0 | U9: =IF(U$3<=Summary!$C$2,(_xlfn.XLOOKUP(Group!$B9,PL_NG!$C:$C,PL_NG!V:V)+_xlfn.XLOOKUP(Group!$B9,PL_UK!$C:$C,PL_UK!V:V)+_xlfn.XLOOKUP(Group!$B9,PL_UAE!$C:$C,PL_UAE!V:V)),0) -> 0 | V9: =IF(V$3<=Summary!$C$2,(_xlfn.XLOOKUP(Group!$B9,PL_NG!$C:$C,PL_NG!W:W)+_xlfn.XLOOKUP(Group!$B9,PL_UK!$C:$C,PL_UK!W:W)+_xlfn.XLOOKUP(Group!$B9,PL_UAE!$C:$C,PL_UAE!W:W)),0) -> 0 | W9: =IF(W$3<=Summary!$C$2,(_xlfn.XLOOKUP(Group!$B9,PL_NG!$C:$C,PL_NG!X:X)+_xlfn.XLOOKUP(Group!$B9,PL_UK!$C:$C,PL_UK!X:X)+_xlfn.XLOOKUP(Group!$B9,PL_UAE!$C:$C,PL_UAE!X:X)),0) -> 0 | X9: =IF(X$3<=Summary!$C$2,(_xlfn.XLOOKUP(Group!$B9,PL_NG!$C:$C,PL_NG!Y:Y)+_xlfn.XLOOKUP(Group!$B9,PL_UK!$C:$C,PL_UK!Y:Y)+_xlfn.XLOOKUP(Group!$B9,PL_UAE!$C:$C,PL_UAE!Y:Y)),0) -> -134088144 | Y9: =IF(Y$3<=Summary!$C$2,(_xlfn.XLOOKUP(Group!$B9,PL_NG!$C:$C,PL_NG!Z:Z)+_xlfn.XLOOKUP(Group!$B9,PL_UK!$C:$C,PL_UK!Z:Z)+_xlfn.XLOOKUP(Group!$B9,PL_UAE!$C:$C,PL_UAE!Z:Z)),0) -> 0 | Z9: =IF(Z$3<=Summary!$C$2,(_xlfn.XLOOKUP(Group!$B9,PL_NG!$C:$C,PL_NG!AA:AA)+_xlfn.XLOOKUP(Group!$B9,PL_UK!$C:$C,PL_UK!AA:AA)+_xlfn.XLOOKUP(Group!$B9,PL_UAE!$C:$C,PL_UAE!AA:AA)),0) -> 0 | AA9: =IF(AA$3<=Summary!$C$2,(_xlfn.XLOOKUP(Group!$B9,PL_NG!$C:$C,PL_NG!AB:AB)+_xlfn.XLOOKUP(Group!$B9,PL_UK!$C:$C,PL_UK!AB:AB)+_xlfn.XLOOKUP(Group!$B9,PL_UAE!$C:$C,PL_UAE!AB:AB)),0) -> 0 | AB9: =IF(AB$3<=Summary!$C$2,(_xlfn.XLOOKUP(Group!$B9,PL_NG!$C:$C,PL_NG!AC:AC)+_xlfn.XLOOKUP(Group!$B9,PL_UK!$C:$C,PL_UK!AC:AC)+_xlfn.XLOOKUP(Group!$B9,PL_UAE!$C:$C,PL_UAE!AC:AC)),0) -> 0 | AC9: =IF(AC$3<=Summary!$C$2,(_xlfn.XLOOKUP(Group!$B9,PL_NG!$C:$C,PL_NG!AD:AD)+_xlfn.XLOOKUP(Group!$B9,PL_UK!$C:$C,PL_UK!AD:AD)+_xlfn.XLOOKUP(Group!$B9,PL_UAE!$C:$C,PL_UAE!AD:AD)),0) -> 0 | AD9: =IF(AD$3<=Summary!$C$2,(_xlfn.XLOOKUP(Group!$B9,PL_NG!$C:$C,PL_NG!AE:AE)+_xlfn.XLOOKUP(Group!$B9,PL_UK!$C:$C,PL_UK!AE:AE)+_xlfn.XLOOKUP(Group!$B9,PL_UAE!$C:$C,PL_UAE!AE:AE)),0) -> 0 | AE9: =IF(AE$3<=Summary!$C$2,(_xlfn.XLOOKUP(Group!$B9,PL_NG!$C:$C,PL_NG!AF:AF)+_xlfn.XLOOKUP(Group!$B9,PL_UK!$C:$C,PL_UK!AF:AF)+_xlfn.XLOOKUP(Group!$B9,PL_UAE!$C:$C,PL_UAE!AF:AF)),0) -> 0 | AF9: =IF(AF$3<=Summary!$C$2,(_xlfn.XLOOKUP(Group!$B9,PL_NG!$C:$C,PL_NG!AG:AG)+_xlfn.XLOOKUP(Group!$B9,PL_UK!$C:$C,PL_UK!AG:AG)+_xlfn.XLOOKUP(Group!$B9,PL_UAE!$C:$C,PL_UAE!AG:AG)),0) -> 0 | AG9: =IF(AG$3<=Summary!$C$2,(_xlfn.XLOOKUP(Group!$B9,PL_NG!$C:$C,PL_NG!AH:AH)+_xlfn.XLOOKUP(Group!$B9,PL_UK!$C:$C,PL_UK!AH:AH)+_xlfn.XLOOKUP(Group!$B9,PL_UAE!$C:$C,PL_UAE!AH:AH)),0) -> 0 | AH9: =IF(AH$3<=Summary!$C$2,(_xlfn.XLOOKUP(Group!$B9,PL_NG!$C:$C,PL_NG!AI:AI)+_xlfn.XLOOKUP(Group!$B9,PL_UK!$C:$C,PL_UK!AI:AI)+_xlfn.XLOOKUP(Group!$B9,PL_UAE!$C:$C,PL_UAE!AI:AI)),0) -> 0 | AI9: =IF(AI$3<=Summary!$C$2,(_xlfn.XLOOKUP(Group!$B9,PL_NG!$C:$C,PL_NG!AJ:AJ)+_xlfn.XLOOKUP(Group!$B9,PL_UK!$C:$C,PL_UK!AJ:AJ)+_xlfn.XLOOKUP(Group!$B9,PL_UAE!$C:$C,PL_UAE!AJ:AJ)),0) -> 0 | AJ9: =IF(AJ$3<=Summary!$C$2,(_xlfn.XLOOKUP(Group!$B9,PL_NG!$C:$C,PL_NG!AK:AK)+_xlfn.XLOOKUP(Group!$B9,PL_UK!$C:$C,PL_UK!AK:AK)+_xlfn.XLOOKUP(Group!$B9,PL_UAE!$C:$C,PL_UAE!AK:AK)),0) -> 0 | AK9: =IF(AK$3<=Summary!$C$2,(_xlfn.XLOOKUP(Group!$B9,PL_NG!$C:$C,PL_NG!AL:AL)+_xlfn.XLOOKUP(Group!$B9,PL_UK!$C:$C,PL_UK!AL:AL)+_xlfn.XLOOKUP(Group!$B9,PL_UAE!$C:$C,PL_UAE!AL:AL)),0) -> 0 | AL9: =IF(AL$3<=Summary!$C$2,(_xlfn.XLOOKUP(Group!$B9,PL_NG!$C:$C,PL_NG!AM:AM)+_xlfn.XLOOKUP(Group!$B9,PL_UK!$C:$C,PL_UK!AM:AM)+_xlfn.XLOOKUP(Group!$B9,PL_UAE!$C:$C,PL_UAE!AM:AM)),0) -> 0
B10: TOTAL TAX EXPENSES | C10: =IF(C$3<=Summary!$C$2,(_xlfn.XLOOKUP(Group!$B10,PL_NG!$C:$C,PL_NG!D:D)+_xlfn.XLOOKUP(Group!$B10,PL_UK!$C:$C,PL_UK!D:D)+_xlfn.XLOOKUP(Group!$B10,PL_UAE!$C:$C,PL_UAE!D:D)),0) -> 0 | D10: =IF(D$3<=Summary!$C$2,(_xlfn.XLOOKUP(Group!$B10,PL_NG!$C:$C,PL_NG!E:E)+_xlfn.XLOOKUP(Group!$B10,PL_UK!$C:$C,PL_UK!E:E)+_xlfn.XLOOKUP(Group!$B10,PL_UAE!$C:$C,PL_UAE!E:E)),0) -> 0 | E10: =IF(E$3<=Summary!$C$2,(_xlfn.XLOOKUP(Group!$B10,PL_NG!$C:$C,PL_NG!F:F)+_xlfn.XLOOKUP(Group!$B10,PL_UK!$C:$C,PL_UK!F:F)+_xlfn.XLOOKUP(Group!$B10,PL_UAE!$C:$C,PL_UAE!F:F)),0) -> 0 | F10: =IF(F$3<=Summary!$C$2,(_xlfn.XLOOKUP(Group!$B10,PL_NG!$C:$C,PL_NG!G:G)+_xlfn.XLOOKUP(Group!$B10,PL_UK!$C:$C,PL_UK!G:G)+_xlfn.XLOOKUP(Group!$B10,PL_UAE!$C:$C,PL_UAE!G:G)),0) -> 0 | G10: =IF(G$3<=Summary!$C$2,(_xlfn.XLOOKUP(Group!$B10,PL_NG!$C:$C,PL_NG!H:H)+_xlfn.XLOOKUP(Group!$B10,PL_UK!$C:$C,PL_UK!H:H)+_xlfn.XLOOKUP(Group!$B10,PL_UAE!$C:$C,PL_UAE!H:H)),0) -> 0 | H10: =IF(H$3<=Summary!$C$2,(_xlfn.XLOOKUP(Group!$B10,PL_NG!$C:$C,PL_NG!I:I)+_xlfn.XLOOKUP(Group!$B10,PL_UK!$C:$C,PL_UK!I:I)+_xlfn.XLOOKUP(Group!$B10,PL_UAE!$C:$C,PL_UAE!I:I)),0) -> 0 | I10: =IF(I$3<=Summary!$C$2,(_xlfn.XLOOKUP(Group!$B10,PL_NG!$C:$C,PL_NG!J:J)+_xlfn.XLOOKUP(Group!$B10,PL_UK!$C:$C,PL_UK!J:J)+_xlfn.XLOOKUP(Group!$B10,PL_UAE!$C:$C,PL_UAE!J:J)),0) -> 0 | J10: =IF(J$3<=Summary!$C$2,(_xlfn.XLOOKUP(Group!$B10,PL_NG!$C:$C,PL_NG!K:K)+_xlfn.XLOOKUP(Group!$B10,PL_UK!$C:$C,PL_UK!K:K)+_xlfn.XLOOKUP(Group!$B10,PL_UAE!$C:$C,PL_UAE!K:K)),0) -> 0 | K10: =IF(K$3<=Summary!$C$2,(_xlfn.XLOOKUP(Group!$B10,PL_NG!$C:$C,PL_NG!L:L)+_xlfn.XLOOKUP(Group!$B10,PL_UK!$C:$C,PL_UK!L:L)+_xlfn.XLOOKUP(Group!$B10,PL_UAE!$C:$C,PL_UAE!L:L)),0) -> 0 | L10: =IF(L$3<=Summary!$C$2,(_xlfn.XLOOKUP(Group!$B10,PL_NG!$C:$C,PL_NG!M:M)+_xlfn.XLOOKUP(Group!$B10,PL_UK!$C:$C,PL_UK!M:M)+_xlfn.XLOOKUP(Group!$B10,PL_UAE!$C:$C,PL_UAE!M:M)),0) -> 0 | M10: =IF(M$3<=Summary!$C$2,(_xlfn.XLOOKUP(Group!$B10,PL_NG!$C:$C,PL_NG!N:N)+_xlfn.XLOOKUP(Group!$B10,PL_UK!$C:$C,PL_UK!N:N)+_xlfn.XLOOKUP(Group!$B10,PL_UAE!$C:$C,PL_UAE!N:N)),0) -> 0 | N10: =IF(N$3<=Summary!$C$2,(_xlfn.XLOOKUP(Group!$B10,PL_NG!$C:$C,PL_NG!O:O)+_xlfn.XLOOKUP(Group!$B10,PL_UK!$C:$C,PL_UK!O:O)+_xlfn.XLOOKUP(Group!$B10,PL_UAE!$C:$C,PL_UAE!O:O)),0) -> -17250130 | O10: =IF(O$3<=Summary!$C$2,(_xlfn.XLOOKUP(Group!$B10,PL_NG!$C:$C,PL_NG!P:P)+_xlfn.XLOOKUP(Group!$B10,PL_UK!$C:$C,PL_UK!P:P)+_xlfn.XLOOKUP(Group!$B10,PL_UAE!$C:$C,PL_UAE!P:P)),0) -> 0 | P10: =IF(P$3<=Summary!$C$2,(_xlfn.XLOOKUP(Group!$B10,PL_NG!$C:$C,PL_NG!Q:Q)+_xlfn.XLOOKUP(Group!$B10,PL_UK!$C:$C,PL_UK!Q:Q)+_xlfn.XLOOKUP(Group!$B10,PL_UAE!$C:$C,PL_UAE!Q:Q)),0) -> 0 | Q10: =IF(Q$3<=Summary!$C$2,(_xlfn.XLOOKUP(Group!$B10,PL_NG!$C:$C,PL_NG!R:R)+_xlfn.XLOOKUP(Group!$B10,PL_UK!$C:$C,PL_UK!R:R)+_xlfn.XLOOKUP(Group!$B10,PL_UAE!$C:$C,PL_UAE!R:R)),0) -> 0 | R10: =IF(R$3<=Summary!$C$2,(_xlfn.XLOOKUP(Group!$B10,PL_NG!$C:$C,PL_NG!S:S)+_xlfn.XLOOKUP(Group!$B10,PL_UK!$C:$C,PL_UK!S:S)+_xlfn.XLOOKUP(Group!$B10,PL_UAE!$C:$C,PL_UAE!S:S)),0) -> 0 | S10: =IF(S$3<=Summary!$C$2,(_xlfn.XLOOKUP(Group!$B10,PL_NG!$C:$C,PL_NG!T:T)+_xlfn.XLOOKUP(Group!$B10,PL_UK!$C:$C,PL_UK!T:T)+_xlfn.XLOOKUP(Group!$B10,PL_UAE!$C:$C,PL_UAE!T:T)),0) -> 0 | T10: =IF(T$3<=Summary!$C$2,(_xlfn.XLOOKUP(Group!$B10,PL_NG!$C:$C,PL_NG!U:U)+_xlfn.XLOOKUP(Group!$B10,PL_UK!$C:$C,PL_UK!U:U)+_xlfn.XLOOKUP(Group!$B10,PL_UAE!$C:$C,PL_UAE!U:U)),0) -> 0 | U10: =IF(U$3<=Summary!$C$2,(_xlfn.XLOOKUP(Group!$B10,PL_NG!$C:$C,PL_NG!V:V)+_xlfn.XLOOKUP(Group!$B10,PL_UK!$C:$C,PL_UK!V:V)+_xlfn.XLOOKUP(Group!$B10,PL_UAE!$C:$C,PL_UAE!V:V)),0) -> 0 | V10: =IF(V$3<=Summary!$C$2,(_xlfn.XLOOKUP(Group!$B10,PL_NG!$C:$C,PL_NG!W:W)+_xlfn.XLOOKUP(Group!$B10,PL_UK!$C:$C,PL_UK!W:W)+_xlfn.XLOOKUP(Group!$B10,PL_UAE!$C:$C,PL_UAE!W:W)),0) -> 0 | W10: =IF(W$3<=Summary!$C$2,(_xlfn.XLOOKUP(Group!$B10,PL_NG!$C:$C,PL_NG!X:X)+_xlfn.XLOOKUP(Group!$B10,PL_UK!$C:$C,PL_UK!X:X)+_xlfn.XLOOKUP(Group!$B10,PL_UAE!$C:$C,PL_UAE!X:X)),0) -> 0 | X10: =IF(X$3<=Summary!$C$2,(_xlfn.XLOOKUP(Group!$B10,PL_NG!$C:$C,PL_NG!Y:Y)+_xlfn.XLOOKUP(Group!$B10,PL_UK!$C:$C,PL_UK!Y:Y)+_xlfn.XLOOKUP(Group!$B10,PL_UAE!$C:$C,PL_UAE!Y:Y)),0) -> 0 | Y10: =IF(Y$3<=Summary!$C$2,(_xlfn.XLOOKUP(Group!$B10,PL_NG!$C:$C,PL_NG!Z:Z)+_xlfn.XLOOKUP(Group!$B10,PL_UK!$C:$C,PL_UK!Z:Z)+_xlfn.XLOOKUP(Group!$B10,PL_UAE!$C:$C,PL_UAE!Z:Z)),0) -> 0 | Z10: =IF(Z$3<=Summary!$C$2,(_xlfn.XLOOKUP(Group!$B10,PL_NG!$C:$C,PL_NG!AA:AA)+_xlfn.XLOOKUP(Group!$B10,PL_UK!$C:$C,PL_UK!AA:AA)+_xlfn.XLOOKUP(Group!$B10,PL_UAE!$C:$C,PL_UAE!AA:AA)),0) -> 0 | AA10: =IF(AA$3<=Summary!$C$2,(_xlfn.XLOOKUP(Group!$B10,PL_NG!$C:$C,PL_NG!AB:AB)+_xlfn.XLOOKUP(Group!$B10,PL_UK!$C:$C,PL_UK!AB:AB)+_xlfn.XLOOKUP(Group!$B10,PL_UAE!$C:$C,PL_UAE!AB:AB)),0) -> 0 | AB10: =IF(AB$3<=Summary!$C$2,(_xlfn.XLOOKUP(Group!$B10,PL_NG!$C:$C,PL_NG!AC:AC)+_xlfn.XLOOKUP(Group!$B10,PL_UK!$C:$C,PL_UK!AC:AC)+_xlfn.XLOOKUP(Group!$B10,PL_UAE!$C:$C,PL_UAE!AC:AC)),0) -> 0 | AC10: =IF(AC$3<=Summary!$C$2,(_xlfn.XLOOKUP(Group!$B10,PL_NG!$C:$C,PL_NG!AD:AD)+_xlfn.XLOOKUP(Group!$B10,PL_UK!$C:$C,PL_UK!AD:AD)+_xlfn.XLOOKUP(Group!$B10,PL_UAE!$C:$C,PL_UAE!AD:AD)),0) -> 0 | AD10: =IF(AD$3<=Summary!$C$2,(_xlfn.XLOOKUP(Group!$B10,PL_NG!$C:$C,PL_NG!AE:AE)+_xlfn.XLOOKUP(Group!$B10,PL_UK!$C:$C,PL_UK!AE:AE)+_xlfn.XLOOKUP(Group!$B10,PL_UAE!$C:$C,PL_UAE!AE:AE)),0) -> 0 | AE10: =IF(AE$3<=Summary!$C$2,(_xlfn.XLOOKUP(Group!$B10,PL_NG!$C:$C,PL_NG!AF:AF)+_xlfn.XLOOKUP(Group!$B10,PL_UK!$C:$C,PL_UK!AF:AF)+_xlfn.XLOOKUP(Group!$B10,PL_UAE!$C:$C,PL_UAE!AF:AF)),0) -> 0 | AF10: =IF(AF$3<=Summary!$C$2,(_xlfn.XLOOKUP(Group!$B10,PL_NG!$C:$C,PL_NG!AG:AG)+_xlfn.XLOOKUP(Group!$B10,PL_UK!$C:$C,PL_UK!AG:AG)+_xlfn.XLOOKUP(Group!$B10,PL_UAE!$C:$C,PL_UAE!AG:AG)),0) -> 0 | AG10: =IF(AG$3<=Summary!$C$2,(_xlfn.XLOOKUP(Group!$B10,PL_NG!$C:$C,PL_NG!AH:AH)+_xlfn.XLOOKUP(Group!$B10,PL_UK!$C:$C,PL_UK!AH:AH)+_xlfn.XLOOKUP(Group!$B10,PL_UAE!$C:$C,PL_UAE!AH:AH)),0) -> 0 | AH10: =IF(AH$3<=Summary!$C$2,(_xlfn.XLOOKUP(Group!$B10,PL_NG!$C:$C,PL_NG!AI:AI)+_xlfn.XLOOKUP(Group!$B10,PL_UK!$C:$C,PL_UK!AI:AI)+_xlfn.XLOOKUP(Group!$B10,PL_UAE!$C:$C,PL_UAE!AI:AI)),0) -> 0 | AI10: =IF(AI$3<=Summary!$C$2,(_xlfn.XLOOKUP(Group!$B10,PL_NG!$C:$C,PL_NG!AJ:AJ)+_xlfn.XLOOKUP(Group!$B10,PL_UK!$C:$C,PL_UK!AJ:AJ)+_xlfn.XLOOKUP(Group!$B10,PL_UAE!$C:$C,PL_UAE!AJ:AJ)),0) -> 0 | AJ10: =IF(AJ$3<=Summary!$C$2,(_xlfn.XLOOKUP(Group!$B10,PL_NG!$C:$C,PL_NG!AK:AK)+_xlfn.XLOOKUP(Group!$B10,PL_UK!$C:$C,PL_UK!AK:AK)+_xlfn.XLOOKUP(Group!$B10,PL_UAE!$C:$C,PL_UAE!AK:AK)),0) -> 0 | AK10: =IF(AK$3<=Summary!$C$2,(_xlfn.XLOOKUP(Group!$B10,PL_NG!$C:$C,PL_NG!AL:AL)+_xlfn.XLOOKUP(Group!$B10,PL_UK!$C:$C,PL_UK!AL:AL)+_xlfn.XLOOKUP(Group!$B10,PL_UAE!$C:$C,PL_UAE!AL:AL)),0) -> 0 | AL10: =IF(AL$3<=Summary!$C$2,(_xlfn.XLOOKUP(Group!$B10,PL_NG!$C:$C,PL_NG!AM:AM)+_xlfn.XLOOKUP(Group!$B10,PL_UK!$C:$C,PL_UK!AM:AM)+_xlfn.XLOOKUP(Group!$B10,PL_UAE!$C:$C,PL_UAE!AM:AM)),0) -> 0
